Workbook

Sheet Output BDV
F3: =+SUM(F5:F1000) -> 9.4862799e-08 | G3: =+SUM(G5:G1000) -> 6 | H3: =+SUM(H5:H1000) -> 6.0000002 | M3: 673226.64
A4: SP/CE | B4: ricavi o costi | C4: Ricla MG esteso | D4: Key | E4: Account | F4: CVS | G4: De Giorgi | H4: Total
A5: SP | C5: Intangible Assets | D5: =+_xlfn.NUMBERVALUE(LEFT(E5,6)) -> 100201 | E5: 100201 - Costi Di Impianto E Ampliamento | F5: =+_xlfn.XLOOKUP(D5,CVS!E:E,CVS!I:I,0) -> 4214.29 | G5: =+SUMIFS('De Giorgi BDV'!C:C,'De Giorgi BDV'!D:D,D5) -> 0 | H5: =+F5+G5 -> 4214.29 | I5: =+_xlfn.XLOOKUP(D5,[1]BDV!$F:$F,[1]BDV!$AI:$AI) -> 4214.29 | J5: =+H5-I5 -> 0
A6: SP | B6: 0 | C6: Intangible Assets | D6: =+_xlfn.NUMBERVALUE(LEFT(E6,6)) -> 100203 | E6: 100203 - Software | F6: =+_xlfn.XLOOKUP(D6,CVS!E:E,CVS!I:I,0) -> 4758632.6 | G6: =+SUMIFS('De Giorgi BDV'!C:C,'De Giorgi BDV'!D:D,D6) -> 33076 | H6: =+F6+G6 -> 4791708.6 | I6: =+_xlfn.XLOOKUP(D6,[1]BDV!$F:$F,[1]BDV!$AI:$AI) -> 4791708.6 | J6: =+H6-I6 -> 0
A7: SP | B7: 0 | C7: Intangible Assets | D7: =+_xlfn.NUMBERVALUE(LEFT(E7,6)) -> 100205 | E7: 100205 - Avviamento | F7: =+_xlfn.XLOOKUP(D7,CVS!E:E,CVS!I:I,0) -> 50053945 | G7: =+SUMIFS('De Giorgi BDV'!C:C,'De Giorgi BDV'!D:D,D7) -> 0 | H7: =+F7+G7 -> 50053945 | I7: =+_xlfn.XLOOKUP(D7,[1]BDV!$F:$F,[1]BDV!$AI:$AI) -> 50053945 | J7: =+H7-I7 -> 0
A8: SP | B8: 0 | C8: Intangible Assets | D8: =+_xlfn.NUMBERVALUE(LEFT(E8,6)) -> 100207 | E8: 100207 - Lavori Straor. Su Beni Di Terzi | F8: =+_xlfn.XLOOKUP(D8,CVS!E:E,CVS!I:I,0) -> 1.2097657e+08 | G8: =+SUMIFS('De Giorgi BDV'!C:C,'De Giorgi BDV'!D:D,D8) -> 1044800.9 | H8: =+F8+G8 -> 1.2202137e+08 | I8: =+_xlfn.XLOOKUP(D8,[1]BDV!$F:$F,[1]BDV!$AI:$AI) -> 1.2202137e+08 | J8: =+H8-I8 -> 0
A9: SP | B9: 0 | C9: Intangible Assets | D9: =+_xlfn.NUMBERVALUE(LEFT(E9,6)) -> 100209 | E9: 100209 - Lavori Straor. Su Beni Di Terzi In Corso | F9: =+_xlfn.XLOOKUP(D9,CVS!E:E,CVS!I:I,0) -> 21620273 | G9: =+SUMIFS('De Giorgi BDV'!C:C,'De Giorgi BDV'!D:D,D9) -> 0 | H9: =+F9+G9 -> 21620273 | I9: =+_xlfn.XLOOKUP(D9,[1]BDV!$F:$F,[1]BDV!$AI:$AI) -> 21620273 | J9: =+H9-I9 -> 0
A10: SP | B10: 0 | C10: Intangible Assets | D10: =+_xlfn.NUMBERVALUE(LEFT(E10,6)) -> 100215 | E10: 100215 - Concessioni, Licenze E Marchi | F10: =+_xlfn.XLOOKUP(D10,CVS!E:E,CVS!I:I,0) -> 354977.91 | G10: =+SUMIFS('De Giorgi BDV'!C:C,'De Giorgi BDV'!D:D,D10) -> 0 | H10: =+F10+G10 -> 354977.91 | I10: =+_xlfn.XLOOKUP(D10,[1]BDV!$F:$F,[1]BDV!$AI:$AI) -> 354977.91 | J10: =+H10-I10 -> 0
A11: SP | B11: 0 | C11: Intangible Assets | D11: =+_xlfn.NUMBERVALUE(LEFT(E11,6)) -> 100217 | E11: 100217 - Altri Costi Ad Util. Plur. Da Amm. | F11: =+_xlfn.XLOOKUP(D11,CVS!E:E,CVS!I:I,0) -> 201871.57 | G11: =+SUMIFS('De Giorgi BDV'!C:C,'De Giorgi BDV'!D:D,D11) -> 8966.25 | H11: =+F11+G11 -> 210837.82 | I11: =+_xlfn.XLOOKUP(D11,[1]BDV!$F:$F,[1]BDV!$AI:$AI) -> 210837.82 | J11: =+H11-I11 -> 0
A12: SP | B12: 0 | C12: Intangible Assets | D12: =+_xlfn.NUMBERVALUE(LEFT(E12,6)) -> 100223 | E12: 100223 - F/Amm. Costi Impianto | F12: =+_xlfn.XLOOKUP(D12,CVS!E:E,CVS!I:I,0) -> -1496.05 | G12: =+SUMIFS('De Giorgi BDV'!C:C,'De Giorgi BDV'!D:D,D12) -> 0 | H12: =+F12+G12 -> -1496.05 | I12: =+_xlfn.XLOOKUP(D12,[1]BDV!$F:$F,[1]BDV!$AI:$AI) -> -1496.05 | J12: =+H12-I12 -> 0
A13: SP | B13: 0 | C13: Intangible Assets | D13: =+_xlfn.NUMBERVALUE(LEFT(E13,6)) -> 100225 | E13: 100225 - F/Amm Software | F13: =+_xlfn.XLOOKUP(D13,CVS!E:E,CVS!I:I,0) -> -2334868.1 | G13: =+SUMIFS('De Giorgi BDV'!C:C,'De Giorgi BDV'!D:D,D13) -> -33076 | H13: =+F13+G13 -> -2367944.1 | I13: =+_xlfn.XLOOKUP(D13,[1]BDV!$F:$F,[1]BDV!$AI:$AI) -> -2367944.1 | J13: =+H13-I13 -> 0
A14: SP | B14: 0 | C14: Intangible Assets | D14: =+_xlfn.NUMBERVALUE(LEFT(E14,6)) -> 100227 | E14: 100227 - F/Amm Avviamento | F14: =+_xlfn.XLOOKUP(D14,CVS!E:E,CVS!I:I,0) -> -8392.14 | G14: =+SUMIFS('De Giorgi BDV'!C:C,'De Giorgi BDV'!D:D,D14) -> 0 | H14: =+F14+G14 -> -8392.14 | I14: =+_xlfn.XLOOKUP(D14,[1]BDV!$F:$F,[1]BDV!$AI:$AI) -> -8392.14 | J14: =+H14-I14 -> 0
A15: SP | B15: 0 | C15: Intangible Assets | D15: =+_xlfn.NUMBERVALUE(LEFT(E15,6)) -> 100231 | E15: 100231 - F/Amm Concessioni, Licenze E Marchi | F15: =+_xlfn.XLOOKUP(D15,CVS!E:E,CVS!I:I,0) -> -260807.85 | G15: =+SUMIFS('De Giorgi BDV'!C:C,'De Giorgi BDV'!D:D,D15) -> 0 | H15: =+F15+G15 -> -260807.85 | I15: =+_xlfn.XLOOKUP(D15,[1]BDV!$F:$F,[1]BDV!$AI:$AI) -> -260807.85 | J15: =+H15-I15 -> 0
A16: SP | B16: 0 | C16: Intangible Assets | D16: =+_xlfn.NUMBERVALUE(LEFT(E16,6)) -> 100235 | E16: 100235 - F/Amm. Lav. Str. Su Beni Di Terzi | F16: =+_xlfn.XLOOKUP(D16,CVS!E:E,CVS!I:I,0) -> -43002348 | G16: =+SUMIFS('De Giorgi BDV'!C:C,'De Giorgi BDV'!D:D,D16) -> -466034.54 | H16: =+F16+G16 -> -43468383 | I16: =+_xlfn.XLOOKUP(D16,[1]BDV!$F:$F,[1]BDV!$AI:$AI) -> -43468383 | J16: =+H16-I16 -> 0
A17: SP | B17: 0 | C17: Intangible Assets | D17: =+_xlfn.NUMBERVALUE(LEFT(E17,6)) -> 100237 | E17: 100237 - F/Amm. Alt. Cost. Ad Ut. Plu. Amm. | F17: =+_xlfn.XLOOKUP(D17,CVS!E:E,CVS!I:I,0) -> -196064.56 | G17: =+SUMIFS('De Giorgi BDV'!C:C,'De Giorgi BDV'!D:D,D17) -> -8966.25 | H17: =+F17+G17 -> -205030.81 | I17: =+_xlfn.XLOOKUP(D17,[1]BDV!$F:$F,[1]BDV!$AI:$AI) -> -205030.81 | J17: =+H17-I17 -> 0
... A49: SP | B49: 0 | C49: Tangible Assets | D49: =+_xlfn.NUMBERVALUE(LEFT(E49,6)) -> 100455 | E49: 100455 - F/Amm Arredamento | F49: =+_xlfn.XLOOKUP(D49,CVS!E:E,CVS!I:I,0) -> -6367.3 | G49: =+SUMIFS('De Giorgi BDV'!C:C,'De Giorgi BDV'!D:D,D49) -> -24502.75 | H49: =+F49+G49 -> -30870.05 | I49: =+_xlfn.XLOOKUP(D49,[1]BDV!$F:$F,[1]BDV!$AI:$AI) -> -30870.05 | J49: =+H49-I49 -> 0
A50: SP | B50: FV | C50: Tangible Assets | D50: =+_xlfn.NUMBERVALUE(LEFT(E50,6)) -> 100457 | E50: 100457 - Immobiliazioni Materiali In Corso - FV Lizzano | F50: =+_xlfn.XLOOKUP(D50,CVS!E:E,CVS!I:I,0) -> 81349.91 | G50: =+SUMIFS('De Giorgi BDV'!C:C,'De Giorgi BDV'!D:D,D50) -> 0 | H50: =+F50+G50 -> 81349.91 | I50: =+_xlfn.XLOOKUP(D50,[1]BDV!$F:$F,[1]BDV!$AI:$AI) -> 81349.91 | J50: =+H50-I50 -> 0
A51: SP | B51: FV | C51: Tangible Assets | D51: =+_xlfn.NUMBERVALUE(LEFT(E51,6)) -> 100459 | E51: 100459 - Fornitori Imm. Materiali c/acconti - FV Mucca Nera | F51: =+_xlfn.XLOOKUP(D51,CVS!E:E,CVS!I:I,0) -> 5035.95 | G51: =+SUMIFS('De Giorgi BDV'!C:C,'De Giorgi BDV'!D:D,D51) -> 0 | H51: =+F51+G51 -> 5035.95 | I51: =+_xlfn.XLOOKUP(D51,[1]BDV!$F:$F,[1]BDV!$AI:$AI) -> 5035.95 | J51: =+H51-I51 -> 0
A52: SP | B52: 0 | C52: Tangible Assets | D52: =+_xlfn.NUMBERVALUE(LEFT(E52,6)) -> 100461 | E52: 100461 - Fornitori Imm. Materiali c/acconti | F52: =+_xlfn.XLOOKUP(D52,CVS!E:E,CVS!I:I,0) -> 46863.2 | G52: =+SUMIFS('De Giorgi BDV'!C:C,'De Giorgi BDV'!D:D,D52) -> 0 | H52: =+F52+G52 -> 46863.2 | I52: =+_xlfn.XLOOKUP(D52,[1]BDV!$F:$F,[1]BDV!$AI:$AI) -> 46863.2 | J52: =+H52-I52 -> 0
A53: SP | B53: 0 | C53: Tangible Assets | D53: =+_xlfn.NUMBERVALUE(LEFT(E53,6)) -> 100463 | E53: 100463 - Fabbricati Ind.Li e Comm. Li (MiniPia) | F53: =+_xlfn.XLOOKUP(D53,CVS!E:E,CVS!I:I,0) -> 542422.65 | G53: =+SUMIFS('De Giorgi BDV'!C:C,'De Giorgi BDV'!D:D,D53) -> 0 | H53: =+F53+G53 -> 542422.65 | I53: =+_xlfn.XLOOKUP(D53,[1]BDV!$F:$F,[1]BDV!$AI:$AI) -> 542422.65 | J53: =+H53-I53 -> 0
A54: SP | B54: 0 | C54: Tangible Assets | D54: =+_xlfn.NUMBERVALUE(LEFT(E54,6)) -> 100465 | E54: 100465 - F/Amm Fabbricati Ind.Li E Comm. Li (MiniPia) | F54: =+_xlfn.XLOOKUP(D54,CVS!E:E,CVS!I:I,0) -> -59135.35 | G54: =+SUMIFS('De Giorgi BDV'!C:C,'De Giorgi BDV'!D:D,D54) -> 0 | H54: =+F54+G54 -> -59135.35 | I54: =+_xlfn.XLOOKUP(D54,[1]BDV!$F:$F,[1]BDV!$AI:$AI) -> -59135.35 | J54: =+H54-I54 -> 0
A55: SP | B55: 0 | C55: Tangible Assets | D55: =+_xlfn.NUMBERVALUE(LEFT(E55,6)) -> 100467 | E55: 100467 - F/Amm. Beni Inferiori Ai 516,46 Euro | F55: =+_xlfn.XLOOKUP(D55,CVS!E:E,CVS!I:I,0) -> -18097.31 | G55: =+SUMIFS('De Giorgi BDV'!C:C,'De Giorgi BDV'!D:D,D55) -> 0 | H55: =+F55+G55 -> -18097.31 | I55: =+_xlfn.XLOOKUP(D55,[1]BDV!$F:$F,[1]BDV!$AI:$AI) -> -18097.31 | J55: =+H55-I55 -> 0
A56: SP | B56: FV | C56: Tangible Assets | D56: =+_xlfn.NUMBERVALUE(LEFT(E56,6)) -> 100469 | E56: 100469 - Immobiliazioni Materiali In Corso - FV Avezzano 3 | F56: =+_xlfn.XLOOKUP(D56,CVS!E:E,CVS!I:I,0) -> 1164176.8 | G56: =+SUMIFS('De Giorgi BDV'!C:C,'De Giorgi BDV'!D:D,D56) -> 0 | H56: =+F56+G56 -> 1164176.8 | I56: =+_xlfn.XLOOKUP(D56,[1]BDV!$F:$F,[1]BDV!$AI:$AI) -> 1164176.8 | J56: =+H56-I56 -> 0
A57: SP | B57: FV | C57: Tangible Assets | D57: =+_xlfn.NUMBERVALUE(LEFT(E57,6)) -> 100471 | E57: 100471 - Immobiliazioni Materiali In Corso - FV Montorio al Vomano 1 | F57: =+_xlfn.XLOOKUP(D57,CVS!E:E,CVS!I:I,0) -> 1645137.9 | G57: =+SUMIFS('De Giorgi BDV'!C:C,'De Giorgi BDV'!D:D,D57) -> 0 | H57: =+F57+G57 -> 1645137.9 | I57: =+_xlfn.XLOOKUP(D57,[1]BDV!$F:$F,[1]BDV!$AI:$AI) -> 1645137.9 | J57: =+H57-I57 -> 0
A58: SP | B58: FV | C58: Tangible Assets | D58: =+_xlfn.NUMBERVALUE(LEFT(E58,6)) -> 100473 | E58: 100473 - Immobiliazioni Materiali In Corso - FV Giulianova | F58: =+_xlfn.XLOOKUP(D58,CVS!E:E,CVS!I:I,0) -> 921393.76 | G58: =+SUMIFS('De Giorgi BDV'!C:C,'De Giorgi BDV'!D:D,D58) -> 0 | H58: =+F58+G58 -> 921393.76 | I58: =+_xlfn.XLOOKUP(D58,[1]BDV!$F:$F,[1]BDV!$AI:$AI) -> 921393.76 | J58: =+H58-I58 -> 0
A59: SP | B59: FV | C59: Tangible Assets | D59: =+_xlfn.NUMBERVALUE(LEFT(E59,6)) -> 100475 | E59: 100475 - Immobiliazioni Materiali In Corso - FV Borgorose | F59: =+_xlfn.XLOOKUP(D59,CVS!E:E,CVS!I:I,0) -> 973496.14 | G59: =+SUMIFS('De Giorgi BDV'!C:C,'De Giorgi BDV'!D:D,D59) -> 0 | H59: =+F59+G59 -> 973496.14 | I59: =+_xlfn.XLOOKUP(D59,[1]BDV!$F:$F,[1]BDV!$AI:$AI) -> 973496.14 | J59: =+H59-I59 -> 0
A60: SP | B60: FV | C60: Tangible Assets | D60: =+_xlfn.NUMBERVALUE(LEFT(E60,6)) -> 100477 | E60: 100477 - Immobiliazioni Materiali In Corso - FV Copertino 1 | F60: =+_xlfn.XLOOKUP(D60,CVS!E:E,CVS!I:I,0) -> 1115669.6 | G60: =+SUMIFS('De Giorgi BDV'!C:C,'De Giorgi BDV'!D:D,D60) -> 0 | H60: =+F60+G60 -> 1115669.6 | I60: =+_xlfn.XLOOKUP(D60,[1]BDV!$F:$F,[1]BDV!$AI:$AI) -> 1115669.6 | J60: =+H60-I60 -> 0
A61: SP | B61: FV | C61: Tangible Assets | D61: =+_xlfn.NUMBERVALUE(LEFT(E61,6)) -> 100479 | E61: 100479 - Immobiliazioni Materiali In Corso - FV Corfinio | F61: =+_xlfn.XLOOKUP(D61,CVS!E:E,CVS!I:I,0) -> 829090.49 | G61: =+SUMIFS('De Giorgi BDV'!C:C,'De Giorgi BDV'!D:D,D61) -> 0 | H61: =+F61+G61 -> 829090.49 | I61: =+_xlfn.XLOOKUP(D61,[1]BDV!$F:$F,[1]BDV!$AI:$AI) -> 829090.49 | J61: =+H61-I61 -> 0
A62: SP | B62: FV | C62: Tangible Assets | D62: =+_xlfn.NUMBERVALUE(LEFT(E62,6)) -> 100481 | E62: 100481 - Immobiliazioni Materiali In Corso - FV Avezzano 4 | F62: =+_xlfn.XLOOKUP(D62,CVS!E:E,CVS!I:I,0) -> 1087160.8 | G62: =+SUMIFS('De Giorgi BDV'!C:C,'De Giorgi BDV'!D:D,D62) -> 0 | H62: =+F62+G62 -> 1087160.8 | I62: =+_xlfn.XLOOKUP(D62,[1]BDV!$F:$F,[1]BDV!$AI:$AI) -> 1087160.8 | J62: =+H62-I62 -> 0
A63: SP | B63: FV | C63: Tangible Assets | D63: =+_xlfn.NUMBERVALUE(LEFT(E63,6)) -> 100483 | E63: 100483 - Immobiliazioni Materiali In Corso - FV Montorio al Vomano 3 | F63: =+_xlfn.XLOOKUP(D63,CVS!E:E,CVS!I:I,0) -> 991956.75 | G63: =+SUMIFS('De Giorgi BDV'!C:C,'De Giorgi BDV'!D:D,D63) -> 0 | H63: =+F63+G63 -> 991956.75 | I63: =+_xlfn.XLOOKUP(D63,[1]BDV!$F:$F,[1]BDV!$AI:$AI) -> 991956.75 | J63: =+H63-I63 -> 0
A64: SP | B64: FV | C64: Tangible Assets | D64: =+_xlfn.NUMBERVALUE(LEFT(E64,6)) -> 100485 | E64: 100485 - Immobiliazioni Materiali In Corso - FV Montorio al Vomano 4 | F64: =+_xlfn.XLOOKUP(D64,CVS!E:E,CVS!I:I,0) -> 916403.37 | G64: =+SUMIFS('De Giorgi BDV'!C:C,'De Giorgi BDV'!D:D,D64) -> 0 | H64: =+F64+G64 -> 916403.37 | I64: =+_xlfn.XLOOKUP(D64,[1]BDV!$F:$F,[1]BDV!$AI:$AI) -> 916403.37 | J64: =+H64-I64 -> 0
A65: SP | B65: FV | C65: Tangible Assets | D65: =+_xlfn.NUMBERVALUE(LEFT(E65,6)) -> 100487 | E65: 100487 - Immobiliazioni Materiali In Corso - FV Collarmele | F65: =+_xlfn.XLOOKUP(D65,CVS!E:E,CVS!I:I,0) -> 838538.06 | G65: =+SUMIFS('De Giorgi BDV'!C:C,'De Giorgi BDV'!D:D,D65) -> 0 | H65: =+F65+G65 -> 838538.06 | I65: =+_xlfn.XLOOKUP(D65,[1]BDV!$F:$F,[1]BDV!$AI:$AI) -> 838538.06 | J65: =+H65-I65 -> 0
A66: SP | B66: FV | C66: Tangible Assets | D66: =+_xlfn.NUMBERVALUE(LEFT(E66,6)) -> 100489 | E66: 100489 - Immobiliazioni Materiali In Corso - FV Campi Salentina 1 | F66: =+_xlfn.XLOOKUP(D66,CVS!E:E,CVS!I:I,0) -> 1087448.5 | G66: =+SUMIFS('De Giorgi BDV'!C:C,'De Giorgi BDV'!D:D,D66) -> 0 | H66: =+F66+G66 -> 1087448.5 | I66: =+_xlfn.XLOOKUP(D66,[1]BDV!$F:$F,[1]BDV!$AI:$AI) -> 1087448.5 | J66: =+H66-I66 -> 0
A67: SP | B67: FV | C67: Tangible Assets | D67: =+_xlfn.NUMBERVALUE(LEFT(E67,6)) -> 100491 | E67: 100491 - Immobiliazioni Materiali In Corso - FV Copertino 2 | F67: =+_xlfn.XLOOKUP(D67,CVS!E:E,CVS!I:I,0) -> 766621.33 | G67: =+SUMIFS('De Giorgi BDV'!C:C,'De Giorgi BDV'!D:D,D67) -> 0 | H67: =+F67+G67 -> 766621.33 | I67: =+_xlfn.XLOOKUP(D67,[1]BDV!$F:$F,[1]BDV!$AI:$AI) -> 766621.33 | J67: =+H67-I67 -> 0
... A71: SP | B71: FV | C71: Tangible Assets | D71: =+_xlfn.NUMBERVALUE(LEFT(E71,6)) -> 100499 | E71: 100499 - Immobiliazioni Materiali In Corso - FV Tricase | F71: =+_xlfn.XLOOKUP(D71,CVS!E:E,CVS!I:I,0) -> 143607.9 | G71: =+SUMIFS('De Giorgi BDV'!C:C,'De Giorgi BDV'!D:D,D71) -> 0 | H71: =+F71+G71 -> 143607.9 | I71: =+_xlfn.XLOOKUP(D71,[1]BDV!$F:$F,[1]BDV!$AI:$AI) -> 143607.9 | J71: =+H71-I71 -> 0
A72: SP | B72: 0 | C72: Intangible Assets | D72: =+_xlfn.NUMBERVALUE(LEFT(E72,6)) -> 100501 | E72: 100501 - Diritti D'uso | F72: =+_xlfn.XLOOKUP(D72,CVS!E:E,CVS!I:I,0) -> 3399355.5 | G72: =+SUMIFS('De Giorgi BDV'!C:C,'De Giorgi BDV'!D:D,D72) -> 0 | H72: =+F72+G72 -> 3399355.5 | I72: =+_xlfn.XLOOKUP(D72,[1]BDV!$F:$F,[1]BDV!$AI:$AI) -> 3399355.5 | J72: =+H72-I72 -> 0
A73: SP | B73: 0 | C73: Intangible Assets | D73: =+_xlfn.NUMBERVALUE(LEFT(E73,6)) -> 100503 | E73: 100503 - Fondo amm.to diritti d'uso | F73: =+_xlfn.XLOOKUP(D73,CVS!E:E,CVS!I:I,0) -> -1302951.5 | G73: =+SUMIFS('De Giorgi BDV'!C:C,'De Giorgi BDV'!D:D,D73) -> 0 | H73: =+F73+G73 -> -1302951.5 | I73: =+_xlfn.XLOOKUP(D73,[1]BDV!$F:$F,[1]BDV!$AI:$AI) -> -1302951.5 | J73: =+H73-I73 -> 0
A74: SP | B74: FV | C74: Tangible Assets | D74: =+_xlfn.NUMBERVALUE(LEFT(E74,6)) -> 100505 | E74: 100505 - Immobiliazioni Materiali In Corso - FV San Giorgio Ionico | F74: =+_xlfn.XLOOKUP(D74,CVS!E:E,CVS!I:I,0) -> 154101.24 | G74: =+SUMIFS('De Giorgi BDV'!C:C,'De Giorgi BDV'!D:D,D74) -> 0 | H74: =+F74+G74 -> 154101.24 | I74: =+_xlfn.XLOOKUP(D74,[1]BDV!$F:$F,[1]BDV!$AI:$AI) -> 154101.24 | J74: =+H74-I74 -> 0
A75: SP | B75: FV | C75: Tangible Assets | D75: =+_xlfn.NUMBERVALUE(LEFT(E75,6)) -> 100509 | E75: 100509 - Immobiliazioni Materiali In Corso - FV Avezzano 5 | F75: =+_xlfn.XLOOKUP(D75,CVS!E:E,CVS!I:I,0) -> 57320.6 | G75: =+SUMIFS('De Giorgi BDV'!C:C,'De Giorgi BDV'!D:D,D75) -> 0 | H75: =+F75+G75 -> 57320.6 | I75: =+_xlfn.XLOOKUP(D75,[1]BDV!$F:$F,[1]BDV!$AI:$AI) -> 57320.6 | J75: =+H75-I75 -> 0
A76: SP | B76: FV | C76: Tangible Assets | D76: =+_xlfn.NUMBERVALUE(LEFT(E76,6)) -> 100513 | E76: 100513 - Immobiliazioni Materiali In Corso - FV Taviano 2 | F76: =+_xlfn.XLOOKUP(D76,CVS!E:E,CVS!I:I,0) -> 411699.71 | G76: =+SUMIFS('De Giorgi BDV'!C:C,'De Giorgi BDV'!D:D,D76) -> 0 | H76: =+F76+G76 -> 411699.71 | I76: =+_xlfn.XLOOKUP(D76,[1]BDV!$F:$F,[1]BDV!$AI:$AI) -> 411699.71 | J76: =+H76-I76 -> 0
A77: SP | B77: FV | C77: Tangible Assets | D77: =+_xlfn.NUMBERVALUE(LEFT(E77,6)) -> 100515 | E77: 100515 - Immobiliazioni Materiali In Corso - FV Scurcola 1 | F77: =+_xlfn.XLOOKUP(D77,CVS!E:E,CVS!I:I,0) -> 110808.86 | G77: =+SUMIFS('De Giorgi BDV'!C:C,'De Giorgi BDV'!D:D,D77) -> 0 | H77: =+F77+G77 -> 110808.86 | I77: =+_xlfn.XLOOKUP(D77,[1]BDV!$F:$F,[1]BDV!$AI:$AI) -> 110808.86 | J77: =+H77-I77 -> 0
A78: SP | B78: 0 | C78: Financial Assets | D78: =+_xlfn.NUMBERVALUE(LEFT(E78,6)) -> 100601 | E78: 100601 - Partecipazioni Imp. Controllate | F78: =+_xlfn.XLOOKUP(D78,CVS!E:E,CVS!I:I,0) -> 12654422 | G78: =+SUMIFS('De Giorgi BDV'!C:C,'De Giorgi BDV'!D:D,D78) -> 0 | H78: =+F78+G78 -> 12654422 | I78: =+_xlfn.XLOOKUP(D78,[1]BDV!$F:$F,[1]BDV!$AI:$AI) -> 12654422 | J78: =+H78-I78 -> 0
A79: SP | B79: 0 | C79: Financial Assets | D79: =+_xlfn.NUMBERVALUE(LEFT(E79,6)) -> 100603 | E79: 100603 - Partecipazioni Imp. Collegate | F79: =+_xlfn.XLOOKUP(D79,CVS!E:E,CVS!I:I,0) -> 491899.5 | G79: =+SUMIFS('De Giorgi BDV'!C:C,'De Giorgi BDV'!D:D,D79) -> 0 | H79: =+F79+G79 -> 491899.5 | I79: =+_xlfn.XLOOKUP(D79,[1]BDV!$F:$F,[1]BDV!$AI:$AI) -> 491899.5 | J79: =+H79-I79 -> 0
A80: SP | B80: 0 | C80: Financial Assets | D80: =+_xlfn.NUMBERVALUE(LEFT(E80,6)) -> 100605 | E80: 100605 - Partecipazioni Imp. Altre Imprese | F80: =+_xlfn.XLOOKUP(D80,CVS!E:E,CVS!I:I,0) -> 46954.62 | G80: =+SUMIFS('De Giorgi BDV'!C:C,'De Giorgi BDV'!D:D,D80) -> 2066 | H80: =+F80+G80 -> 49020.62 | I80: =+_xlfn.XLOOKUP(D80,[1]BDV!$F:$F,[1]BDV!$AI:$AI) -> 49020.62 | J80: =+H80-I80 -> 0
A81: SP | B81: 0 | C81: Other Credit | D81: =+_xlfn.NUMBERVALUE(LEFT(E81,6)) -> 100607 | E81: 100607 - Crediti Vs. Imp. Controllate | F81: =+_xlfn.XLOOKUP(D81,CVS!E:E,CVS!I:I,0) -> 17114347 | G81: =+SUMIFS('De Giorgi BDV'!C:C,'De Giorgi BDV'!D:D,D81) -> 0 | H81: =+F81+G81 -> 17114347 | I81: =+_xlfn.XLOOKUP(D81,[1]BDV!$F:$F,[1]BDV!$AI:$AI) -> 17114347 | J81: =+H81-I81 -> 0
A82: SP | B82: 0 | C82: Other Credit | D82: =+_xlfn.NUMBERVALUE(LEFT(E82,6)) -> 100611 | E82: 100611 - Crediti Vs. Imp. Altre Imprese | F82: =+_xlfn.XLOOKUP(D82,CVS!E:E,CVS!I:I,0) -> 3992 | G82: =+SUMIFS('De Giorgi BDV'!C:C,'De Giorgi BDV'!D:D,D82) -> 0 | H82: =+F82+G82 -> 3992 | I82: =+_xlfn.XLOOKUP(D82,[1]BDV!$F:$F,[1]BDV!$AI:$AI) -> 3992 | J82: =+H82-I82 -> 0
A83: SP | B83: 0 | C83: Other Credit | D83: =+_xlfn.NUMBERVALUE(LEFT(E83,6)) -> 100615 | E83: 100615 - Crediti Vs. Altri | F83: =+_xlfn.XLOOKUP(D83,CVS!E:E,CVS!I:I,0) -> 120180.32 | G83: =+SUMIFS('De Giorgi BDV'!C:C,'De Giorgi BDV'!D:D,D83) -> 0 | H83: =+F83+G83 -> 120180.32 | I83: =+_xlfn.XLOOKUP(D83,[1]BDV!$F:$F,[1]BDV!$AI:$AI) -> 120180.32 | J83: =+H83-I83 -> 0
A84: SP | B84: 0 | C84: Other Credit | D84: =+_xlfn.NUMBERVALUE(LEFT(E84,6)) -> 100621 | E84: 100621 - Depositi Cauzioniari Commerciali | F84: =+_xlfn.XLOOKUP(D84,CVS!E:E,CVS!I:I,0) -> 135934.92 | G84: =+SUMIFS('De Giorgi BDV'!C:C,'De Giorgi BDV'!D:D,D84) -> 0 | H84: =+F84+G84 -> 135934.92 | I84: =+_xlfn.XLOOKUP(D84,[1]BDV!$F:$F,[1]BDV!$AI:$AI) -> 135934.92 | J84: =+H84-I84 -> 0
A85: SP | B85: 0 | C85: Other Reserves | D85: =+_xlfn.NUMBERVALUE(LEFT(E85,6)) -> 100622 | E85: 100622 - Soci c/sottoscrizione | F85: =+_xlfn.XLOOKUP(D85,CVS!E:E,CVS!I:I,0) -> 108000 | G85: =+SUMIFS('De Giorgi BDV'!C:C,'De Giorgi BDV'!D:D,D85) -> 0 | H85: =+F85+G85 -> 108000 | I85: =+_xlfn.XLOOKUP(D85,[1]BDV!$F:$F,[1]BDV!$AI:$AI) -> 108000 | J85: =+H85-I85 -> 0
A86: SP | B86: 0 | C86: Financial Assets | D86: =+_xlfn.NUMBERVALUE(LEFT(E86,6)) -> 100623 | E86: 100623 - Crediti Vs. SPV Città Metropolitana Venezia II | F86: =+_xlfn.XLOOKUP(D86,CVS!E:E,CVS!I:I,0) -> 2888550.2 | G86: =+SUMIFS('De Giorgi BDV'!C:C,'De Giorgi BDV'!D:D,D86) -> 0 | H86: =+F86+G86 -> 2888550.2 | I86: =+_xlfn.XLOOKUP(D86,[1]BDV!$F:$F,[1]BDV!$AI:$AI) -> 2888550.2 | J86: =+H86-I86 -> 0
A87: SP | B87: 0 | C87: Financial Assets | D87: =+_xlfn.NUMBERVALUE(LEFT(E87,6)) -> 100625 | E87: 100625 - Crediti Vs. SPV Crosia Smart City | F87: =+_xlfn.XLOOKUP(D87,CVS!E:E,CVS!I:I,0) -> 894050.18 | G87: =+SUMIFS('De Giorgi BDV'!C:C,'De Giorgi BDV'!D:D,D87) -> 0 | H87: =+F87+G87 -> 894050.18 | I87: =+_xlfn.XLOOKUP(D87,[1]BDV!$F:$F,[1]BDV!$AI:$AI) -> 894050.18 | J87: =+H87-I87 -> 0
A88: SP | B88: 0 | C88: Financial Assets | D88: =+_xlfn.NUMBERVALUE(LEFT(E88,6)) -> 100627 | E88: 100627 - Crediti Vs. SPV Spezzano Albanese Smart City | F88: =+_xlfn.XLOOKUP(D88,CVS!E:E,CVS!I:I,0) -> 978336.66 | G88: =+SUMIFS('De Giorgi BDV'!C:C,'De Giorgi BDV'!D:D,D88) -> 0 | H88: =+F88+G88 -> 978336.66 | I88: =+_xlfn.XLOOKUP(D88,[1]BDV!$F:$F,[1]BDV!$AI:$AI) -> 978336.66 | J88: =+H88-I88 -> 0
A89: SP | B89: 0 | C89: Financial Assets | D89: =+_xlfn.NUMBERVALUE(LEFT(E89,6)) -> 100635 | E89: 100635 - Credito Acquisizione Alfano_Partecipazione TECS | F89: =+_xlfn.XLOOKUP(D89,CVS!E:E,CVS!I:I,0) -> 7918688 | G89: =+SUMIFS('De Giorgi BDV'!C:C,'De Giorgi BDV'!D:D,D89) -> 0 | H89: =+F89+G89 -> 7918688 | I89: =+_xlfn.XLOOKUP(D89,[1]BDV!$F:$F,[1]BDV!$AI:$AI) -> 7918688 | J89: =+H89-I89 -> 0
... A100: SP | B100: 0 | C100: Financial Assets | D100: =+_xlfn.NUMBERVALUE(LEFT(E100,6)) -> 160201 | E100: 160201 - Altri Titoli | F100: =+_xlfn.XLOOKUP(D100,CVS!E:E,CVS!I:I,0) -> 461829.21 | G100: =+SUMIFS('De Giorgi BDV'!C:C,'De Giorgi BDV'!D:D,D100) -> 0 | H100: =+F100+G100 -> 461829.21 | I100: =+_xlfn.XLOOKUP(D100,[1]BDV!$F:$F,[1]BDV!$AI:$AI) -> 461829.21 | J100: =+H100-I100 -> 0
A101: CE | B101: R | C101: Other Revenues | D101: =+_xlfn.NUMBERVALUE(LEFT(E101,6)) -> 160203 | E101: 160203 - Spese Anticipate | F101: =+_xlfn.XLOOKUP(D101,CVS!E:E,CVS!I:I,0) -> -756.79 | G101: =+SUMIFS('De Giorgi BDV'!C:C,'De Giorgi BDV'!D:D,D101) -> 0 | H101: =+F101+G101 -> -756.79 | I101: =+_xlfn.XLOOKUP(D101,[1]BDV!$F:$F,[1]BDV!$AI:$AI) -> -756.79 | J101: =+H101-I101 -> 0
A102: SP | B102: 0 | C102: Other Credit | D102: =+_xlfn.NUMBERVALUE(LEFT(E102,6)) -> 160205 | E102: 160205 - Anticipo Bolla Doganale | F102: =+_xlfn.XLOOKUP(D102,CVS!E:E,CVS!I:I,0) -> -28579.75 | G102: =+SUMIFS('De Giorgi BDV'!C:C,'De Giorgi BDV'!D:D,D102) -> 0 | H102: =+F102+G102 -> -28579.75 | I102: =+_xlfn.XLOOKUP(D102,[1]BDV!$F:$F,[1]BDV!$AI:$AI) -> -28579.75 | J102: =+H102-I102 -> 0
A103: SP | B103: 0 | C103: Trade Receivables | D103: =+_xlfn.NUMBERVALUE(LEFT(E103,6)) -> 160207 | E103: 160207 - Fatture Da Emettere | F103: =+_xlfn.XLOOKUP(D103,CVS!E:E,CVS!I:I,0) -> 17628920 | G103: =+SUMIFS('De Giorgi BDV'!C:C,'De Giorgi BDV'!D:D,D103) -> 33623.11 | H103: =+F103+G103 -> 17662543 | I103: =+_xlfn.XLOOKUP(D103,[1]BDV!$F:$F,[1]BDV!$AI:$AI) -> 17662543 | J103: =+H103-I103 -> 0
A104: SP | B104: 0 | C104: Other Credit | D104: =+_xlfn.NUMBERVALUE(LEFT(E104,6)) -> 160208 | E104: 160208 - Crediti verso Altri | F104: =+_xlfn.XLOOKUP(D104,CVS!E:E,CVS!I:I,0) -> 353316.06 | G104: =+SUMIFS('De Giorgi BDV'!C:C,'De Giorgi BDV'!D:D,D104) -> 0 | H104: =+F104+G104 -> 353316.06 | I104: =+_xlfn.XLOOKUP(D104,[1]BDV!$F:$F,[1]BDV!$AI:$AI) -> 353316.06 | J104: =+H104-I104 -> 0
A105: SP | B105: 0 | C105: Trade Payables | D105: =+_xlfn.NUMBERVALUE(LEFT(E105,6)) -> 160210 | E105: 160210 - Note di Credito Da Ricevere | F105: =+_xlfn.XLOOKUP(D105,CVS!E:E,CVS!I:I,0) -> 147938.91 | G105: =+SUMIFS('De Giorgi BDV'!C:C,'De Giorgi BDV'!D:D,D105) -> 0 | H105: =+F105+G105 -> 147938.91 | I105: =+_xlfn.XLOOKUP(D105,[1]BDV!$F:$F,[1]BDV!$AI:$AI) -> 147938.91 | J105: =+H105-I105 -> 0
A106: SP | B106: 0 | C106: Trade Payables | D106: =+_xlfn.NUMBERVALUE(LEFT(E106,6)) -> 160212 | E106: 160212 - Fornitori C/Acconti | F106: =+_xlfn.XLOOKUP(D106,CVS!E:E,CVS!I:I,0) -> 166102.55 | G106: =+SUMIFS('De Giorgi BDV'!C:C,'De Giorgi BDV'!D:D,D106) -> 0 | H106: =+F106+G106 -> 166102.55 | I106: =+_xlfn.XLOOKUP(D106,[1]BDV!$F:$F,[1]BDV!$AI:$AI) -> 166102.55 | J106: =+H106-I106 -> 0
A107: SP | B107: 0 | C107: Other Credit | D107: =+_xlfn.NUMBERVALUE(LEFT(E107,6)) -> 160216 | E107: 160216 - Crediti per ritenuta a garanzia | F107: =+_xlfn.XLOOKUP(D107,CVS!E:E,CVS!I:I,0) -> 641999.5 | G107: =+SUMIFS('De Giorgi BDV'!C:C,'De Giorgi BDV'!D:D,D107) -> 0 | H107: =+F107+G107 -> 641999.5 | I107: =+_xlfn.XLOOKUP(D107,[1]BDV!$F:$F,[1]BDV!$AI:$AI) -> 641999.5 | J107: =+H107-I107 -> 0
A108: SP | B108: 0 | C108: Other Credit | D108: =+_xlfn.NUMBERVALUE(LEFT(E108,6)) -> 160218 | E108: 160218 - Crediti/Debiti v/Atlantico Spa | F108: =+_xlfn.XLOOKUP(D108,CVS!E:E,CVS!I:I,0) -> 3335 | G108: =+SUMIFS('De Giorgi BDV'!C:C,'De Giorgi BDV'!D:D,D108) -> 0 | H108: =+F108+G108 -> 3335 | I108: =+_xlfn.XLOOKUP(D108,[1]BDV!$F:$F,[1]BDV!$AI:$AI) -> 3335 | J108: =+H108-I108 -> 0
A109: SP | B109: 0 | C109: Other Credit | D109: =+_xlfn.NUMBERVALUE(LEFT(E109,6)) -> 160220 | E109: 160220 - Crediti V/Socio Sofein Da Richiamare | F109: =+_xlfn.XLOOKUP(D109,CVS!E:E,CVS!I:I,0) -> 5062.5 | G109: =+SUMIFS('De Giorgi BDV'!C:C,'De Giorgi BDV'!D:D,D109) -> 0 | H109: =+F109+G109 -> 5062.5 | I109: =+_xlfn.XLOOKUP(D109,[1]BDV!$F:$F,[1]BDV!$AI:$AI) -> 5062.5 | J109: =+H109-I109 -> 0
A110: SP | B110: 0 | C110: Other Credit | D110: =+_xlfn.NUMBERVALUE(LEFT(E110,6)) -> 160222 | E110: 160222 - Credito V/Sofein Accordo Transattivo | F110: =+_xlfn.XLOOKUP(D110,CVS!E:E,CVS!I:I,0) -> 137585.87 | G110: =+SUMIFS('De Giorgi BDV'!C:C,'De Giorgi BDV'!D:D,D110) -> 0 | H110: =+F110+G110 -> 137585.87 | I110: =+_xlfn.XLOOKUP(D110,[1]BDV!$F:$F,[1]BDV!$AI:$AI) -> 137585.87 | J110: =+H110-I110 -> 0
A111: SP | B111: 0 | C111: Trade Receivables | D111: =+_xlfn.NUMBERVALUE(LEFT(E111,6)) -> 160224 | E111: 160224 - Credito V/Estra Clima | F111: =+_xlfn.XLOOKUP(D111,CVS!E:E,CVS!I:I,0) -> 16.75 | G111: =+SUMIFS('De Giorgi BDV'!C:C,'De Giorgi BDV'!D:D,D111) -> 0 | H111: =+F111+G111 -> 16.75 | I111: =+_xlfn.XLOOKUP(D111,[1]BDV!$F:$F,[1]BDV!$AI:$AI) -> 16.75 | J111: =+H111-I111 -> 0
A112: SP | B112: 0 | C112: Tax Credit | D112: =+_xlfn.NUMBERVALUE(LEFT(E112,6)) -> 160401 | E112: 160401 - Erario C/Iva Compensazione | F112: =+_xlfn.XLOOKUP(D112,CVS!E:E,CVS!I:I,0) -> 1012821.4 | G112: =+SUMIFS('De Giorgi BDV'!C:C,'De Giorgi BDV'!D:D,D112) -> 131602.09 | H112: =+F112+G112 -> 1144423.5 | I112: =+_xlfn.XLOOKUP(D112,[1]BDV!$F:$F,[1]BDV!$AI:$AI) -> 1144423.5 | J112: =+H112-I112 -> 0
A113: SP | B113: 0 | C113: Tax Credit | D113: =+_xlfn.NUMBERVALUE(LEFT(E113,6)) -> 160403 | E113: 160403 - Erario C/Iva Rimborso | F113: =+_xlfn.XLOOKUP(D113,CVS!E:E,CVS!I:I,0) -> 2942929.8 | G113: =+SUMIFS('De Giorgi BDV'!C:C,'De Giorgi BDV'!D:D,D113) -> 0 | H113: =+F113+G113 -> 2942929.8 | I113: =+_xlfn.XLOOKUP(D113,[1]BDV!$F:$F,[1]BDV!$AI:$AI) -> 2942929.8 | J113: =+H113-I113 -> 0
... A235: SP | B235: 0 | C235: Other Liabilities | D235: =+_xlfn.NUMBERVALUE(LEFT(E235,6)) -> 360203 | E235: 360203 - Ratei Passivi | F235: =+_xlfn.XLOOKUP(D235,CVS!E:E,CVS!I:I,0) -> -22386.38 | G235: =+SUMIFS('De Giorgi BDV'!C:C,'De Giorgi BDV'!D:D,D235) -> 0 | H235: =+F235+G235 -> -22386.38 | I235: =+_xlfn.XLOOKUP(D235,[1]BDV!$F:$F,[1]BDV!$AI:$AI) -> -22386.38 | J235: =+H235-I235 -> 0
A236: CE | B236: Revenues | C236: Canone | D236: =+_xlfn.NUMBERVALUE(LEFT(E236,6)) -> 620201 | E236: 620201 - Ricavi | F236: =+_xlfn.XLOOKUP(D236,CVS!E:E,CVS!I:I,0) -> -36911194 | G236: =+SUMIFS('De Giorgi BDV'!C:C,'De Giorgi BDV'!D:D,D236) -> -703945.96 | H236: =+F236+G236 -> -37615140 | I236: =+_xlfn.XLOOKUP(D236,[1]BDV!$F:$F,[1]BDV!$AI:$AI) -> 0 | J236: =+H236-I236 -> -37615140
A237: CE | B237: Revenues | C237: Canone | D237: =+_xlfn.NUMBERVALUE(LEFT(E237,6)) -> 620203 | E237: 620203 - Ricavi I/C | F237: =+_xlfn.XLOOKUP(D237,CVS!E:E,CVS!I:I,0) -> -789276.15 | G237: =+SUMIFS('De Giorgi BDV'!C:C,'De Giorgi BDV'!D:D,D237) -> 0 | H237: =+F237+G237 -> -789276.15 | I237: =+_xlfn.XLOOKUP(D237,[1]BDV!$F:$F,[1]BDV!$AI:$AI) -> -789276.15 | J237: =+H237-I237 -> 0
A238: CE | B238: R | C238: Costruzioni Interne | D238: =+_xlfn.NUMBERVALUE(LEFT(E238,6)) -> 640201 | E238: 640201 - Capit. Costi di Imm. Immat. | F238: =+_xlfn.XLOOKUP(D238,CVS!E:E,CVS!I:I,0) -> -2824723.6 | G238: =+SUMIFS('De Giorgi BDV'!C:C,'De Giorgi BDV'!D:D,D238) -> 0 | H238: =+F238+G238 -> -2824723.6 | I238: =+_xlfn.XLOOKUP(D238,[1]BDV!$F:$F,[1]BDV!$AI:$AI) -> -2824723.6 | J238: =+H238-I238 -> 0
A239: CE | B239: R | C239: Other Revenues | D239: =+_xlfn.NUMBERVALUE(LEFT(E239,6)) -> 660201 | E239: 660201 - Sconti, Ribassi e Abbuoni Attivi | F239: =+_xlfn.XLOOKUP(D239,CVS!E:E,CVS!I:I,0) -> -7206.23 | G239: =+SUMIFS('De Giorgi BDV'!C:C,'De Giorgi BDV'!D:D,D239) -> -0.97 | H239: =+F239+G239 -> -7207.2 | I239: =+_xlfn.XLOOKUP(D239,[1]BDV!$F:$F,[1]BDV!$AI:$AI) -> -7207.2 | J239: =+H239-I239 -> 0
A240: CE | B240: R | C240: Other Revenues | D240: =+_xlfn.NUMBERVALUE(LEFT(E240,6)) -> 660203 | E240: 660203 - Altri Ricavi E Proventi Vari | F240: =+_xlfn.XLOOKUP(D240,CVS!E:E,CVS!I:I,0) -> -9498.5 | G240: =+SUMIFS('De Giorgi BDV'!C:C,'De Giorgi BDV'!D:D,D240) -> -3770 | H240: =+F240+G240 -> -13268.5 | I240: =+_xlfn.XLOOKUP(D240,[1]BDV!$F:$F,[1]BDV!$AI:$AI) -> -13268.5 | J240: =+H240-I240 -> 0
A241: CE | B241: R | C241: Other Revenues | D241: =+_xlfn.NUMBERVALUE(LEFT(E241,6)) -> 660403 | E241: 660403 - Plusvalenze | F241: =+_xlfn.XLOOKUP(D241,CVS!E:E,CVS!I:I,0) -> -3152.3 | G241: =+SUMIFS('De Giorgi BDV'!C:C,'De Giorgi BDV'!D:D,D241) -> 0 | H241: =+F241+G241 -> -3152.3 | I241: =+_xlfn.XLOOKUP(D241,[1]BDV!$F:$F,[1]BDV!$AI:$AI) -> -3152.3 | J241: =+H241-I241 -> 0
A242: CE | B242: R | C242: Extraordinary Item (Attive) | D242: =+_xlfn.NUMBERVALUE(LEFT(E242,6)) -> 660407 | E242: 660407 - Sopravvenienze Attive | F242: =+_xlfn.XLOOKUP(D242,CVS!E:E,CVS!I:I,0) -> -23438.42 | G242: =+SUMIFS('De Giorgi BDV'!C:C,'De Giorgi BDV'!D:D,D242) -> -70 | H242: =+F242+G242 -> -23508.42 | I242: =+_xlfn.XLOOKUP(D242,[1]BDV!$F:$F,[1]BDV!$AI:$AI) -> -23508.42 | J242: =+H242-I242 -> 0
A243: CE | B243: R | C243: Extraordinary Item (Attive) | D243: =+_xlfn.NUMBERVALUE(LEFT(E243,6)) -> 660409 | E243: 660409 - Sopravvenienze Attive Ord. Inded. | F243: =+_xlfn.XLOOKUP(D243,CVS!E:E,CVS!I:I,0) -> -1691.99 | G243: =+SUMIFS('De Giorgi BDV'!C:C,'De Giorgi BDV'!D:D,D243) -> 0 | H243: =+F243+G243 -> -1691.99 | I243: =+_xlfn.XLOOKUP(D243,[1]BDV!$F:$F,[1]BDV!$AI:$AI) -> -1691.99 | J243: =+H243-I243 -> 0
A244: CE | B244: R | C244: Other Revenues | D244: =+_xlfn.NUMBERVALUE(LEFT(E244,6)) -> 660413 | E244: 660413 - Contributi In C/Esercizio | F244: =+_xlfn.XLOOKUP(D244,CVS!E:E,CVS!I:I,0) -> -18677.46 | G244: =+SUMIFS('De Giorgi BDV'!C:C,'De Giorgi BDV'!D:D,D244) -> 0 | H244: =+F244+G244 -> -18677.46 | I244: =+_xlfn.XLOOKUP(D244,[1]BDV!$F:$F,[1]BDV!$AI:$AI) -> -18677.46 | J244: =+H244-I244 -> 0
A245: CE | B245: C | C245: Costi Diretti | D245: =+_xlfn.NUMBERVALUE(LEFT(E245,6)) -> 680201 | E245: 680201 - Merci C/Acquisti Nazionali | F245: =+_xlfn.XLOOKUP(D245,CVS!E:E,CVS!I:I,0) -> 7647933.3 | G245: =+SUMIFS('De Giorgi BDV'!C:C,'De Giorgi BDV'!D:D,D245) -> 75376.38 | H245: =+F245+G245 -> 7723309.7 | I245: =+_xlfn.XLOOKUP(D245,[1]BDV!$F:$F,[1]BDV!$AI:$AI) -> 7723309.7 | J245: =+H245-I245 -> 0
A246: CE | B246: R | C246: Costruzioni Interne | D246: =+_xlfn.NUMBERVALUE(LEFT(E246,6)) -> 680209 | E246: 680209 - Capitalizzazioni costi di materie prime | F246: =+_xlfn.XLOOKUP(D246,CVS!E:E,CVS!I:I,0) -> -2001545.2 | G246: =+SUMIFS('De Giorgi BDV'!C:C,'De Giorgi BDV'!D:D,D246) -> 0 | H246: =+F246+G246 -> -2001545.2 | I246: =+_xlfn.XLOOKUP(D246,[1]BDV!$F:$F,[1]BDV!$AI:$AI) -> -2001545.2 | J246: =+H246-I246 -> 0
A247: CE | B247: C | C247: Overheads | D247: =+_xlfn.NUMBERVALUE(LEFT(E247,6)) -> 680401 | E247: 680401 - Acquisti Vari | F247: =+_xlfn.XLOOKUP(D247,CVS!E:E,CVS!I:I,0) -> 81.89 | G247: =+SUMIFS('De Giorgi BDV'!C:C,'De Giorgi BDV'!D:D,D247) -> 0 | H247: =+F247+G247 -> 81.89 | I247: =+_xlfn.XLOOKUP(D247,[1]BDV!$F:$F,[1]BDV!$AI:$AI) -> 81.89 | J247: =+H247-I247 -> 0
... A363: CE | B363: C | C363: Financial Income | D363: =+_xlfn.NUMBERVALUE(LEFT(E363,6)) -> 900201 | E363: 900201 - Differenziale Derivati Di Copertura | F363: =+_xlfn.XLOOKUP(D363,CVS!E:E,CVS!I:I,0) -> -214475.36 | G363: =+SUMIFS('De Giorgi BDV'!C:C,'De Giorgi BDV'!D:D,D363) -> 0 | H363: =+F363+G363 -> -214475.36 | I363: =+_xlfn.XLOOKUP(D363,[1]BDV!$F:$F,[1]BDV!$AI:$AI) -> -214475.36 | J363: =+H363-I363 -> 0
A364: CE | B364: R | C364: Financial Income | D364: =+_xlfn.NUMBERVALUE(LEFT(E364,6)) -> 900209 | E364: 900209 - Interessi Attivi | F364: =+_xlfn.XLOOKUP(D364,CVS!E:E,CVS!I:I,0) -> -19111.54 | G364: 6 | H364: =+F364+G364 -> -19105.54 | I364: =+_xlfn.XLOOKUP(D364,[1]BDV!$F:$F,[1]BDV!$AI:$AI) -> -19111.54 | J364: =+H364-I364 -> 6
A365: CE | B365: C | C365: Financial Expenses | D365: =+_xlfn.NUMBERVALUE(LEFT(E365,6)) -> 920207 | E365: 920207 - Interessi Da Debiti Verso Banche | F365: =+_xlfn.XLOOKUP(D365,CVS!E:E,CVS!I:I,0) -> 83426.69 | G365: =+SUMIFS('De Giorgi BDV'!C:C,'De Giorgi BDV'!D:D,D365) -> 3049.58 | H365: =+F365+G365 -> 86476.27 | I365: =+_xlfn.XLOOKUP(D365,[1]BDV!$F:$F,[1]BDV!$AI:$AI) -> 86476.27 | J365: =+H365-I365 -> 0
A366: CE | B366: C | C366: Financial Expenses | D366: =+_xlfn.NUMBERVALUE(LEFT(E366,6)) -> 920211 | E366: 920211 - Interessi Da Altri Debiti | F366: =+_xlfn.XLOOKUP(D366,CVS!E:E,CVS!I:I,0) -> 14.09 | G366: =+SUMIFS('De Giorgi BDV'!C:C,'De Giorgi BDV'!D:D,D366) -> 364.27 | H366: =+F366+G366 -> 378.36 | I366: =+_xlfn.XLOOKUP(D366,[1]BDV!$F:$F,[1]BDV!$AI:$AI) -> 378.36 | J366: =+H366-I366 -> 0
A367: CE | B367: C | C367: Financial Expenses | D367: =+_xlfn.NUMBERVALUE(LEFT(E367,6)) -> 920213 | E367: 920213 - Int. Passivi V/Fornitori | F367: =+_xlfn.XLOOKUP(D367,CVS!E:E,CVS!I:I,0) -> 661.76 | G367: =+SUMIFS('De Giorgi BDV'!C:C,'De Giorgi BDV'!D:D,D367) -> 0 | H367: =+F367+G367 -> 661.76 | I367: =+_xlfn.XLOOKUP(D367,[1]BDV!$F:$F,[1]BDV!$AI:$AI) -> 661.76 | J367: =+H367-I367 -> 0
A368: CE | B368: C | C368: Financial Expenses | D368: =+_xlfn.NUMBERVALUE(LEFT(E368,6)) -> 920215 | E368: 920215 - Interessi Da Debiti Verso Banche_Linea Senior | F368: =+_xlfn.XLOOKUP(D368,CVS!E:E,CVS!I:I,0) -> 487688.42 | G368: =+SUMIFS('De Giorgi BDV'!C:C,'De Giorgi BDV'!D:D,D368) -> 0 | H368: =+F368+G368 -> 487688.42 | I368: =+_xlfn.XLOOKUP(D368,[1]BDV!$F:$F,[1]BDV!$AI:$AI) -> 487688.42 | J368: =+H368-I368 -> 0
A369: CE | B369: C | C369: Taxes | D369: =+_xlfn.NUMBERVALUE(LEFT(E369,6)) -> 940201 | E369: 940201 - Irap Dell'esercizio | F369: =+_xlfn.XLOOKUP(D369,CVS!E:E,CVS!I:I,0) -> 4801 | G369: =+SUMIFS('De Giorgi BDV'!C:C,'De Giorgi BDV'!D:D,D369) -> 3668 | H369: =+F369+G369 -> 8469 | I369: =+_xlfn.XLOOKUP(D369,[1]BDV!$F:$F,[1]BDV!$AI:$AI) -> 8469 | J369: =+H369-I369 -> 0
A370: CE | B370: C | C370: Taxes | D370: =+_xlfn.NUMBERVALUE(LEFT(E370,6)) -> 940209 | E370: 940209 - Ires Dell'esercizio | F370: =+_xlfn.XLOOKUP(D370,CVS!E:E,CVS!I:I,0) -> 29605 | G370: =+SUMIFS('De Giorgi BDV'!C:C,'De Giorgi BDV'!D:D,D370) -> 16354 | H370: =+F370+G370 -> 45959 | I370: =+_xlfn.XLOOKUP(D370,[1]BDV!$F:$F,[1]BDV!$AI:$AI) -> 45959 | J370: =+H370-I370 -> 0
A371: SP | B371: 0 | C371: Other Credit | D371: GST-001 | E371: GST-001 - Inventory Asset (Gest.) | F371: =+_xlfn.XLOOKUP(D371,CVS!E:E,CVS!I:I,0) -> 661599.88 | G371: =+SUMIFS('De Giorgi BDV'!C:C,'De Giorgi BDV'!D:D,D371) -> 0 | H371: =+F371+G371 -> 661599.88 | I371: =+_xlfn.XLOOKUP(D371,[1]BDV!$F:$F,[1]BDV!$AI:$AI) -> 661599.88 | J371: =+H371-I371 -> 0
A372: SP | B372: 0 | C372: Other Liabilities | D372: GST-002 | E372: GST-002 - Accrued Purchases (Gest.) | F372: =+_xlfn.XLOOKUP(D372,CVS!E:E,CVS!I:I,0) -> -787113.65 | G372: =+SUMIFS('De Giorgi BDV'!C:C,'De Giorgi BDV'!D:D,D372) -> 0 | H372: =+F372+G372 -> -787113.65 | I372: =+_xlfn.XLOOKUP(D372,[1]BDV!$F:$F,[1]BDV!$AI:$AI) -> -787113.65 | J372: =+H372-I372 -> 0
A373: CE | B373: C | C373: Costi Diretti | D373: GST-005 | E373: GST-005 - Cost of Goods Sold (Gest.) | F373: =+_xlfn.XLOOKUP(D373,CVS!E:E,CVS!I:I,0) -> 123959.8 | G373: =+SUMIFS('De Giorgi BDV'!C:C,'De Giorgi BDV'!D:D,D373) -> 0 | H373: =+F373+G373 -> 123959.8 | I373: =+_xlfn.XLOOKUP(D373,[1]BDV!$F:$F,[1]BDV!$AI:$AI) -> 123959.8 | J373: =+H373-I373 -> 0
A374: SP | B374: 0 | C374: Other Credit | D374: GST-007 | E374: GST-007 - Rettifica Inventariale (Gest.) | F374: =+_xlfn.XLOOKUP(D374,CVS!E:E,CVS!I:I,0) -> 0 | G374: =+SUMIFS('De Giorgi BDV'!C:C,'De Giorgi BDV'!D:D,D374) -> 0 | H374: =+F374+G374 -> 0 | I374: =+_xlfn.XLOOKUP(D374,[1]BDV!$F:$F,[1]BDV!$AI:$AI) -> 0 | J374: =+H374-I374 -> 0
A375: SP | B375: 0 | C375: Other Credit | D375: GST-008 | E375: GST-008 - Inventory In Transit (Gest.) | F375: =+_xlfn.XLOOKUP(D375,CVS!E:E,CVS!I:I,0) -> 1553.97 | G375: =+SUMIFS('De Giorgi BDV'!C:C,'De Giorgi BDV'!D:D,D375) -> 0 | H375: =+F375+G375 -> 1553.97 | I375: =+_xlfn.XLOOKUP(D375,[1]BDV!$F:$F,[1]BDV!$AI:$AI) -> 1553.97 | J375: =+H375-I375 -> 0
A376: CE | B376: C | C376: Overheads | D376: 68/05/501 | E376: SPESE PARTECIPAZIONE CONSORZIO | F376: =+_xlfn.XLOOKUP(D376,CVS!E:E,CVS!I:I,0) -> 0 | G376: =+SUMIFS('De Giorgi BDV'!C:C,'De Giorgi BDV'!D:D,D376) -> 3355.78 | H376: =+F376+G376 -> 3355.78 | I376: =+_xlfn.XLOOKUP(D376,[1]BDV!$F:$F,[1]BDV!$AI:$AI) -> 3355.78 | J376: =+H376-I376 -> 0
A377: SP | B377: 0 | C377: Cash & Cash Equivalent | D377: 24/05/002 | E377: BANCA MPS C/C 1616312 | F377: =+_xlfn.XLOOKUP(D377,CVS!E:E,CVS!I:I,0) -> 0 | G377: =+SUMIFS('De Giorgi BDV'!C:C,'De Giorgi BDV'!D:D,D377) -> 172828.39 | H377: =+F377+G377 -> 172828.39 | I377: =+_xlfn.XLOOKUP(D377,[1]BDV!$F:$F,[1]BDV!$AI:$AI) -> 172828.39 | J377: =+H377-I377 -> 0
A378: SP | B378: 0 | C378: Cash & Cash Equivalent | D378: 24/05/003 | E378: BANCA INTESA - EX B.NAPOLI | F378: =+_xlfn.XLOOKUP(D378,CVS!E:E,CVS!I:I,0) -> 0 | G378: =+SUMIFS('De Giorgi BDV'!C:C,'De Giorgi BDV'!D:D,D378) -> 121605.94 | H378: =+F378+G378 -> 121605.94 | I378: =+_xlfn.XLOOKUP(D378,[1]BDV!$F:$F,[1]BDV!$AI:$AI) -> 121605.94 | J378: =+H378-I378 -> 0
A379: SP | B379: 0 | C379: Cash & Cash Equivalent | D379: 24/05/006 | E379: CARTA PREPAGATA INTESA 50 | F379: =+_xlfn.XLOOKUP(D379,CVS!E:E,CVS!I:I,0) -> 0 | G379: =+SUMIFS('De Giorgi BDV'!C:C,'De Giorgi BDV'!D:D,D379) -> 56.06 | H379: =+F379+G379 -> 56.06 | I379: =+_xlfn.XLOOKUP(D379,[1]BDV!$F:$F,[1]BDV!$AI:$AI) -> 56.06 | J379: =+H379-I379 -> 0
A380: SP | B380: =+_xlfn.XLOOKUP(D380,[1]BDV!$F:$F,[1]BDV!$D:$D) -> 0 | D380: 120201 | E380: Materie Prime, Sussidiarie E Consumo Iniziali | F380: =+_xlfn.XLOOKUP(D380,CVS!E:E,CVS!I:I,0) -> 0 | G380: =+SUMIFS('De Giorgi BDV'!C:C,'De Giorgi BDV'!D:D,D380) -> 111115.03 | H380: =+F380+G380 -> 111115.03 | I380: =+_xlfn.XLOOKUP(D380,[1]BDV!$F:$F,[1]BDV!$AI:$AI) -> 111115.03 | J380: =+H380-I380 -> 0
A381: SP | B381: =+_xlfn.XLOOKUP(D381,[1]BDV!$F:$F,[1]BDV!$D:$D) -> 0 | D381: 120205 | E381: Erario c/Ritenute lavoratori autonomi | F381: =+_xlfn.XLOOKUP(D381,CVS!E:E,CVS!I:I,0) -> 0 | G381: =+SUMIFS('De Giorgi BDV'!C:C,'De Giorgi BDV'!D:D,D381) -> 23970.69 | H381: =+F381+G381 -> 23970.69 | I381: =+_xlfn.XLOOKUP(D381,[1]BDV!$F:$F,[1]BDV!$AI:$AI) -> 23970.69 | J381: =+H381-I381 -> 0
A382: SP | B382: =+_xlfn.XLOOKUP(D382,[1]BDV!$F:$F,[1]BDV!$D:$D) -> 0 | D382: 320407 | E382: Lavori In Corso Su Ordinazione | F382: =+_xlfn.XLOOKUP(D382,CVS!E:E,CVS!I:I,0) -> 0 | G382: =+SUMIFS('De Giorgi BDV'!C:C,'De Giorgi BDV'!D:D,D382) -> -3868.18 | H382: =+F382+G382 -> -3868.18 | I382: =+_xlfn.XLOOKUP(D382,[1]BDV!$F:$F,[1]BDV!$AI:$AI) -> -3868.18 | J382: =+H382-I382 -> 0
...

Sheet De Giorgi BDV
B1: ATTIVO | C1: =SUBTOTAL(9,C9:C38) -> 2709096.5
B2: PASSIVO | C2: =SUBTOTAL(9,C41:C71) -> -2676155.7 | E2: RISULTATO DI ESERCIZIO | F2: =+C1+C2 -> 32940.77
B3: COSTI | C3: =SUBTOTAL(9,C74:C149) -> 787941.81
B4: RICAVI | C4: =SUBTOTAL(9,C152:C163) -> -820882.58
A5: De Giorgi | D5: Civismart
A6: Codice | B6: Descrizione | C6: Saldo al 31/12/2026 | D6: Codice | E6: Type | F6: Descrizione | G6: Note
A8: ** | B8: ATTIVO
A9: 03/15/015 | B9: LIC.ZA USO SOFTWARE TEMPO INDET. | C9: 33076 | D9: 100203 | E9: Fixed Asset | F9: Software | H9: =+_xlfn.XLOOKUP(D9,'Output BDV'!D:D,'Output BDV'!D:D) -> 100203
A10: 03/35/005 | B10: LAVORI STRAOR. SU BENI DI TERZI | C10: 159664.19 | D10: 100207 | E10: Fixed Asset | F10: Lavori Straor. Su Beni Di Terzi | H10: =+_xlfn.XLOOKUP(D10,'Output BDV'!D:D,'Output BDV'!D:D) -> 100207
A11: 03/35/015 | B11: ALTRI COSTI AD UTIL.PLUR.DA AMM. | C11: 8966.25 | D11: 100217 | E11: Fixed Asset | F11: Altri Costi Ad Util. Plur. Da Amm. | H11: =+_xlfn.XLOOKUP(D11,'Output BDV'!D:D,'Output BDV'!D:D) -> 100217
A12: 03/35/501 | B12: COSTI APPALTO LIZZANELLO | C12: 885136.76 | D12: 100207 | E12: Fixed Asset | F12: Lavori Straor. Su Beni Di Terzi | H12: =+_xlfn.XLOOKUP(D12,'Output BDV'!D:D,'Output BDV'!D:D) -> 100207
A13: 06/05/005 | B13: TERRENI | C13: 11857.65 | D13: 100401 | E13: Fixed Asset | F13: Terreni | H13: =+_xlfn.XLOOKUP(D13,'Output BDV'!D:D,'Output BDV'!D:D) -> 100401
A14: 06/05/015 | B14: FABBRICATI IND.LI E COMM.LI | C14: 385661.11 | D14: 100405 | E14: Fixed Asset | F14: Fabbricati Ind.Li E Comm. Li | H14: =+_xlfn.XLOOKUP(D14,'Output BDV'!D:D,'Output BDV'!D:D) -> 100405
A15: 06/10/005 | B15: IMPIANTI GENERICI | C15: 4098.25 | D15: 100415 | E15: Fixed Asset | F15: Impianti Generici | H15: =+_xlfn.XLOOKUP(D15,'Output BDV'!D:D,'Output BDV'!D:D) -> 100415
A16: 06/10/015 | B16: MACCHINARI | C16: 32895.58 | D16: 100409 | E16: Fixed Asset | F16: Macchinari | H16: =+_xlfn.XLOOKUP(D16,'Output BDV'!D:D,'Output BDV'!D:D) -> 100409
A17: 06/15/005 | B17: ATTREZZAT. IND.LI E COMM.LI | C17: 41352.67 | D17: 100411 | E17: Fixed Asset | F17: Attrezzature Industriali E Commerciali | H17: =+_xlfn.XLOOKUP(D17,'Output BDV'!D:D,'Output BDV'!D:D) -> 100411
A18: 06/15/010 | B18: ATTR.VARIE E MINUTE (<516,46 E.) | C18: 40456.09 | D18: 100413 | E18: Fixed Asset | F18: Attrezzatura Varia E Minuta | H18: =+_xlfn.XLOOKUP(D18,'Output BDV'!D:D,'Output BDV'!D:D) -> 100413
A19: 06/20/010 | B19: MACCHINE ELETTROMEC. D'UFFICIO | C19: 18720.07 | D19: 100421 | E19: Fixed Asset | F19: Macchine Elettromeccaniche D'ufficio | H19: =+_xlfn.XLOOKUP(D19,'Output BDV'!D:D,'Output BDV'!D:D) -> 100421
A20: 06/25/015 | B20: AUTOCARRI/AUTOVETTURE | C20: 214006.57 | D20: 100423 | E20: Fixed Asset | F20: Autoveicoli E Autocarri | H20: =+_xlfn.XLOOKUP(D20,'Output BDV'!D:D,'Output BDV'!D:D) -> 100423
... A31: 18/25/020 | B31: INAIL C/ACCONTI | C31: 6119.97 | D31: 160413 | E31: Other Current Asset | F31: I.N.A.I.L. C/Acconti | H31: =+_xlfn.XLOOKUP(D31,'Output BDV'!D:D,'Output BDV'!D:D) -> 160413
A32: 24/05/002 | B32: BANCA MPS C/C 1616312 | C32: 172828.39 | D32: 24/05/002 | G32: Da creare | H32: =+_xlfn.XLOOKUP(D32,'Output BDV'!D:D,'Output BDV'!D:D) -> 24/05/002
A33: 24/05/003 | B33: BANCA INTESA - EX B.NAPOLI | C33: 121605.94 | D33: 24/05/003 | G33: Da creare | H33: =+_xlfn.XLOOKUP(D33,'Output BDV'!D:D,'Output BDV'!D:D) -> 24/05/003
A34: 24/05/006 | B34: CARTA PREPAGATA INTESA 50 | C34: 56.06 | D34: 24/05/006 | G34: Da creare | H34: =+_xlfn.XLOOKUP(D34,'Output BDV'!D:D,'Output BDV'!D:D) -> 24/05/006
A35: 24/15/005 | B35: DENARO IN CASSA | C35: 6.87 | D35: 180201 | E35: Bank | F35: Cassa | H35: =+_xlfn.XLOOKUP(D35,'Output BDV'!D:D,'Output BDV'!D:D) -> 180201
A36: 26/10/005 | B36: RISCONTI ATTIVI | C36: 5531.99 | D36: 360201 | E36: Deferred Expense | F36: Risconti Attivi | H36: =+_xlfn.XLOOKUP(D36,'Output BDV'!D:D,'Output BDV'!D:D) -> 360201
A37: 48/05/040 | B37: ERARIO C/IVA | C37: 3253.16 | D37: 320409 | E37: Other Current Liability | F37: Erario C/Iva | H37: =+_xlfn.XLOOKUP(D37,'Output BDV'!D:D,'Output BDV'!D:D) -> 320409
A38: 48/05/100 | B38: REGIONI C/IRAP | C38: 4339 | D38: 320405 | E38: Other Current Liability | F38: Regioni C/Irap | H38: =+_xlfn.XLOOKUP(D38,'Output BDV'!D:D,'Output BDV'!D:D) -> 320405
H39: =+_xlfn.XLOOKUP(D39,'Output BDV'!D:D,'Output BDV'!D:D) -> 0
A40: ** | B40: PASSIVO | H40: =+_xlfn.XLOOKUP(D40,'Output BDV'!D:D,'Output BDV'!D:D) -> 0
A41: 04/15/015 | B41: F/AMM.LIC. D'USO SOF. A TEM. IND | C41: -33076 | D41: 100225 | E41: Fixed Asset | F41: F/Amm Software | H41: =+_xlfn.XLOOKUP(D41,'Output BDV'!D:D,'Output BDV'!D:D) -> 100225
A42: 04/35/005 | B42: F/AMM. LAV. STR. SU BENI DI TERZ | C42: -149012.63 | D42: 100235 | E42: Fixed Asset | F42: F/Amm. Lav. Str. Su Beni Di Terzi | H42: =+_xlfn.XLOOKUP(D42,'Output BDV'!D:D,'Output BDV'!D:D) -> 100235
A43: 04/35/015 | B43: F/AMM.ALT. COS. AD UT. PLU. AMM | C43: -8966.25 | D43: 100237 | E43: Fixed Asset | F43: F/Amm. Alt. Cost. Ad Ut. Plu. Amm. | H43: =+_xlfn.XLOOKUP(D43,'Output BDV'!D:D,'Output BDV'!D:D) -> 100237
A44: 04/35/501 | B44: F/AMM COSTI APPALTO LIZZANELLO | C44: -317021.91 | D44: 100235 | E44: Fixed Asset | F44: F/Amm. Lav. Str. Su Beni Di Terzi | H44: =+_xlfn.XLOOKUP(D44,'Output BDV'!D:D,'Output BDV'!D:D) -> 100235
A45: 07/05/006 | B45: F/AMM. TERRENI | C45: -11857.65 | D45: 100429 | E45: Fixed Asset | F45: F/Amm Fabbricati Ind.Li E Comm. Li | H45: =+_xlfn.XLOOKUP(D45,'Output BDV'!D:D,'Output BDV'!D:D) -> 100429
A46: 07/05/015 | B46: F/AMM.FABBR. IND.LI E COMM.LI. | C46: -221946.25 | D46: 100429 | E46: Fixed Asset | F46: F/Amm Fabbricati Ind.Li E Comm. Li | H46: =+_xlfn.XLOOKUP(D46,'Output BDV'!D:D,'Output BDV'!D:D) -> 100429
A47: 07/10/005 | B47: F/AMM.IMPIANTI GENERICI | C47: -3971.97 | D47: 100439 | E47: Fixed Asset | F47: F/Amm Impianti Generici | H47: =+_xlfn.XLOOKUP(D47,'Output BDV'!D:D,'Output BDV'!D:D) -> 100439
A48: 07/10/015 | B48: F/AMM.MACCHINARI | C48: -31725.72 | D48: 100433 | E48: Fixed Asset | F48: F/Amm Macchinari | H48: =+_xlfn.XLOOKUP(D48,'Output BDV'!D:D,'Output BDV'!D:D) -> 100433
A49: 07/15/005 | B49: F/AMM.ATTREZ. IND.LI E COMM.LI | C49: -41194.32 | D49: 100435 | E49: Fixed Asset | F49: F/Amm Attrezzatura Industriali E Commerciali | H49: =+_xlfn.XLOOKUP(D49,'Output BDV'!D:D,'Output BDV'!D:D) -> 100435
A50: 07/15/010 | B50: F/AMM.ATTR. VARIE E MINUTE | C50: -40456.09 | D50: 100437 | E50: Fixed Asset | F50: F/Amm Attrezzatura Varia E Minuta | H50: =+_xlfn.XLOOKUP(D50,'Output BDV'!D:D,'Output BDV'!D:D) -> 100437
A51: 07/20/010 | B51: F/AMM.MACCH. ELETTROM. D'UFF. | C51: -16375.74 | D51: 100445 | E51: Fixed Asset | F51: F/Amm Macchine Elettromeccaniche D'ufficio | H51: =+_xlfn.XLOOKUP(D51,'Output BDV'!D:D,'Output BDV'!D:D) -> 100445
A52: 07/25/015 | B52: F/AMM. AUTOCARRI/AUTOVETTURE | C52: -155726.02 | D52: 100447 | E52: Fixed Asset | F52: F/Amm Autoveicoli E Autocarri | H52: =+_xlfn.XLOOKUP(D52,'Output BDV'!D:D,'Output BDV'!D:D) -> 100447
... A71: 54/10/005 | B71: RISCONTI PASSIVI | C71: -994.37 | D71: 200203 | E71: Deferred Revenue | F71: Risconti Passivi | H71: =+_xlfn.XLOOKUP(D71,'Output BDV'!D:D,'Output BDV'!D:D) -> 200203
H72: =+_xlfn.XLOOKUP(D72,'Output BDV'!D:D,'Output BDV'!D:D) -> 0
A73: ** | B73: COSTI | H73: =+_xlfn.XLOOKUP(D73,'Output BDV'!D:D,'Output BDV'!D:D) -> 0
A74: 61/05/005 | B74: LAV.IN CORSO.C/E.I. <12M.VAL.COS | C74: 93704.4 | D74: 700203 | E74: Expense | F74: Lavoraz. Di Terzi P/Prod. Servizi | H74: =+_xlfn.XLOOKUP(D74,'Output BDV'!D:D,'Output BDV'!D:D) -> 700203
A75: 66/05/005 | B75: MATERIE PRIME C/ACQUISTI | C75: 71673.7 | D75: 680201 | E75: Expense | F75: Merci C/Acquisti Nazionali | H75: =+_xlfn.XLOOKUP(D75,'Output BDV'!D:D,'Output BDV'!D:D) -> 680201
A76: 66/10/005 | B76: COSTO ENERGIA COMUNE S.DONATO | C76: 95314.7 | D76: 700601 | E76: Expense | F76: Spesa Energia Commesse | H76: =+_xlfn.XLOOKUP(D76,'Output BDV'!D:D,'Output BDV'!D:D) -> 700601
A77: 66/15/005 | B77: COSTO ENERGIA COM. LIZZANELLO | C77: 55974.56 | D77: 700601 | E77: Expense | F77: Spesa Energia Commesse | H77: =+_xlfn.XLOOKUP(D77,'Output BDV'!D:D,'Output BDV'!D:D) -> 700601
A78: 66/20/005 | B78: MATERIE DI CONSUMO C/ACQUISTI | C78: 2343.3 | D78: 680201 | E78: Expense | F78: Merci C/Acquisti Nazionali | H78: =+_xlfn.XLOOKUP(D78,'Output BDV'!D:D,'Output BDV'!D:D) -> 680201
A79: 66/30/025 | B79: CANCELLERIA | C79: 335.88 | D79: 700803 | E79: Expense | F79: Cancelleria | H79: =+_xlfn.XLOOKUP(D79,'Output BDV'!D:D,'Output BDV'!D:D) -> 700803
A80: 66/30/035 | B80: CARBURANTI E LUBRIFICANTI | C80: 2683.18 | D80: 680601 | E80: Expense | F80: Carburante | H80: =+_xlfn.XLOOKUP(D80,'Output BDV'!D:D,'Output BDV'!D:D) -> 680601
A81: 66/30/037 | B81: CARBURANTI E LUBRIF.PARZ.DED. | C81: 1832.81 | D81: 680603 | E81: Expense | F81: Carburante Parz. Ded. | H81: =+_xlfn.XLOOKUP(D81,'Output BDV'!D:D,'Output BDV'!D:D) -> 680603
A82: 66/30/045 | B82: INDUMENTI DI LAVORO | C82: 139.26 | D82: 680201 | E82: Expense | F82: Merci C/Acquisti Nazionali | H82: =+_xlfn.XLOOKUP(D82,'Output BDV'!D:D,'Output BDV'!D:D) -> 680201
A83: 66/30/055 | B83: SPESE ACCESSORIE SU ACQUISTI | C83: 220 | D83: 680403 | E83: Expense | F83: Spese Accessorie Su Acquisti | H83: =+_xlfn.XLOOKUP(D83,'Output BDV'!D:D,'Output BDV'!D:D) -> 680403
A84: 66/30/060 | B84: ACQUISTI BENI COSTO UNIT.<516,46 | C84: 1220.12 | D84: 680201 | E84: Expense | F84: Merci C/Acquisti Nazionali | H84: =+_xlfn.XLOOKUP(D84,'Output BDV'!D:D,'Output BDV'!D:D) -> 680201
A85: 66/30/491 | B85: ALTRI ACQUISTI INDEDUCIBILI | C85: 118.44 | D85: 701603 | E85: Expense | F85: Spese Di Rappresentanza Non Ded. | H85: =+_xlfn.XLOOKUP(D85,'Output BDV'!D:D,'Output BDV'!D:D) -> 701603
... A111: 68/05/490 | B111: ALTRI SERVIZI DEDUCIBILI | C111: 2929.64 | D111: 700203 | E111: Expense | F111: Lavoraz. Di Terzi P/Prod. Servizi | H111: =+_xlfn.XLOOKUP(D111,'Output BDV'!D:D,'Output BDV'!D:D) -> 700203
A112: 68/05/501 | B112: SPESE PARTECIPAZIONE CONSORZIO | C112: 3355.78 | D112: 68/05/501 | G112: Da creare | H112: =+_xlfn.XLOOKUP(D112,'Output BDV'!D:D,'Output BDV'!D:D) -> 68/05/501
A113: 70/05/101 | B113: NOLEGGIO DEDUCIBILE | C113: 957.67 | D113: 720403 | E113: Expense | F113: Noleggi Deducibili | H113: =+_xlfn.XLOOKUP(D113,'Output BDV'!D:D,'Output BDV'!D:D) -> 720403
A114: 70/25/010 | B114: LIC. D'USO SOFTWARE DI ESERCIZIO | C114: 1108.84 | D114: 702401 | E114: Expense | F114: Canoni Software, Licenze E Simili | H114: =+_xlfn.XLOOKUP(D114,'Output BDV'!D:D,'Output BDV'!D:D) -> 702401
A115: 72/05/015 | B115: SALARI E STIP.DIP.TEMPO INDET. | C115: 69448.05 | D115: 740201 | E115: Other Expense | F115: Salari E Stipendi - Operai | H115: =+_xlfn.XLOOKUP(D115,'Output BDV'!D:D,'Output BDV'!D:D) -> 740201
A116: 72/05/501 | B116: SALARI E STIPENDI - AMMINISTR. | C116: 17212.78 | D116: 740203 | E116: Other Expense | F116: Salari E Stipendi - Impiegati | H116: =+_xlfn.XLOOKUP(D116,'Output BDV'!D:D,'Output BDV'!D:D) -> 740203
A117: 72/15/007 | B117: ONERI SOCIALI INPS DIP.TEMPO IND | C117: 19015.7 | D117: 740601 | E117: Other Expense | F117: Oneri Previdenziali I.N.P.S. - Operai | H117: =+_xlfn.XLOOKUP(D117,'Output BDV'!D:D,'Output BDV'!D:D) -> 740601
A118: 72/15/093 | B118: ALTRI ONERI SOC.TEMPO INDET. | C118: 520 | D118: 740603 | E118: Other Expense | F118: Altri Oneri Previdenziali | H118: =+_xlfn.XLOOKUP(D118,'Output BDV'!D:D,'Output BDV'!D:D) -> 740603
A119: 72/15/501 | B119: ONERI SOCIALI INPS - AMMINISTRAT | C119: 3489.92 | D119: 740611 | E119: Other Expense | F119: Oneri Previdenziali I.N.P.S. - Impiegati | H119: =+_xlfn.XLOOKUP(D119,'Output BDV'!D:D,'Output BDV'!D:D) -> 740611
A120: 72/20/009 | B120: TFR DIPENDENTI A TEMPO INDETERM. | C120: 7392.4 | D120: 741201 | E120: Other Expense | F120: Trattamento Di Fine Rapporto | H120: =+_xlfn.XLOOKUP(D120,'Output BDV'!D:D,'Output BDV'!D:D) -> 741201
A121: 74/35/005 | B121: AMM.LAV. STRAORD.BENI DI TERZI | C121: 5314.85 | D121: 760601 | E121: Expense | F121: Amm.To Lav. Straord. Beni Di Terzi | H121: =+_xlfn.XLOOKUP(D121,'Output BDV'!D:D,'Output BDV'!D:D) -> 760601
A122: 74/35/501 | B122: AMM.TO COSTI APP. LIZZANELLO | C122: 23748.83 | D122: 760601 | E122: Expense | F122: Amm.To Lav. Straord. Beni Di Terzi | H122: =+_xlfn.XLOOKUP(D122,'Output BDV'!D:D,'Output BDV'!D:D) -> 760601
A123: 75/05/015 | B123: AMM.TO ORD.FABB.IND.LI E COM. | C123: 7702.66 | D123: 780201 | E123: Expense | F123: Amm.To Ord. Fabb. Ind.Li E Comm. | H123: =+_xlfn.XLOOKUP(D123,'Output BDV'!D:D,'Output BDV'!D:D) -> 780201
A124: 75/10/005 | B124: AMM.TO ORD.IMP.GEN. | C124: 272.85 | D124: 780601 | E124: Expense | F124: Amm.To Ord. Imp. Gen. | H124: =+_xlfn.XLOOKUP(D124,'Output BDV'!D:D,'Output BDV'!D:D) -> 780601
... A149: 96/05/015 | B149: IRES DELL'ESERCIZIO | C149: 16354 | D149: 940209 | E149: Other Expense | F149: Ires Dell'esercizio | H149: =+_xlfn.XLOOKUP(D149,'Output BDV'!D:D,'Output BDV'!D:D) -> 940209
H150: =+_xlfn.XLOOKUP(D150,'Output BDV'!D:D,'Output BDV'!D:D) -> 0
A151: ** | B151: RICAVI | H151: =+_xlfn.XLOOKUP(D151,'Output BDV'!D:D,'Output BDV'!D:D) -> 0
A152: 58/10/005 | B152: RICAVI PER PRESTAZ. DI SERVIZI | C152: -290116.91 | D152: 620201 | E152: Income | F152: Ricavi | H152: =+_xlfn.XLOOKUP(D152,'Output BDV'!D:D,'Output BDV'!D:D) -> 620201
A153: 58/10/010 | B153: CONTRIB.INC.IMP.FOTOVOLTAICO | C153: -338.42 | D153: 620201 | E153: Income | F153: Ricavi | H153: =+_xlfn.XLOOKUP(D153,'Output BDV'!D:D,'Output BDV'!D:D) -> 620201
A154: 58/10/015 | B154: RICAVI COMUNE DI SAN DONATO | C154: -131459.6 | D154: 620201 | E154: Income | F154: Ricavi | H154: =+_xlfn.XLOOKUP(D154,'Output BDV'!D:D,'Output BDV'!D:D) -> 620201
A155: 58/10/490 | B155: ALTRI RICAVI DELLE PRESTAZIONI | C155: -283.13 | D155: 620201 | E155: Income | F155: Ricavi | H155: =+_xlfn.XLOOKUP(D155,'Output BDV'!D:D,'Output BDV'!D:D) -> 620201
A156: 58/10/501 | B156: RICAVI COMUNE DI LIZZANELLO | C156: -254572.41 | D156: 620201 | E156: Income | F156: Ricavi | H156: =+_xlfn.XLOOKUP(D156,'Output BDV'!D:D,'Output BDV'!D:D) -> 620201
A157: 61/05/010 | B157: LAV.IN CORSO C/R.F.<12M.VAL.COS | C157: -23970.69 | D157: 620201 | E157: Income | F157: Ricavi | H157: =+_xlfn.XLOOKUP(D157,'Output BDV'!D:D,'Output BDV'!D:D) -> 620201
A158: 64/05/045 | B158: RIS.DANNI BENI DEST. ALLA RIVEN. | C158: -3204.8 | D158: 620201 | E158: Income | F158: Ricavi | H158: =+_xlfn.XLOOKUP(D158,'Output BDV'!D:D,'Output BDV'!D:D) -> 620201
A159: 64/05/100 | B159: ABBUONI/ARROT. ATTIVI IMP. | C159: -0.97 | D159: 660201 | E159: Other Income | F159: Sconti, Ribassi e Abbuoni Attivi | H159: =+_xlfn.XLOOKUP(D159,'Output BDV'!D:D,'Output BDV'!D:D) -> 660201
A160: 64/05/115 | B160: SOPRAVVENIENZE ORDINARIE ATTIVE | C160: -70 | D160: 660407 | E160: Other Income | F160: Sopravvenienze Attive | H160: =+_xlfn.XLOOKUP(D160,'Output BDV'!D:D,'Output BDV'!D:D) -> 660407
A161: 64/05/390 | B161: ALTRI RICAVI E PROVENTI VARI | C161: -3770 | D161: 660203 | E161: Other Income | F161: Altri Ricavi E Proventi Vari | H161: =+_xlfn.XLOOKUP(D161,'Output BDV'!D:D,'Output BDV'!D:D) -> 660203
A162: 64/15/025 | B162: CONTRIBUTI C/IMPIANTI | C162: -1980.62 | D162: 660411 | E162: Other Income | F162: Contributi In C/Impianti | H162: =+_xlfn.XLOOKUP(D162,'Output BDV'!D:D,'Output BDV'!D:D) -> 660411
A163: 80/05/010 | B163: MATERIE PRIME C/RIMANENZE FINALI | C163: -111115.03 | D163: 800205 | E163: Other Income | F163: Materie Prime C/Rim Finali | H163: =+_xlfn.XLOOKUP(D163,'Output BDV'!D:D,'Output BDV'!D:D) -> 800205

Sheet CVS
B4: Quadro | C4: Altro | D4: Ricla MG esteso | E4: Conto | F4: Account | G4: Debit | H4: Credit | I4: Agosto | J4: Giugno | K4: Giu RR | L4: Delta
B5: SP | C5: 0 | D5: Intangible Assets | E5: =+_xlfn.NUMBERVALUE(LEFT(F5,6)) -> 100201 | F5: 100201 - Costi Di Impianto E Ampliamento | G5: 4214.29 | I5: =+G5-H5 -> 4214.29 | J5: =+_xlfn.XLOOKUP(E5,[1]BDV!$F:$F,[1]BDV!$AC:$AC) -> 4214.29 | K5: =+J5/6*8 -> 5619.0533 | L5: =+K5-I5 -> 1404.7633
B6: SP | C6: 0 | D6: Intangible Assets | E6: =+_xlfn.NUMBERVALUE(LEFT(F6,6)) -> 100203 | F6: 100203 - Software | G6: 4758632.6 | I6: =+G6-H6 -> 4758632.6 | J6: =+_xlfn.XLOOKUP(E6,[1]BDV!$F:$F,[1]BDV!$AC:$AC) -> 4717032.6 | K6: =+J6/6*8 -> 6289376.8 | L6: =+K6-I6 -> 1530744.2
B7: SP | C7: 0 | D7: Intangible Assets | E7: =+_xlfn.NUMBERVALUE(LEFT(F7,6)) -> 100205 | F7: 100205 - Avviamento | G7: 50053945 | I7: =+G7-H7 -> 50053945 | J7: =+_xlfn.XLOOKUP(E7,[1]BDV!$F:$F,[1]BDV!$AC:$AC) -> 50053945 | K7: =+J7/6*8 -> 66738593 | L7: =+K7-I7 -> 16684648
B8: SP | C8: 0 | D8: Intangible Assets | E8: =+_xlfn.NUMBERVALUE(LEFT(F8,6)) -> 100207 | F8: 100207 - Lavori Straor. Su Beni Di Terzi | G8: 1.2097657e+08 | I8: =+G8-H8 -> 1.2097657e+08 | J8: =+_xlfn.XLOOKUP(E8,[1]BDV!$F:$F,[1]BDV!$AC:$AC) -> 1.1670003e+08 | K8: =+J8/6*8 -> 1.5560004e+08 | L8: =+K8-I8 -> 34623468
B9: SP | C9: 0 | D9: Intangible Assets | E9: =+_xlfn.NUMBERVALUE(LEFT(F9,6)) -> 100209 | F9: 100209 - Lavori Straor. Su Beni Di Terzi In Corso | G9: 21620273 | I9: =+G9-H9 -> 21620273 | J9: =+_xlfn.XLOOKUP(E9,[1]BDV!$F:$F,[1]BDV!$AC:$AC) -> 20295752 | K9: =+J9/6*8 -> 27061002 | L9: =+K9-I9 -> 5440729.2
B10: SP | C10: 0 | D10: Intangible Assets | E10: =+_xlfn.NUMBERVALUE(LEFT(F10,6)) -> 100215 | F10: 100215 - Concessioni, Licenze E Marchi | G10: 354977.91 | I10: =+G10-H10 -> 354977.91 | J10: =+_xlfn.XLOOKUP(E10,[1]BDV!$F:$F,[1]BDV!$AC:$AC) -> 354977.91 | K10: =+J10/6*8 -> 473303.88 | L10: =+K10-I10 -> 118325.97
B11: SP | C11: 0 | D11: Intangible Assets | E11: =+_xlfn.NUMBERVALUE(LEFT(F11,6)) -> 100217 | F11: 100217 - Altri Costi Ad Util. Plur. Da Amm. | G11: 201871.57 | I11: =+G11-H11 -> 201871.57 | J11: =+_xlfn.XLOOKUP(E11,[1]BDV!$F:$F,[1]BDV!$AC:$AC) -> 201871.57 | K11: =+J11/6*8 -> 269162.09 | L11: =+K11-I11 -> 67290.523
B12: SP | C12: 0 | D12: Intangible Assets | E12: =+_xlfn.NUMBERVALUE(LEFT(F12,6)) -> 100223 | F12: 100223 - F/Amm. Costi Impianto | H12: 1496.05 | I12: =+G12-H12 -> -1496.05 | J12: =+_xlfn.XLOOKUP(E12,[1]BDV!$F:$F,[1]BDV!$AC:$AC) -> -1403.05 | K12: =+J12/6*8 -> -1870.7333 | L12: =+K12-I12 -> -374.68333
B13: SP | C13: 0 | D13: Intangible Assets | E13: =+_xlfn.NUMBERVALUE(LEFT(F13,6)) -> 100225 | F13: 100225 - F/Amm Software | H13: 2334868.1 | I13: =+G13-H13 -> -2334868.1 | J13: =+_xlfn.XLOOKUP(E13,[1]BDV!$F:$F,[1]BDV!$AC:$AC) -> -2176218.1 | K13: =+J13/6*8 -> -2901624.2 | L13: =+K13-I13 -> -566756.03
B14: SP | C14: 0 | D14: Intangible Assets | E14: =+_xlfn.NUMBERVALUE(LEFT(F14,6)) -> 100227 | F14: 100227 - F/Amm Avviamento | H14: 8392.14 | I14: =+G14-H14 -> -8392.14 | J14: =+_xlfn.XLOOKUP(E14,[1]BDV!$F:$F,[1]BDV!$AC:$AC) -> -8082.14 | K14: =+J14/6*8 -> -10776.187 | L14: =+K14-I14 -> -2384.0467
B15: SP | C15: 0 | D15: Intangible Assets | E15: =+_xlfn.NUMBERVALUE(LEFT(F15,6)) -> 100231 | F15: 100231 - F/Amm Concessioni, Licenze E Marchi | H15: 260807.85 | I15: =+G15-H15 -> -260807.85 | J15: =+_xlfn.XLOOKUP(E15,[1]BDV!$F:$F,[1]BDV!$AC:$AC) -> -253386.81 | K15: =+J15/6*8 -> -337849.08 | L15: =+K15-I15 -> -77041.23
B16: SP | C16: 0 | D16: Intangible Assets | E16: =+_xlfn.NUMBERVALUE(LEFT(F16,6)) -> 100235 | F16: 100235 - F/Amm. Lav. Str. Su Beni Di Terzi | H16: 43002348 | I16: =+G16-H16 -> -43002348 | J16: =+_xlfn.XLOOKUP(E16,[1]BDV!$F:$F,[1]BDV!$AC:$AC) -> -41630306 | K16: =+J16/6*8 -> -55507075 | L16: =+K16-I16 -> -12504727
B17: SP | C17: 0 | D17: Intangible Assets | E17: =+_xlfn.NUMBERVALUE(LEFT(F17,6)) -> 100237 | F17: 100237 - F/Amm. Alt. Cost. Ad Ut. Plu. Amm. | H17: 196064.56 | I17: =+G17-H17 -> -196064.56 | J17: =+_xlfn.XLOOKUP(E17,[1]BDV!$F:$F,[1]BDV!$AC:$AC) -> -195615.56 | K17: =+J17/6*8 -> -260820.75 | L17: =+K17-I17 -> -64756.187
B18: SP | C18: 0 | D18: Intangible Assets | E18: =+_xlfn.NUMBERVALUE(LEFT(F18,6)) -> 100239 | F18: 100239 - Spese Di Costituzione | G18: 55778.54 | I18: =+G18-H18 -> 55778.54 | J18: =+_xlfn.XLOOKUP(E18,[1]BDV!$F:$F,[1]BDV!$AC:$AC) -> 55778.54 | K18: =+J18/6*8 -> 74371.387 | L18: =+K18-I18 -> 18592.847
B19: SP | C19: 0 | D19: Intangible Assets | E19: =+_xlfn.NUMBERVALUE(LEFT(F19,6)) -> 100241 | F19: 100241 - F/Amm. Spese Di Costituzione | H19: 55414.19 | I19: =+G19-H19 -> -55414.19 | J19: =+_xlfn.XLOOKUP(E19,[1]BDV!$F:$F,[1]BDV!$AC:$AC) -> -55232.19 | K19: =+J19/6*8 -> -73642.92 | L19: =+K19-I19 -> -18228.73
B20: SP | C20: 0 | D20: Intangible Assets | E20: =+_xlfn.NUMBERVALUE(LEFT(F20,6)) -> 100249 | F20: 100249 - Lista clienti | G20: 29035481 | I20: =+G20-H20 -> 29035481 | J20: =+_xlfn.XLOOKUP(E20,[1]BDV!$F:$F,[1]BDV!$AC:$AC) -> 29035481 | K20: =+J20/6*8 -> 38713974 | L20: =+K20-I20 -> 9678493.5
B21: SP | C21: 0 | D21: Intangible Assets | E21: =+_xlfn.NUMBERVALUE(LEFT(F21,6)) -> 100251 | F21: 100251 - F.do amm.to Lista clienti | H21: 4531375.8 | I21: =+G21-H21 -> -4531375.8 | J21: =+_xlfn.XLOOKUP(E21,[1]BDV!$F:$F,[1]BDV!$AC:$AC) -> -4244018.4 | K21: =+J21/6*8 -> -5658691.2 | L21: =+K21-I21 -> -1127315.4
B22: SP | C22: 0 | D22: Tangible Assets | E22: =+_xlfn.NUMBERVALUE(LEFT(F22,6)) -> 100401 | F22: 100401 - Terreni | G22: 14238.97 | I22: =+G22-H22 -> 14238.97 | J22: =+_xlfn.XLOOKUP(E22,[1]BDV!$F:$F,[1]BDV!$AC:$AC) -> 106086.67 | K22: =+J22/6*8 -> 141448.89 | L22: =+K22-I22 -> 127209.92
B23: SP | C23: 0 | D23: Tangible Assets | E23: =+_xlfn.NUMBERVALUE(LEFT(F23,6)) -> 100403 | F23: 100403 - Beni Inferiori Ai 516,46 Euro | G23: 18097 | I23: =+G23-H23 -> 18097 | J23: =+_xlfn.XLOOKUP(E23,[1]BDV!$F:$F,[1]BDV!$AC:$AC) -> 18097 | K23: =+J23/6*8 -> 24129.333 | L23: =+K23-I23 -> 6032.3333
B24: SP | C24: 0 | D24: Tangible Assets | E24: =+_xlfn.NUMBERVALUE(LEFT(F24,6)) -> 100405 | F24: 100405 - Fabbricati Ind.Li E Comm. Li | G24: 1050820.4 | I24: =+G24-H24 -> 1050820.4 | J24: =+_xlfn.XLOOKUP(E24,[1]BDV!$F:$F,[1]BDV!$AC:$AC) -> 1050820.4 | K24: =+J24/6*8 -> 1401093.9 | L24: =+K24-I24 -> 350273.47
B25: SP | C25: 0 | D25: Tangible Assets | E25: =+_xlfn.NUMBERVALUE(LEFT(F25,6)) -> 100407 | F25: 100407 - Costruzioni Leggere | G25: 104546 | I25: =+G25-H25 -> 104546 | J25: =+_xlfn.XLOOKUP(E25,[1]BDV!$F:$F,[1]BDV!$AC:$AC) -> 104546 | K25: =+J25/6*8 -> 139394.67 | L25: =+K25-I25 -> 34848.667
B26: SP | C26: 0 | D26: Tangible Assets | E26: =+_xlfn.NUMBERVALUE(LEFT(F26,6)) -> 100409 | F26: 100409 - Macchinari | G26: 36920 | I26: =+G26-H26 -> 36920 | J26: =+_xlfn.XLOOKUP(E26,[1]BDV!$F:$F,[1]BDV!$AC:$AC) -> 36920 | K26: =+J26/6*8 -> 49226.667 | L26: =+K26-I26 -> 12306.667
B27: SP | C27: 0 | D27: Tangible Assets | E27: =+_xlfn.NUMBERVALUE(LEFT(F27,6)) -> 100411 | F27: 100411 - Attrezzature Industriali E Commerciali | G27: 717177.2 | I27: =+G27-H27 -> 717177.2 | J27: =+_xlfn.XLOOKUP(E27,[1]BDV!$F:$F,[1]BDV!$AC:$AC) -> 703528.86 | K27: =+J27/6*8 -> 938038.48 | L27: =+K27-I27 -> 220861.28
B28: SP | C28: 0 | D28: Tangible Assets | E28: =+_xlfn.NUMBERVALUE(LEFT(F28,6)) -> 100413 | F28: 100413 - Attrezzatura Varia E Minuta | G28: 77813.34 | I28: =+G28-H28 -> 77813.34 | J28: =+_xlfn.XLOOKUP(E28,[1]BDV!$F:$F,[1]BDV!$AC:$AC) -> 77813.34 | K28: =+J28/6*8 -> 103751.12 | L28: =+K28-I28 -> 25937.78
B29: SP | C29: 0 | D29: Tangible Assets | E29: =+_xlfn.NUMBERVALUE(LEFT(F29,6)) -> 100415 | F29: 100415 - Impianti Generici | G29: 372327.78 | I29: =+G29-H29 -> 372327.78 | J29: =+_xlfn.XLOOKUP(E29,[1]BDV!$F:$F,[1]BDV!$AC:$AC) -> 372327.78 | K29: =+J29/6*8 -> 496437.04 | L29: =+K29-I29 -> 124109.26
B30: SP | C30: 0 | D30: Tangible Assets | E30: =+_xlfn.NUMBERVALUE(LEFT(F30,6)) -> 100417 | F30: 100417 - Impianti Specifici | G30: 571065.7 | I30: =+G30-H30 -> 571065.7 | J30: =+_xlfn.XLOOKUP(E30,[1]BDV!$F:$F,[1]BDV!$AC:$AC) -> 571065.7 | K30: =+J30/6*8 -> 761420.93 | L30: =+K30-I30 -> 190355.23
B31: SP | C31: 0 | D31: Tangible Assets | E31: =+_xlfn.NUMBERVALUE(LEFT(F31,6)) -> 100419 | F31: 100419 - Mobili E Macchine Ordinarie D'ufficio | G31: 516770.12 | I31: =+G31-H31 -> 516770.12 | J31: =+_xlfn.XLOOKUP(E31,[1]BDV!$F:$F,[1]BDV!$AC:$AC) -> 513770.12 | K31: =+J31/6*8 -> 685026.83 | L31: =+K31-I31 -> 168256.71
B32: SP | C32: 0 | D32: Tangible Assets | E32: =+_xlfn.NUMBERVALUE(LEFT(F32,6)) -> 100421 | F32: 100421 - Macchine Elettromeccaniche D'ufficio | G32: 364211.72 | I32: =+G32-H32 -> 364211.72 | J32: =+_xlfn.XLOOKUP(E32,[1]BDV!$F:$F,[1]BDV!$AC:$AC) -> 348980.49 | K32: =+J32/6*8 -> 465307.32 | L32: =+K32-I32 -> 101095.6
B33: SP | C33: 0 | D33: Tangible Assets | E33: =+_xlfn.NUMBERVALUE(LEFT(F33,6)) -> 100423 | F33: 100423 - Autoveicoli E Autocarri | G33: 710845.27 | I33: =+G33-H33 -> 710845.27 | J33: =+_xlfn.XLOOKUP(E33,[1]BDV!$F:$F,[1]BDV!$AC:$AC) -> 710845.27 | K33: =+J33/6*8 -> 947793.69 | L33: =+K33-I33 -> 236948.42
... B35: SP | C35: 0 | D35: Tangible Assets | E35: =+_xlfn.NUMBERVALUE(LEFT(F35,6)) -> 100427 | F35: 100427 - Appar. Radiomobili Detr. 80% | G35: 46069.52 | I35: =+G35-H35 -> 46069.52 | J35: =+_xlfn.XLOOKUP(E35,[1]BDV!$F:$F,[1]BDV!$AC:$AC) -> 46069.52 | K35: =+J35/6*8 -> 61426.027 | L35: =+K35-I35 -> 15356.507
B36: SP | C36: 0 | D36: Tangible Assets | E36: =+_xlfn.NUMBERVALUE(LEFT(F36,6)) -> 100429 | F36: 100429 - F/Amm Fabbricati Ind.Li E Comm. Li | H36: 299457.1 | I36: =+G36-H36 -> -299457.1 | J36: =+_xlfn.XLOOKUP(E36,[1]BDV!$F:$F,[1]BDV!$AC:$AC) -> -294384.2 | K36: =+J36/6*8 -> -392512.27 | L36: =+K36-I36 -> -93055.167
B37: SP | C37: 0 | D37: Tangible Assets | E37: =+_xlfn.NUMBERVALUE(LEFT(F37,6)) -> 100431 | F37: 100431 - F/Amm Costruzioni Leggere | H37: 74989 | I37: =+G37-H37 -> -74989 | J37: =+_xlfn.XLOOKUP(E37,[1]BDV!$F:$F,[1]BDV!$AC:$AC) -> -74338.24 | K37: =+J37/6*8 -> -99117.653 | L37: =+K37-I37 -> -24128.653
B38: SP | C38: 0 | D38: Tangible Assets | E38: =+_xlfn.NUMBERVALUE(LEFT(F38,6)) -> 100433 | F38: 100433 - F/Amm Macchinari | H38: 36919.34 | I38: =+G38-H38 -> -36919.34 | J38: =+_xlfn.XLOOKUP(E38,[1]BDV!$F:$F,[1]BDV!$AC:$AC) -> -36919.34 | K38: =+J38/6*8 -> -49225.787 | L38: =+K38-I38 -> -12306.447
B39: SP | C39: 0 | D39: Tangible Assets | E39: =+_xlfn.NUMBERVALUE(LEFT(F39,6)) -> 100435 | F39: 100435 - F/Amm Attrezzatura Industriali E Commerciali | H39: 652334.16 | I39: =+G39-H39 -> -652334.16 | J39: =+_xlfn.XLOOKUP(E39,[1]BDV!$F:$F,[1]BDV!$AC:$AC) -> -638216.7 | K39: =+J39/6*8 -> -850955.6 | L39: =+K39-I39 -> -198621.44
B40: SP | C40: 0 | D40: Tangible Assets | E40: =+_xlfn.NUMBERVALUE(LEFT(F40,6)) -> 100437 | F40: 100437 - F/Amm Attrezzatura Varia E Minuta | H40: 74803.03 | I40: =+G40-H40 -> -74803.03 | J40: =+_xlfn.XLOOKUP(E40,[1]BDV!$F:$F,[1]BDV!$AC:$AC) -> -74166.88 | K40: =+J40/6*8 -> -98889.173 | L40: =+K40-I40 -> -24086.143
B41: SP | C41: 0 | D41: Tangible Assets | E41: =+_xlfn.NUMBERVALUE(LEFT(F41,6)) -> 100439 | F41: 100439 - F/Amm Impianti Generici | H41: 329143.84 | I41: =+G41-H41 -> -329143.84 | J41: =+_xlfn.XLOOKUP(E41,[1]BDV!$F:$F,[1]BDV!$AC:$AC) -> -326493.87 | K41: =+J41/6*8 -> -435325.16 | L41: =+K41-I41 -> -106181.32
B42: SP | C42: 0 | D42: Tangible Assets | E42: =+_xlfn.NUMBERVALUE(LEFT(F42,6)) -> 100441 | F42: 100441 - F/Amm Impianti Specifici | H42: 478748.5 | I42: =+G42-H42 -> -478748.5 | J42: =+_xlfn.XLOOKUP(E42,[1]BDV!$F:$F,[1]BDV!$AC:$AC) -> -473050.14 | K42: =+J42/6*8 -> -630733.52 | L42: =+K42-I42 -> -151985.02
B43: SP | C43: 0 | D43: Tangible Assets | E43: =+_xlfn.NUMBERVALUE(LEFT(F43,6)) -> 100443 | F43: 100443 - F/Amm Mobili E Macchine Ordinarie D'ufficio | H43: 395317.49 | I43: =+G43-H43 -> -395317.49 | J43: =+_xlfn.XLOOKUP(E43,[1]BDV!$F:$F,[1]BDV!$AC:$AC) -> -390059.69 | K43: =+J43/6*8 -> -520079.59 | L43: =+K43-I43 -> -124762.1
B44: SP | C44: 0 | D44: Tangible Assets | E44: =+_xlfn.NUMBERVALUE(LEFT(F44,6)) -> 100445 | F44: 100445 - F/Amm Macchine Elettromeccaniche D'ufficio | H44: 237452.24 | I44: =+G44-H44 -> -237452.24 | J44: =+_xlfn.XLOOKUP(E44,[1]BDV!$F:$F,[1]BDV!$AC:$AC) -> -230985.9 | K44: =+J44/6*8 -> -307981.2 | L44: =+K44-I44 -> -70528.96
B45: SP | C45: 0 | D45: Tangible Assets | E45: =+_xlfn.NUMBERVALUE(LEFT(F45,6)) -> 100447 | F45: 100447 - F/Amm Autoveicoli E Autocarri | H45: 666067.87 | I45: =+G45-H45 -> -666067.87 | J45: =+_xlfn.XLOOKUP(E45,[1]BDV!$F:$F,[1]BDV!$AC:$AC) -> -662807.72 | K45: =+J45/6*8 -> -883743.63 | L45: =+K45-I45 -> -217675.76
B46: SP | C46: 0 | D46: Tangible Assets | E46: =+_xlfn.NUMBERVALUE(LEFT(F46,6)) -> 100449 | F46: 100449 - F/Amm Autovetture | H46: 88911.25 | I46: =+G46-H46 -> -88911.25 | J46: =+_xlfn.XLOOKUP(E46,[1]BDV!$F:$F,[1]BDV!$AC:$AC) -> -88175.81 | K46: =+J46/6*8 -> -117567.75 | L46: =+K46-I46 -> -28656.497
B47: SP | C47: 0 | D47: Tangible Assets | E47: =+_xlfn.NUMBERVALUE(LEFT(F47,6)) -> 100451 | F47: 100451 - F/Amm Appar. Radiomobili | H47: 43338.58 | I47: =+G47-H47 -> -43338.58 | J47: =+_xlfn.XLOOKUP(E47,[1]BDV!$F:$F,[1]BDV!$AC:$AC) -> -43114.12 | K47: =+J47/6*8 -> -57485.493 | L47: =+K47-I47 -> -14146.913
B48: SP | C48: 0 | D48: Tangible Assets | E48: =+_xlfn.NUMBERVALUE(LEFT(F48,6)) -> 100453 | F48: 100453 - Arredamento | G48: 6766 | I48: =+G48-H48 -> 6766 | J48: =+_xlfn.XLOOKUP(E48,[1]BDV!$F:$F,[1]BDV!$AC:$AC) -> 6766 | K48: =+J48/6*8 -> 9021.3333 | L48: =+K48-I48 -> 2255.3333
B49: SP | C49: 0 | D49: Tangible Assets | E49: =+_xlfn.NUMBERVALUE(LEFT(F49,6)) -> 100455 | F49: 100455 - F/Amm Arredamento | H49: 6367.3 | I49: =+G49-H49 -> -6367.3 | J49: =+_xlfn.XLOOKUP(E49,[1]BDV!$F:$F,[1]BDV!$AC:$AC) -> -6353.75 | K49: =+J49/6*8 -> -8471.6667 | L49: =+K49-I49 -> -2104.3667
B50: SP | C50: FV | D50: Tangible Assets | E50: =+_xlfn.NUMBERVALUE(LEFT(F50,6)) -> 100457 | F50: 100457 - Immobiliazioni Materiali In Corso - FV Lizzano | G50: 81349.91 | I50: =+G50-H50 -> 81349.91 | J50: =+_xlfn.XLOOKUP(E50,[1]BDV!$F:$F,[1]BDV!$AC:$AC) -> 81349.91 | K50: =+J50/6*8 -> 108466.55 | L50: =+K50-I50 -> 27116.637
B51: SP | C51: FV | D51: Tangible Assets | E51: =+_xlfn.NUMBERVALUE(LEFT(F51,6)) -> 100459 | F51: 100459 - Fornitori Imm. Materiali c/acconti - FV Mucca Nera | G51: 5035.95 | I51: =+G51-H51 -> 5035.95 | J51: =+_xlfn.XLOOKUP(E51,[1]BDV!$F:$F,[1]BDV!$AC:$AC) -> 5035.95 | K51: =+J51/6*8 -> 6714.6 | L51: =+K51-I51 -> 1678.65
B52: SP | C52: 0 | D52: Tangible Assets | E52: =+_xlfn.NUMBERVALUE(LEFT(F52,6)) -> 100461 | F52: 100461 - Fornitori Imm. Materiali c/acconti | G52: 46863.2 | I52: =+G52-H52 -> 46863.2 | J52: =+_xlfn.XLOOKUP(E52,[1]BDV!$F:$F,[1]BDV!$AC:$AC) -> 44863.2 | K52: =+J52/6*8 -> 59817.6 | L52: =+K52-I52 -> 12954.4
B53: SP | C53: 0 | D53: Tangible Assets | E53: =+_xlfn.NUMBERVALUE(LEFT(F53,6)) -> 100463 | F53: 100463 - Fabbricati Ind.Li e Comm. Li (MiniPia) | G53: 542422.65 | I53: =+G53-H53 -> 542422.65 | J53: =+_xlfn.XLOOKUP(E53,[1]BDV!$F:$F,[1]BDV!$AC:$AC) -> 542422.65 | K53: =+J53/6*8 -> 723230.2 | L53: =+K53-I53 -> 180807.55
B54: SP | C54: 0 | D54: Tangible Assets | E54: =+_xlfn.NUMBERVALUE(LEFT(F54,6)) -> 100465 | F54: 100465 - F/Amm Fabbricati Ind.Li E Comm. Li (MiniPia) | H54: 59135.35 | I54: =+G54-H54 -> -59135.35 | J54: =+_xlfn.XLOOKUP(E54,[1]BDV!$F:$F,[1]BDV!$AC:$AC) -> -56423.24 | K54: =+J54/6*8 -> -75230.987 | L54: =+K54-I54 -> -16095.637
B55: SP | C55: 0 | D55: Tangible Assets | E55: =+_xlfn.NUMBERVALUE(LEFT(F55,6)) -> 100467 | F55: 100467 - F/Amm. Beni Inferiori Ai 516,46 Euro | H55: 18097.31 | I55: =+G55-H55 -> -18097.31 | J55: =+_xlfn.XLOOKUP(E55,[1]BDV!$F:$F,[1]BDV!$AC:$AC) -> -18097.31 | K55: =+J55/6*8 -> -24129.747 | L55: =+K55-I55 -> -6032.4367
B56: SP | C56: FV | D56: Tangible Assets | E56: =+_xlfn.NUMBERVALUE(LEFT(F56,6)) -> 100469 | F56: 100469 - Immobiliazioni Materiali In Corso - FV Avezzano 3 | G56: 1164176.8 | I56: =+G56-H56 -> 1164176.8 | J56: =+_xlfn.XLOOKUP(E56,[1]BDV!$F:$F,[1]BDV!$AC:$AC) -> 967268.17 | K56: =+J56/6*8 -> 1289690.9 | L56: =+K56-I56 -> 125514.12
B57: SP | C57: FV | D57: Tangible Assets | E57: =+_xlfn.NUMBERVALUE(LEFT(F57,6)) -> 100471 | F57: 100471 - Immobiliazioni Materiali In Corso - FV Montorio al Vomano 1 | G57: 1645137.9 | I57: =+G57-H57 -> 1645137.9 | J57: =+_xlfn.XLOOKUP(E57,[1]BDV!$F:$F,[1]BDV!$AC:$AC) -> 1301320.5 | K57: =+J57/6*8 -> 1735094 | L57: =+K57-I57 -> 89956.01
B58: SP | C58: FV | D58: Tangible Assets | E58: =+_xlfn.NUMBERVALUE(LEFT(F58,6)) -> 100473 | F58: 100473 - Immobiliazioni Materiali In Corso - FV Giulianova | G58: 921393.76 | I58: =+G58-H58 -> 921393.76 | J58: =+_xlfn.XLOOKUP(E58,[1]BDV!$F:$F,[1]BDV!$AC:$AC) -> 865955.56 | K58: =+J58/6*8 -> 1154607.4 | L58: =+K58-I58 -> 233213.65
B59: SP | C59: FV | D59: Tangible Assets | E59: =+_xlfn.NUMBERVALUE(LEFT(F59,6)) -> 100475 | F59: 100475 - Immobiliazioni Materiali In Corso - FV Borgorose | G59: 973496.14 | I59: =+G59-H59 -> 973496.14 | J59: =+_xlfn.XLOOKUP(E59,[1]BDV!$F:$F,[1]BDV!$AC:$AC) -> 891789.26 | K59: =+J59/6*8 -> 1189052.3 | L59: =+K59-I59 -> 215556.21
B60: SP | C60: FV | D60: Tangible Assets | E60: =+_xlfn.NUMBERVALUE(LEFT(F60,6)) -> 100477 | F60: 100477 - Immobiliazioni Materiali In Corso - FV Copertino 1 | G60: 1115669.6 | I60: =+G60-H60 -> 1115669.6 | J60: =+_xlfn.XLOOKUP(E60,[1]BDV!$F:$F,[1]BDV!$AC:$AC) -> 1010700.7 | K60: =+J60/6*8 -> 1347600.9 | L60: =+K60-I60 -> 231931.36
B61: SP | C61: FV | D61: Tangible Assets | E61: =+_xlfn.NUMBERVALUE(LEFT(F61,6)) -> 100479 | F61: 100479 - Immobiliazioni Materiali In Corso - FV Corfinio | G61: 829090.49 | I61: =+G61-H61 -> 829090.49 | J61: =+_xlfn.XLOOKUP(E61,[1]BDV!$F:$F,[1]BDV!$AC:$AC) -> 775202.49 | K61: =+J61/6*8 -> 1033603.3 | L61: =+K61-I61 -> 204512.83
B62: SP | C62: FV | D62: Tangible Assets | E62: =+_xlfn.NUMBERVALUE(LEFT(F62,6)) -> 100481 | F62: 100481 - Immobiliazioni Materiali In Corso - FV Avezzano 4 | G62: 1087160.8 | I62: =+G62-H62 -> 1087160.8 | J62: =+_xlfn.XLOOKUP(E62,[1]BDV!$F:$F,[1]BDV!$AC:$AC) -> 1032784.2 | K62: =+J62/6*8 -> 1377045.5 | L62: =+K62-I62 -> 289884.77
B63: SP | C63: FV | D63: Tangible Assets | E63: =+_xlfn.NUMBERVALUE(LEFT(F63,6)) -> 100483 | F63: 100483 - Immobiliazioni Materiali In Corso - FV Montorio al Vomano 3 | G63: 991956.75 | I63: =+G63-H63 -> 991956.75 | J63: =+_xlfn.XLOOKUP(E63,[1]BDV!$F:$F,[1]BDV!$AC:$AC) -> 925345.51 | K63: =+J63/6*8 -> 1233794 | L63: =+K63-I63 -> 241837.26
B64: SP | C64: FV | D64: Tangible Assets | E64: =+_xlfn.NUMBERVALUE(LEFT(F64,6)) -> 100485 | F64: 100485 - Immobiliazioni Materiali In Corso - FV Montorio al Vomano 4 | G64: 916403.37 | I64: =+G64-H64 -> 916403.37 | J64: =+_xlfn.XLOOKUP(E64,[1]BDV!$F:$F,[1]BDV!$AC:$AC) -> 816241.22 | K64: =+J64/6*8 -> 1088321.6 | L64: =+K64-I64 -> 171918.26
B65: SP | C65: FV | D65: Tangible Assets | E65: =+_xlfn.NUMBERVALUE(LEFT(F65,6)) -> 100487 | F65: 100487 - Immobiliazioni Materiali In Corso - FV Collarmele | G65: 838538.06 | I65: =+G65-H65 -> 838538.06 | J65: =+_xlfn.XLOOKUP(E65,[1]BDV!$F:$F,[1]BDV!$AC:$AC) -> 572027.84 | K65: =+J65/6*8 -> 762703.79 | L65: =+K65-I65 -> -75834.273
B66: SP | C66: FV | D66: Tangible Assets | E66: =+_xlfn.NUMBERVALUE(LEFT(F66,6)) -> 100489 | F66: 100489 - Immobiliazioni Materiali In Corso - FV Campi Salentina 1 | G66: 1087448.5 | I66: =+G66-H66 -> 1087448.5 | J66: =+_xlfn.XLOOKUP(E66,[1]BDV!$F:$F,[1]BDV!$AC:$AC) -> 1062632.9 | K66: =+J66/6*8 -> 1416843.8 | L66: =+K66-I66 -> 329395.34
B67: SP | C67: FV | D67: Tangible Assets | E67: =+_xlfn.NUMBERVALUE(LEFT(F67,6)) -> 100491 | F67: 100491 - Immobiliazioni Materiali In Corso - FV Copertino 2 | G67: 766621.33 | I67: =+G67-H67 -> 766621.33 | J67: =+_xlfn.XLOOKUP(E67,[1]BDV!$F:$F,[1]BDV!$AC:$AC) -> 536988.21 | K67: =+J67/6*8 -> 715984.28 | L67: =+K67-I67 -> -50637.05
... B71: SP | C71: FV | D71: Tangible Assets | E71: =+_xlfn.NUMBERVALUE(LEFT(F71,6)) -> 100499 | F71: 100499 - Immobiliazioni Materiali In Corso - FV Tricase | G71: 143607.9 | I71: =+G71-H71 -> 143607.9 | J71: =+_xlfn.XLOOKUP(E71,[1]BDV!$F:$F,[1]BDV!$AC:$AC) -> 129020.33 | K71: =+J71/6*8 -> 172027.11 | L71: =+K71-I71 -> 28419.207
B72: SP | C72: 0 | D72: Intangible Assets | E72: =+_xlfn.NUMBERVALUE(LEFT(F72,6)) -> 100501 | F72: 100501 - Diritti D'uso | G72: 3399355.5 | I72: =+G72-H72 -> 3399355.5 | J72: =+_xlfn.XLOOKUP(E72,[1]BDV!$F:$F,[1]BDV!$AC:$AC) -> 3399355.5 | K72: =+J72/6*8 -> 4532474.1 | L72: =+K72-I72 -> 1133118.5
B73: SP | C73: 0 | D73: Intangible Assets | E73: =+_xlfn.NUMBERVALUE(LEFT(F73,6)) -> 100503 | F73: 100503 - Fondo amm.to diritti d'uso | H73: 1302951.5 | I73: =+G73-H73 -> -1302951.5 | J73: =+_xlfn.XLOOKUP(E73,[1]BDV!$F:$F,[1]BDV!$AC:$AC) -> -1302951.5 | K73: =+J73/6*8 -> -1737268.7 | L73: =+K73-I73 -> -434317.17
B74: SP | C74: FV | D74: Tangible Assets | E74: =+_xlfn.NUMBERVALUE(LEFT(F74,6)) -> 100505 | F74: 100505 - Immobiliazioni Materiali In Corso - FV San Giorgio Ionico | G74: 154101.24 | I74: =+G74-H74 -> 154101.24 | J74: =+_xlfn.XLOOKUP(E74,[1]BDV!$F:$F,[1]BDV!$AC:$AC) -> 0 | K74: =+J74/6*8 -> 0 | L74: =+K74-I74 -> -154101.24
B75: SP | C75: FV | D75: Tangible Assets | E75: =+_xlfn.NUMBERVALUE(LEFT(F75,6)) -> 100509 | F75: 100509 - Immobiliazioni Materiali In Corso - FV Avezzano 5 | G75: 57320.6 | I75: =+G75-H75 -> 57320.6 | J75: =+_xlfn.XLOOKUP(E75,[1]BDV!$F:$F,[1]BDV!$AC:$AC) -> 57320.6 | K75: =+J75/6*8 -> 76427.467 | L75: =+K75-I75 -> 19106.867
B76: SP | C76: FV | D76: Tangible Assets | E76: =+_xlfn.NUMBERVALUE(LEFT(F76,6)) -> 100513 | F76: 100513 - Immobiliazioni Materiali In Corso - FV Taviano 2 | G76: 411699.71 | I76: =+G76-H76 -> 411699.71 | J76: =+_xlfn.XLOOKUP(E76,[1]BDV!$F:$F,[1]BDV!$AC:$AC) -> 244636.05 | K76: =+J76/6*8 -> 326181.4 | L76: =+K76-I76 -> -85518.31
B77: SP | C77: FV | D77: Tangible Assets | E77: =+_xlfn.NUMBERVALUE(LEFT(F77,6)) -> 100515 | F77: 100515 - Immobiliazioni Materiali In Corso - FV Scurcola 1 | G77: 110808.86 | I77: =+G77-H77 -> 110808.86 | J77: =+_xlfn.XLOOKUP(E77,[1]BDV!$F:$F,[1]BDV!$AC:$AC) -> 93466.25 | K77: =+J77/6*8 -> 124621.67 | L77: =+K77-I77 -> 13812.807
B78: SP | C78: 0 | D78: Financial Assets | E78: =+_xlfn.NUMBERVALUE(LEFT(F78,6)) -> 100601 | F78: 100601 - Partecipazioni Imp. Controllate | G78: 12654422 | I78: =+G78-H78 -> 12654422 | J78: =+_xlfn.XLOOKUP(E78,[1]BDV!$F:$F,[1]BDV!$AC:$AC) -> 7297751 | K78: =+J78/6*8 -> 9730334.6 | L78: =+K78-I78 -> -2924087.2
B79: SP | C79: 0 | D79: Financial Assets | E79: =+_xlfn.NUMBERVALUE(LEFT(F79,6)) -> 100603 | F79: 100603 - Partecipazioni Imp. Collegate | G79: 491899.5 | I79: =+G79-H79 -> 491899.5 | J79: =+_xlfn.XLOOKUP(E79,[1]BDV!$F:$F,[1]BDV!$AC:$AC) -> 491899.5 | K79: =+J79/6*8 -> 655866 | L79: =+K79-I79 -> 163966.5
B80: SP | C80: 0 | D80: Financial Assets | E80: =+_xlfn.NUMBERVALUE(LEFT(F80,6)) -> 100605 | F80: 100605 - Partecipazioni Imp. Altre Imprese | G80: 46954.62 | I80: =+G80-H80 -> 46954.62 | J80: =+_xlfn.XLOOKUP(E80,[1]BDV!$F:$F,[1]BDV!$AC:$AC) -> 7754.62 | K80: =+J80/6*8 -> 10339.493 | L80: =+K80-I80 -> -36615.127
B81: SP | C81: 0 | D81: Other Credit | E81: =+_xlfn.NUMBERVALUE(LEFT(F81,6)) -> 100607 | F81: 100607 - Crediti Vs. Imp. Controllate | G81: 17114347 | I81: =+G81-H81 -> 17114347 | J81: =+_xlfn.XLOOKUP(E81,[1]BDV!$F:$F,[1]BDV!$AC:$AC) -> 16044347 | K81: =+J81/6*8 -> 21392463 | L81: =+K81-I81 -> 4278115.7
B82: SP | C82: 0 | D82: Other Credit | E82: =+_xlfn.NUMBERVALUE(LEFT(F82,6)) -> 100611 | F82: 100611 - Crediti Vs. Imp. Altre Imprese | G82: 3992 | I82: =+G82-H82 -> 3992 | J82: =+_xlfn.XLOOKUP(E82,[1]BDV!$F:$F,[1]BDV!$AC:$AC) -> 3992 | K82: =+J82/6*8 -> 5322.6667 | L82: =+K82-I82 -> 1330.6667
B83: SP | C83: 0 | D83: Other Credit | E83: =+_xlfn.NUMBERVALUE(LEFT(F83,6)) -> 100615 | F83: 100615 - Crediti Vs. Altri | G83: 120180.32 | I83: =+G83-H83 -> 120180.32 | J83: =+_xlfn.XLOOKUP(E83,[1]BDV!$F:$F,[1]BDV!$AC:$AC) -> 150816.43 | K83: =+J83/6*8 -> 201088.57 | L83: =+K83-I83 -> 80908.253
B84: SP | C84: 0 | D84: Other Credit | E84: =+_xlfn.NUMBERVALUE(LEFT(F84,6)) -> 100621 | F84: 100621 - Depositi Cauzioniari Commerciali | G84: 135934.92 | I84: =+G84-H84 -> 135934.92 | J84: =+_xlfn.XLOOKUP(E84,[1]BDV!$F:$F,[1]BDV!$AC:$AC) -> 134201.73 | K84: =+J84/6*8 -> 178935.64 | L84: =+K84-I84 -> 43000.72
B85: SP | C85: 0 | D85: Other Reserves | E85: =+_xlfn.NUMBERVALUE(LEFT(F85,6)) -> 100622 | F85: 100622 - Soci c/sottoscrizione | G85: 108000 | I85: =+G85-H85 -> 108000 | J85: =+_xlfn.XLOOKUP(E85,[1]BDV!$F:$F,[1]BDV!$AC:$AC) -> 108000 | K85: =+J85/6*8 -> 144000 | L85: =+K85-I85 -> 36000
B86: SP | C86: 0 | D86: Financial Assets | E86: =+_xlfn.NUMBERVALUE(LEFT(F86,6)) -> 100623 | F86: 100623 - Crediti Vs. SPV Città Metropolitana Venezia II | G86: 2888550.2 | I86: =+G86-H86 -> 2888550.2 | J86: =+_xlfn.XLOOKUP(E86,[1]BDV!$F:$F,[1]BDV!$AC:$AC) -> 2888550.2 | K86: =+J86/6*8 -> 3851400.3 | L86: =+K86-I86 -> 962850.07
B87: SP | C87: 0 | D87: Financial Assets | E87: =+_xlfn.NUMBERVALUE(LEFT(F87,6)) -> 100625 | F87: 100625 - Crediti Vs. SPV Crosia Smart City | G87: 894050.18 | I87: =+G87-H87 -> 894050.18 | J87: =+_xlfn.XLOOKUP(E87,[1]BDV!$F:$F,[1]BDV!$AC:$AC) -> 894050.18 | K87: =+J87/6*8 -> 1192066.9 | L87: =+K87-I87 -> 298016.73
B88: SP | C88: 0 | D88: Financial Assets | E88: =+_xlfn.NUMBERVALUE(LEFT(F88,6)) -> 100627 | F88: 100627 - Crediti Vs. SPV Spezzano Albanese Smart City | G88: 978336.66 | I88: =+G88-H88 -> 978336.66 | J88: =+_xlfn.XLOOKUP(E88,[1]BDV!$F:$F,[1]BDV!$AC:$AC) -> 978336.66 | K88: =+J88/6*8 -> 1304448.9 | L88: =+K88-I88 -> 326112.22
B89: SP | C89: 0 | D89: Financial Assets | E89: =+_xlfn.NUMBERVALUE(LEFT(F89,6)) -> 100635 | F89: 100635 - Credito Acquisizione Alfano_Partecipazione TECS | G89: 7918688 | I89: =+G89-H89 -> 7918688 | J89: =+_xlfn.XLOOKUP(E89,[1]BDV!$F:$F,[1]BDV!$AC:$AC) -> 7300000 | K89: =+J89/6*8 -> 9733333.3 | L89: =+K89-I89 -> 1814645.3
... B92: SP | C92: 0 | D92: Trade Receivables | E92: =+_xlfn.NUMBERVALUE(LEFT(F92,6)) -> 140201 | F92: 140201 - Crediti Vs Clienti Nazionali | G92: 13611788 | I92: =+G92-H92 -> 13611788 | J92: =+_xlfn.XLOOKUP(E92,[1]BDV!$F:$F,[1]BDV!$AC:$AC) -> 11427295 | K92: =+J92/6*8 -> 15236393 | L92: =+K92-I92 -> 1624604.8
B93: SP | C93: 0 | D93: Trade Receivables | E93: =+_xlfn.NUMBERVALUE(LEFT(F93,6)) -> 140205 | F93: 140205 - Fondo Svalutazione Crediti | H93: 590461.28 | I93: =+G93-H93 -> -590461.28 | J93: =+_xlfn.XLOOKUP(E93,[1]BDV!$F:$F,[1]BDV!$AC:$AC) -> -590461.28 | K93: =+J93/6*8 -> -787281.71 | L93: =+K93-I93 -> -196820.43
B94: SP | C94: 0 | D94: Trade Receivables | E94: =+_xlfn.NUMBERVALUE(LEFT(F94,6)) -> 140219 | F94: 140219 - Credito v/GSE (conto termico) | G94: 146.4 | I94: =+G94-H94 -> 146.4 | J94: =+_xlfn.XLOOKUP(E94,[1]BDV!$F:$F,[1]BDV!$AC:$AC) -> 4804.39 | K94: =+J94/6*8 -> 6405.8533 | L94: =+K94-I94 -> 6259.4533
B95: SP | C95: 0 | D95: Trade Receivables | E95: =+_xlfn.NUMBERVALUE(LEFT(F95,6)) -> 140221 | F95: 140221 - Credito v/Regione Basilicata | G95: 113167.29 | I95: =+G95-H95 -> 113167.29 | J95: =+_xlfn.XLOOKUP(E95,[1]BDV!$F:$F,[1]BDV!$AC:$AC) -> 113167.29 | K95: =+J95/6*8 -> 150889.72 | L95: =+K95-I95 -> 37722.43
B96: SP | C96: 0 | D96: Tax Credit | E96: =+_xlfn.NUMBERVALUE(LEFT(F96,6)) -> 140223 | F96: 140223 - Crediti v/imprese controllanti per consolidato fiscale | G96: 116452.71 | I96: =+G96-H96 -> 116452.71 | J96: =+_xlfn.XLOOKUP(E96,[1]BDV!$F:$F,[1]BDV!$AC:$AC) -> 116452.71 | K96: =+J96/6*8 -> 155270.28 | L96: =+K96-I96 -> 38817.57
B97: SP | C97: 0 | D97: Trade Receivables | E97: =+_xlfn.NUMBERVALUE(LEFT(F97,6)) -> 140225 | F97: 140225 - Crediti Vs Clienti Esteri | G97: 1525 | I97: =+G97-H97 -> 1525 | J97: =+_xlfn.XLOOKUP(E97,[1]BDV!$F:$F,[1]BDV!$AC:$AC) -> 1525 | K97: =+J97/6*8 -> 2033.3333 | L97: =+K97-I97 -> 508.33333
B98: SP | C98: 0 | D98: Other Credit | E98: =+_xlfn.NUMBERVALUE(LEFT(F98,6)) -> 140227 | F98: 140227 - Crediti Intercompany | G98: 563849.75 | I98: =+G98-H98 -> 563849.75 | J98: =+_xlfn.XLOOKUP(E98,[1]BDV!$F:$F,[1]BDV!$AC:$AC) -> 477931.6 | K98: =+J98/6*8 -> 637242.13 | L98: =+K98-I98 -> 73392.383
B99: SP | C99: 0 | D99: Trade Receivables | E99: =+_xlfn.NUMBERVALUE(LEFT(F99,6)) -> 140229 | F99: 140229 - Crediti Vs Chioggia Servizi | G99: 1700391.7 | I99: =+G99-H99 -> 1700391.7 | J99: =+_xlfn.XLOOKUP(E99,[1]BDV!$F:$F,[1]BDV!$AC:$AC) -> 2167245.9 | K99: =+J99/6*8 -> 2889661.2 | L99: =+K99-I99 -> 1189269.5
B100: SP | C100: 0 | D100: Financial Assets | E100: =+_xlfn.NUMBERVALUE(LEFT(F100,6)) -> 160201 | F100: 160201 - Altri Titoli | G100: 461829.21 | I100: =+G100-H100 -> 461829.21 | J100: =+_xlfn.XLOOKUP(E100,[1]BDV!$F:$F,[1]BDV!$AC:$AC) -> 458495.88 | K100: =+J100/6*8 -> 611327.84 | L100: =+K100-I100 -> 149498.63
B101: CE | C101: R | D101: Other Revenues | E101: =+_xlfn.NUMBERVALUE(LEFT(F101,6)) -> 160203 | F101: 160203 - Spese Anticipate | H101: 756.79 | I101: =+G101-H101 -> -756.79 | J101: =+_xlfn.XLOOKUP(E101,[1]BDV!$F:$F,[1]BDV!$AC:$AC) -> 34.6 | K101: =+J101/6*8 -> 46.133333 | L101: =+K101-I101 -> 802.92333
B102: SP | C102: 0 | D102: Other Credit | E102: =+_xlfn.NUMBERVALUE(LEFT(F102,6)) -> 160205 | F102: 160205 - Anticipo Bolla Doganale | H102: 28579.75 | I102: =+G102-H102 -> -28579.75 | J102: =+_xlfn.XLOOKUP(E102,[1]BDV!$F:$F,[1]BDV!$AC:$AC) -> 0 | K102: =+J102/6*8 -> 0 | L102: =+K102-I102 -> 28579.75
B103: SP | C103: 0 | D103: Trade Receivables | E103: =+_xlfn.NUMBERVALUE(LEFT(F103,6)) -> 160207 | F103: 160207 - Fatture Da Emettere | G103: 17628920 | I103: =+G103-H103 -> 17628920 | J103: =+_xlfn.XLOOKUP(E103,[1]BDV!$F:$F,[1]BDV!$AC:$AC) -> 18675003 | K103: =+J103/6*8 -> 24900003 | L103: =+K103-I103 -> 7271083.2
B104: SP | C104: 0 | D104: Other Credit | E104: =+_xlfn.NUMBERVALUE(LEFT(F104,6)) -> 160208 | F104: 160208 - Crediti verso Altri | G104: 353316.06 | I104: =+G104-H104 -> 353316.06 | J104: =+_xlfn.XLOOKUP(E104,[1]BDV!$F:$F,[1]BDV!$AC:$AC) -> 353262.62 | K104: =+J104/6*8 -> 471016.83 | L104: =+K104-I104 -> 117700.77
B105: SP | C105: 0 | D105: Trade Payables | E105: =+_xlfn.NUMBERVALUE(LEFT(F105,6)) -> 160210 | F105: 160210 - Note di Credito Da Ricevere | G105: 147938.91 | I105: =+G105-H105 -> 147938.91 | J105: =+_xlfn.XLOOKUP(E105,[1]BDV!$F:$F,[1]BDV!$AC:$AC) -> 156035.08 | K105: =+J105/6*8 -> 208046.77 | L105: =+K105-I105 -> 60107.863
B106: SP | C106: 0 | D106: Trade Payables | E106: =+_xlfn.NUMBERVALUE(LEFT(F106,6)) -> 160212 | F106: 160212 - Fornitori C/Acconti | G106: 166102.55 | I106: =+G106-H106 -> 166102.55 | J106: =+_xlfn.XLOOKUP(E106,[1]BDV!$F:$F,[1]BDV!$AC:$AC) -> 211069.71 | K106: =+J106/6*8 -> 281426.28 | L106: =+K106-I106 -> 115323.73
B107: SP | C107: 0 | D107: Other Credit | E107: =+_xlfn.NUMBERVALUE(LEFT(F107,6)) -> 160216 | F107: 160216 - Crediti per ritenuta a garanzia | G107: 641999.5 | I107: =+G107-H107 -> 641999.5 | J107: =+_xlfn.XLOOKUP(E107,[1]BDV!$F:$F,[1]BDV!$AC:$AC) -> 619022.96 | K107: =+J107/6*8 -> 825363.95 | L107: =+K107-I107 -> 183364.45
B108: SP | C108: 0 | D108: Other Credit | E108: =+_xlfn.NUMBERVALUE(LEFT(F108,6)) -> 160218 | F108: 160218 - Crediti/Debiti v/Atlantico Spa | G108: 3335 | I108: =+G108-H108 -> 3335 | J108: =+_xlfn.XLOOKUP(E108,[1]BDV!$F:$F,[1]BDV!$AC:$AC) -> 3335 | K108: =+J108/6*8 -> 4446.6667 | L108: =+K108-I108 -> 1111.6667
B109: SP | C109: 0 | D109: Other Credit | E109: =+_xlfn.NUMBERVALUE(LEFT(F109,6)) -> 160220 | F109: 160220 - Crediti V/Socio Sofein Da Richiamare | G109: 5062.5 | I109: =+G109-H109 -> 5062.5 | J109: =+_xlfn.XLOOKUP(E109,[1]BDV!$F:$F,[1]BDV!$AC:$AC) -> 5062.5 | K109: =+J109/6*8 -> 6750 | L109: =+K109-I109 -> 1687.5
...

Sheet delta only CVS
G2: Costi Diretti | H2: =+SUMIFS(L:L,D:D,G2) -> -93229.13 | I2: minori costi
G3: Overheads | H3: =+SUMIFS(L:L,D:D,G3) -> -132393.35 | I3: minori costi
G4: Canone | H4: =+SUMIFS(L:L,D:D,G4) -> -1312065.4 | I4: Ricavi Inferiori
G5: Costruzioni Interne | H5: =+SUMIFS(L:L,D:D,G5) -> -527633.79 | I5: meno CapEx
G6: Personnel Costs | H6: =+SUMIFS(L:L,D:D,G6) -> -80137.637 | I6: minori costi
G7: Taxes overheads | H7: =+SUMIFS(L:L,D:D,G7) -> 5561.6633 | I7: più costi
G9: Extraordinary Item (Attive) | H9: =+SUMIFS(L:L,D:D,G9) -> -14015.393
G10: Other Revenues | H10: =+SUMIFS(L:L,D:D,G10) -> 1906.4267
G11: Depreciation and amortization | H11: =+SUMIFS(L:L,D:D,G11) -> 362659.95
G12: Financial Income | H12: =+SUMIFS(L:L,D:D,G12) -> 244924.5
G13: Financial Expenses | H13: =+SUMIFS(L:L,D:D,G13) -> 66454.707
G14: Taxes | H14: =+SUMIFS(L:L,D:D,G14) -> -34406
B16: Quadro | C16: Altro | D16: Ricla MG esteso | E16: Conto | F16: Account | G16: Debit | H16: Credit | I16: Agosto | J16: Giugno | K16: Giu RR | L16: Delta
B17: CE | C17: C | D17: Magazzino | E17: 800405 | F17: 800405 - Materie Prime C/Rim Iniziali | G17: 2131263.2 | I17: 2131263.2 | J17: 2131263.2 | K17: =+J17/6*8 -> 2841684.3 | L17: =+K17-I17 -> 710421.07
B18: CE | C18: C | D18: Depreciation and amortization | E18: 760601 | F18: 760601 - Amm.To Lav. Straord. Beni Di Terzi | G18: 4362356 | I18: 4362356 | J18: 3547371 | K18: =+J18/6*8 -> 4729828 | L18: =+K18-I18 -> 367471.93
B19: CE | C19: C | D19: Costi Diretti | E19: 680201 | F19: 680201 - Merci C/Acquisti Nazionali | G19: 7647933.3 | I19: 7647933.3 | J19: 5934074.4 | K19: =+J19/6*8 -> 7912099.2 | L19: =+K19-I19 -> 264165.87
B20: CE | C20: C | D20: Financial Income | E20: 900201 | F20: 900201 - Differenziale Derivati Di Copertura | H20: 214475.36 | I20: -214475.36 | J20: 16821.08 | K20: =+J20/6*8 -> 22428.107 | L20: =+K20-I20 -> 236903.47
B21: CE | C21: C | D21: Costi Diretti | E21: 700203 | F21: 700203 - Lavoraz. Di Terzi P/Prod. Servizi | G21: 11105305 | I21: 11105305 | J21: 8415918.3 | K21: =+J21/6*8 -> 11221224 | L21: =+K21-I21 -> 115919.65
B22: CE | C22: C | D22: Overheads | E22: 700407 | F22: 700407 - Comp. Prof. Attinenti Attivita' C/Rit. | G22: 1078802.8 | I22: 1078802.8 | J22: 887136.03 | K22: =+J22/6*8 -> 1182848 | L22: =+K22-I22 -> 104045.28
B23: CE | C23: C | D23: Financial Expenses | E23: 920215 | F23: 920215 - Interessi Da Debiti Verso Banche_Linea Senior | G23: 487688.42 | I23: 487688.42 | J23: 418991.35 | K23: =+J23/6*8 -> 558655.13 | L23: =+K23-I23 -> 70966.713
B24: CE | C24: C | D24: Overheads | E24: 700409 | F24: 700409 - Comp. Prof. Attinenti Attivita' | G24: 403472.76 | I24: 403472.76 | J24: 351421.82 | K24: =+J24/6*8 -> 468562.43 | L24: =+K24-I24 -> 65089.667
B25: CE | C25: C | D25: Taxes overheads | E25: 880207 | F25: 880207 - Altre Imposte E Tasse Inded. | G25: 166401.98 | I25: 166401.98 | J25: 165226.79 | K25: =+J25/6*8 -> 220302.39 | L25: =+K25-I25 -> 53900.407
B26: CE | C26: C | D26: Overheads | E26: 701607 | F26: 701607 - Pubb. E Markt | G26: 161022.3 | I26: 161022.3 | J26: 155751.2 | K26: =+J26/6*8 -> 207668.27 | L26: =+K26-I26 -> 46645.967
B27: CE | C27: C | D27: Personnel Costs | E27: 740609 | F27: 740609 - Oneri Previdenziali I.N.P.S. - Dirigenti | G27: 336838.91 | I27: 336838.91 | J27: 279271.38 | K27: =+J27/6*8 -> 372361.84 | L27: =+K27-I27 -> 35522.93
B28: CE | C28: C | D28: Personnel Costs | E28: 741201 | F28: 741201 - Trattamento Di Fine Rapporto | G28: 140397.95 | I28: 140397.95 | J28: 127457.54 | K28: =+J28/6*8 -> 169943.39 | L28: =+K28-I28 -> 29545.437
B29: CE | C29: C | D29: Overheads | E29: 700213 | F29: 700213 - Manut. E Rip. Ord. Beni Di Terzi | G29: 77150.23 | I29: 77150.23 | J29: 77150.23 | K29: =+J29/6*8 -> 102866.97 | L29: =+K29-I29 -> 25716.743
B30: CE | C30: C | D30: Overheads | E30: 702411 | F30: 702411 - Altre Assicurazioni | G30: 191525.62 | I30: 191525.62 | J30: 161362.36 | K30: =+J30/6*8 -> 215149.81 | L30: =+K30-I30 -> 23624.193
B31: CE | C31: C | D31: Personnel Costs | E31: 741607 | F31: 741607 - Welfare | G31: 97340.13 | I31: 97340.13 | J31: 86889.27 | K31: =+J31/6*8 -> 115852.36 | L31: =+K31-I31 -> 18512.23
B32: CE | C32: C | D32: Overheads | E32: 700801 | F32: 700801 - Commissioni Bancarie | G32: 80784.01 | I32: 80784.01 | J32: 68487.55 | K32: =+J32/6*8 -> 91316.733 | L32: =+K32-I32 -> 10532.723
... B37: CE | C37: C | D37: Overheads | E37: 702405 | F37: 702405 - Assicurazioni R.C. | G37: 30902.54 | I37: 30902.54 | J37: 29972.01 | K37: =+J37/6*8 -> 39962.68 | L37: =+K37-I37 -> 9060.14
B38: CE | C38: R | D38: Financial Income | E38: 900209 | F38: 900209 - Interessi Attivi | H38: 19111.54 | I38: -19111.54 | J38: -8317.88 | K38: =+J38/6*8 -> -11090.507 | L38: =+K38-I38 -> 8021.0333
B39: CE | C39: C | D39: Overheads | E39: 702201 | F39: 702201 - Spese Telefoniche | G39: 70568.7 | I39: 70568.7 | J39: 58085.49 | K39: =+J39/6*8 -> 77447.32 | L39: =+K39-I39 -> 6878.62
B40: CE | C40: C | D40: Overheads | E40: 700209 | F40: 700209 - Manut. E Rip. Autocarri | G40: 58945.79 | I40: 58945.79 | J40: 48624.7 | K40: =+J40/6*8 -> 64832.933 | L40: =+K40-I40 -> 5887.1433
B41: CE | C41: C | D41: Overheads | E41: 881001 | F41: 881001 - Erog. Liberali Ded. | G41: 24265 | I41: 24265 | J41: 22265 | K41: =+J41/6*8 -> 29686.667 | L41: =+K41-I41 -> 5421.6667
B42: CE | C42: R | D42: Extraordinary Item (Attive) | E42: 660407 | F42: 660407 - Sopravvenienze Attive | H42: 23438.42 | I42: -23438.42 | J42: -13766.53 | K42: =+J42/6*8 -> -18355.373 | L42: =+K42-I42 -> 5083.0467
B43: CE | C43: C | D43: Overheads | E43: 700815 | F43: 700815 - Spese Per Trasferte | G43: 119529.99 | I43: 119529.99 | J43: 93192.04 | K43: =+J43/6*8 -> 124256.05 | L43: =+K43-I43 -> 4726.0633
B44: CE | C44: C | D44: Personnel Costs | E44: 740207 | F44: 740207 - Rimborsi Da Nota Spese | G44: 101489.14 | I44: 101489.14 | J44: 79544.46 | K44: =+J44/6*8 -> 106059.28 | L44: =+K44-I44 -> 4570.14
B45: CE | C45: C | D45: Personnel Costs | E45: 700403 | F45: 700403 - Compensi A Collaboratori Co.Co.Co. | G45: 242668.54 | I45: 242668.54 | J45: 184694.93 | K45: =+J45/6*8 -> 246259.91 | L45: =+K45-I45 -> 3591.3667
B46: CE | C46: R | D46: Other Revenues | E46: 660403 | F46: 660403 - Plusvalenze | H46: 3152.3 | I46: -3152.3 | J46: 0 | K46: =+J46/6*8 -> 0 | L46: =+K46-I46 -> 3152.3
B47: CE | C47: C | D47: Overheads | E47: 702407 | F47: 702407 - Assicurazioni R.C.A. Parz. Deduc. | G47: 15259.39 | I47: 15259.39 | J47: 13689.72 | K47: =+J47/6*8 -> 18252.96 | L47: =+K47-I47 -> 2993.57
B48: CE | C48: C | D48: Overheads | E48: 680601 | F48: 680601 - Carburante | G48: 79349.64 | I48: 79349.64 | J48: 61385.36 | K48: =+J48/6*8 -> 81847.147 | L48: =+K48-I48 -> 2497.5067
B49: CE | C49: C | D49: Overheads | E49: 701811 | F49: 701811 - Revisione Contabile | G49: 6820 | I49: 6820 | J49: 6820 | K49: =+J49/6*8 -> 9093.3333 | L49: =+K49-I49 -> 2273.3333
B50: CE | C50: C | D50: Personnel Costs | E50: 740201 | F50: 740201 - Salari E Stipendi - Operai | G50: 822904.77 | I50: 822904.77 | J50: 618703.7 | K50: =+J50/6*8 -> 824938.27 | L50: =+K50-I50 -> 2033.4967
B51: CE | C51: C | D51: Personnel Costs | E51: 740205 | F51: 740205 - Salari E Stipendi - Dirigenti | G51: 842556.66 | I51: 842556.66 | J51: 633333.35 | K51: =+J51/6*8 -> 844444.47 | L51: =+K51-I51 -> 1887.8067
B52: CE | C52: C | D52: Overheads | E52: 700211 | F52: 700211 - Manut. E Rip. Autovetture Deduc. | G52: 5279.23 | I52: 5279.23 | J52: 4874.22 | K52: =+J52/6*8 -> 6498.96 | L52: =+K52-I52 -> 1219.73
B53: CE | C53: C | D53: Overheads | E53: 880201 | F53: 880201 - Imposta Imu | G53: 3109 | I53: 3109 | J53: 3109 | K53: =+J53/6*8 -> 4145.3333 | L53: =+K53-I53 -> 1036.3333
B54: CE | C54: C | D54: Overheads | E54: 701605 | F54: 701605 - Spese Di Rappresentanza Ded. | G54: 6617.28 | I54: 6617.28 | J54: 5731.17 | K54: =+J54/6*8 -> 7641.56 | L54: =+K54-I54 -> 1024.28
B55: CE | C55: R | D55: Other Revenues | E55: 660413 | F55: 660413 - Contributi In C/Esercizio | H55: 18677.46 | I55: -18677.46 | J55: -13343.37 | K55: =+J55/6*8 -> -17791.16 | L55: =+K55-I55 -> 886.3
B56: CE | C56: R | D56: Other Revenues | E56: 160203 | F56: 160203 - Spese Anticipate | H56: 756.79 | I56: -756.79 | J56: 34.6 | K56: =+J56/6*8 -> 46.133333 | L56: =+K56-I56 -> 802.92333
B57: CE | C57: C | D57: Overheads | E57: 880209 | F57: 880209 - Tasse Di Concessione Governat. | G57: 2375.68 | I57: 2375.68 | J57: 2375.68 | K57: =+J57/6*8 -> 3167.5733 | L57: =+K57-I57 -> 791.89333
B58: CE | C58: C | D58: Personnel Costs | E58: 700411 | F58: 700411 - Contributi Inps Collaboratori Co.Co.Co | G58: 39190.76 | I58: 39190.76 | J58: 29914.92 | K58: =+J58/6*8 -> 39886.56 | L58: =+K58-I58 -> 695.8
B59: CE | C59: C | D59: Overheads | E59: 880203 | F59: 880203 - Tassa Sui Rifiuti | G59: 3015.38 | I59: 3015.38 | J59: 2714.86 | K59: =+J59/6*8 -> 3619.8133 | L59: =+K59-I59 -> 604.43333
B60: CE | C60: C | D60: Personnel Costs | E60: 740209 | F60: 740209 - Salari E Stipendi - 13ma Operai | G60: 79732.86 | I60: 79732.86 | J60: 60124.32 | K60: =+J60/6*8 -> 80165.76 | L60: =+K60-I60 -> 432.9
B61: CE | C61: C | D61: Personnel Costs | E61: 701805 | F61: 701805 - Contributi Inail Amministratore | G61: 852.61 | I61: 852.61 | J61: 852.61 | K61: =+J61/6*8 -> 1136.8133 | L61: =+K61-I61 -> 284.20333
B62: CE | C62: C | D62: Overheads | E62: 720403 | F62: 720403 - Noleggi Deducibili | G62: 47795.17 | I62: 47795.17 | J62: 36032.63 | K62: =+J62/6*8 -> 48043.507 | L62: =+K62-I62 -> 248.33667
B63: CE | C63: R | D63: Other Revenues | E63: 660201 | F63: 660201 - Sconti, Ribassi e Abbuoni Attivi | H63: 7206.23 | I63: -7206.23 | J63: -5231.37 | K63: =+J63/6*8 -> -6975.16 | L63: =+K63-I63 -> 231.07
B64: CE | C64: C | D64: Overheads | E64: 840401 | F64: 840401 - Tassa Di Proprieta' Autoveicoli | G64: 1104.6 | I64: 1104.6 | J64: 1001.39 | K64: =+J64/6*8 -> 1335.1867 | L64: =+K64-I64 -> 230.58667
B65: CE | C65: C | D65: Financial Expenses | E65: 920213 | F65: 920213 - Int. Passivi V/Fornitori | G65: 661.76 | I65: 661.76 | J65: 615.73 | K65: =+J65/6*8 -> 820.97333 | L65: =+K65-I65 -> 159.21333
B66: CE | C66: C | D66: Overheads | E66: 700805 | F66: 700805 - Acqua | G66: 7274.19 | I66: 7274.19 | J66: 5525.93 | K66: =+J66/6*8 -> 7367.9067 | L66: =+K66-I66 -> 93.716667
B67: CE | C67: C | D67: Overheads | E67: 680401 | F67: 680401 - Acquisti Vari | G67: 81.89 | I67: 81.89 | J67: 81.89 | K67: =+J67/6*8 -> 109.18667 | L67: =+K67-I67 -> 27.296667
B68: CE | C68: C | D68: Personnel Costs | E68: 740213 | F68: 740213 - Salari E Stipendi - 13ma Dirigenti | G68: 89304.81 | I68: 89304.81 | J68: 66995 | K68: =+J68/6*8 -> 89326.667 | L68: =+K68-I68 -> 21.856667
B69: CE | C69: C | D69: Depreciation and amortization | E69: 760401 | F69: 760401 - Amm.To Costi D'impianto | G69: 1102 | I69: 1102 | J69: 827 | K69: =+J69/6*8 -> 1102.6667 | L69: =+K69-I69 -> 0.66666667
B70: CE | C70: C | D70: Depreciation and amortization | E70: 761001 | F70: 761001 - Amm.to Concessioni, Licenze, Marchi e Diritti Simili | G70: 29686.15 | I70: 29686.15 | J70: 22265.11 | K70: =+J70/6*8 -> 29686.813 | L70: =+K70-I70 -> 0.66333333
B71: CE | C71: C | D71: Depreciation and amortization | E71: 761601 | F71: 761601 - Amm.to Altri Costi Ad Util. Plur. Da Amm. | G71: 1797 | I71: 1797 | J71: 1348 | K71: =+J71/6*8 -> 1797.3333 | L71: =+K71-I71 -> 0.33333333
B72: CE | C72: C | D72: Depreciation and amortization | E72: 782001 | F72: 782001 - Amm.To Ord. Autovetture | G72: 2941.77 | I72: 2941.77 | J72: 2206.33 | K72: =+J72/6*8 -> 2941.7733 | L72: =+K72-I72 -> 0.0033333333
B73: CE | C73: C | D73: Depreciation and amortization | E73: 780203 | F73: 780203 - Amm.To Ord. Fabb. Ind.Li E Comm. (MiniPia) | G73: 10848.45 | I73: 10848.45 | J73: 8136.34 | K73: =+J73/6*8 -> 10848.453 | L73: =+K73-I73 -> 0.0033333333
B74: CE | C74: C | D74: Depreciation and amortization | E74: 781801 | F74: 781801 - Amm.To Ord. Autocarri/Autovetture | G74: 13040.61 | I74: 13040.61 | J74: 9780.46 | K74: =+J74/6*8 -> 13040.613 | L74: =+K74-I74 -> 0.0033333333
B75: CE | C75: C | D75: Depreciation and amortization | E75: 780201 | F75: 780201 - Amm.To Ord. Fabb. Ind.Li E Comm. | G75: 20291.61 | I75: 20291.61 | J75: 15218.71 | K75: =+J75/6*8 -> 20291.613 | L75: =+K75-I75 -> 0.0033333333
... B84: CE | C84: C | D84: Financial Expenses | E84: 920211 | F84: 920211 - Interessi Da Altri Debiti | G84: 14.09 | I84: 14.09 | J84: 0 | K84: =+J84/6*8 -> 0 | L84: =+K84-I84 -> -14.09
B85: CE | C85: C | D85: Overheads | E85: 880601 | F85: 880601 - Sconti, Ribassi E Abbuoni Passivi | H85: 112.46 | I85: -112.46 | J85: -114.67 | K85: =+J85/6*8 -> -152.89333 | L85: =+K85-I85 -> -40.433333
B86: CE | C86: C | D86: Depreciation and amortization | E86: 780401 | F86: 780401 - Amm.To Ord. Cost. Legg. | G86: 2477.78 | I86: 2477.78 | J86: 1827.02 | K86: =+J86/6*8 -> 2436.0267 | L86: =+K86-I86 -> -41.753333
B87: CE | C87: C | D87: Overheads | E87: 700811 | F87: 700811 - Pedaggi Autostradali | G87: 69.9 | I87: 69.9 | J87: 0 | K87: =+J87/6*8 -> 0 | L87: =+K87-I87 -> -69.9
B88: CE | C88: R | D88: Extraordinary Item (Attive) | E88: 660409 | F88: 660409 - Sopravvenienze Attive Ord. Inded. | H88: 1691.99 | I88: -1691.99 | J88: -1375.4 | K88: =+J88/6*8 -> -1833.8667 | L88: =+K88-I88 -> -141.87667
B89: CE | C89: C | D89: Depreciation and amortization | E89: 781201 | F89: 781201 - Amm.To Ord. Mob.E Mac. Ord. Uff. | G89: 20604.49 | I89: 20604.49 | J89: 15346.69 | K89: =+J89/6*8 -> 20462.253 | L89: =+K89-I89 -> -142.23667
B90: CE | C90: C | D90: Overheads | E90: 860209 | F90: 860209 - Differenze Di Cambio Passive | G90: 172.36 | I90: 172.36 | J90: 0 | K90: =+J90/6*8 -> 0 | L90: =+K90-I90 -> -172.36
B91: CE | C91: C | D91: Personnel Costs | E91: 742001 | F91: 742001 - Trattamento Di Quiescenza E Simili - Operai | G91: 5151.19 | I91: 5151.19 | J91: 3642.03 | K91: =+J91/6*8 -> 4856.04 | L91: =+K91-I91 -> -295.15
B92: CE | C92: C | D92: Personnel Costs | E92: 740801 | F92: 740801 - Oneri Sociali Inail | G92: 34694.67 | I92: 34694.67 | J92: 25766.91 | K92: =+J92/6*8 -> 34355.88 | L92: =+K92-I92 -> -338.79
B93: CE | C93: C | D93: Overheads | E93: 840601 | F93: 840601 - Imposta di bollo | G93: 1910.05 | I93: 1910.05 | J93: 1059.22 | K93: =+J93/6*8 -> 1412.2933 | L93: =+K93-I93 -> -497.75667
B94: CE | C94: C | D94: Personnel Costs | E94: 700823 | F94: 700823 - Contributi Ad Assoc. di Categoria | G94: 7207.96 | I94: 7207.96 | J94: 5007.96 | K94: =+J94/6*8 -> 6677.28 | L94: =+K94-I94 -> -530.68
B95: CE | C95: C | D95: Personnel Costs | E95: 740607 | F95: 740607 - Contributi Previndai | G95: 25573.24 | I95: 25573.24 | J95: 18708.36 | K95: =+J95/6*8 -> 24944.48 | L95: =+K95-I95 -> -628.76
B96: CE | C96: C | D96: Overheads | E96: 880803 | F96: 880803 - Multe E Ammende Indeducibili | G96: 5236.02 | I96: 5236.02 | J96: 3352.25 | K96: =+J96/6*8 -> 4469.6667 | L96: =+K96-I96 -> -766.35333
B97: CE | C97: C | D97: Depreciation and amortization | E97: 781401 | F97: 781401 - Amm.To Ord. Macc. Elettrom. Uff. | G97: 22651.93 | I97: 22651.93 | J97: 16185.59 | K97: =+J97/6*8 -> 21580.787 | L97: =+K97-I97 -> -1071.1433
B98: CE | C98: C | D98: Depreciation and amortization | E98: 781001 | F98: 781001 - Amm.To Ord. Att. Ind.Li E Comm. | G98: 55735.82 | I98: 55735.82 | J98: 40982.21 | K98: =+J98/6*8 -> 54642.947 | L98: =+K98-I98 -> -1092.8733
B99: CE | C99: C | D99: Personnel Costs | E99: 741001 | F99: 741001 - Oneri Sociali Ferie Maturate E Non Godute | G99: 130549.24 | I99: 130549.24 | J99: 97064 | K99: =+J99/6*8 -> 129418.67 | L99: =+K99-I99 -> -1130.5733
B100: CE | C100: C | D100: Overheads | E100: 701807 | F100: 701807 - Compensi Sindaci | G100: 1300 | I100: 1300 | J100: 0 | K100: =+J100/6*8 -> 0 | L100: =+K100-I100 -> -1300
... B112: CE | C112: C | D112: Overheads | E112: 880211 | F112: 880211 - Diritti Camerali | G112: 3568.16 | I112: 3568.16 | J112: 367.42 | K112: =+J112/6*8 -> 489.89333 | L112: =+K112-I112 -> -3078.2667
B113: CE | C113: R | D113: Other Revenues | E113: 660203 | F113: 660203 - Altri Ricavi E Proventi Vari | H113: 9498.5 | I113: -9498.5 | J113: -9498.5 | K113: =+J113/6*8 -> -12664.667 | L113: =+K113-I113 -> -3166.1667
B114: CE | C114: C | D114: Overheads | E114: 720601 | F114: 720601 - Canoni Leasing Operativo | G114: 17675.22 | I114: 17675.22 | J114: 10563.34 | K114: =+J114/6*8 -> 14084.453 | L114: =+K114-I114 -> -3590.7667
B115: CE | C115: C | D115: Overheads | E115: 840403 | F115: 840403 - Tassa Prop.Veicoli Parz.Ded. | G115: 11383.67 | I115: 11383.67 | J115: 5454.1 | K115: =+J115/6*8 -> 7272.1333 | L115: =+K115-I115 -> -4111.5367
B116: CE | C116: C | D116: Overheads | E116: 700813 | F116: 700813 - Pedaggi Autostradali Parz. Ded. | G116: 35087.27 | I116: 35087.27 | J116: 23124.01 | K116: =+J116/6*8 -> 30832.013 | L116: =+K116-I116 -> -4255.2567
B117: CE | C117: C | D117: Financial Expenses | E117: 920207 | F117: 920207 - Interessi Da Debiti Verso Banche | G117: 83426.69 | I117: 83426.69 | J117: 59077.17 | K117: =+J117/6*8 -> 78769.56 | L117: =+K117-I117 -> -4657.13
B118: CE | C118: C | D118: Taxes | E118: 940201 | F118: 940201 - Irap Dell'esercizio | G118: 4801 | I118: 4801 | J118: 0 | K118: =+J118/6*8 -> 0 | L118: =+K118-I118 -> -4801
B119: CE | C119: C | D119: Overheads | E119: 741605 | F119: 741605 - Spese Cellulari | G119: 38032.05 | I119: 38032.05 | J119: 24883 | K119: =+J119/6*8 -> 33177.333 | L119: =+K119-I119 -> -4854.7167
B120: CE | C120: C | D120: Personnel Costs | E120: 741601 | F120: 741601 - Buoni Pasto | G120: 205217.04 | I120: 205217.04 | J120: 149854.8 | K120: =+J120/6*8 -> 199806.4 | L120: =+K120-I120 -> -5410.64
B121: CE | C121: C | D121: Personnel Costs | E121: 740211 | F121: 740211 - Salari E Stipendi - 13ma Impiegati | G121: 225607.77 | I121: 225607.77 | J121: 165131.3 | K121: =+J121/6*8 -> 220175.07 | L121: =+K121-I121 -> -5432.7033
B122: CE | C122: C | D122: Costi Diretti | E122: 700205 | F122: 700205 - Manut. E Rip. Su Beni Di Prop. | G122: 9061.2 | I122: 9061.2 | J122: 2671.4 | K122: =+J122/6*8 -> 3561.8667 | L122: =+K122-I122 -> -5499.3333
B123: CE | C123: C | D123: Overheads | E123: 702203 | F123: 702203 - Spese Telefoniche - Numero Verde | G123: 19464.1 | I123: 19464.1 | J123: 10060.25 | K123: =+J123/6*8 -> 13413.667 | L123: =+K123-I123 -> -6050.4333
B124: CE | C124: C | D124: Overheads | E124: 720605 | F124: 720605 - Canoni Leasing Deducibile | G124: 6500 | I124: 6500 | J124: 0 | K124: =+J124/6*8 -> 0 | L124: =+K124-I124 -> -6500
B125: CE | C125: C | D125: Personnel Costs | E125: 740611 | F125: 740611 - Oneri Previdenziali I.N.P.S. - Impiegati | G125: 664931.25 | I125: 664931.25 | J125: 492524.59 | K125: =+J125/6*8 -> 656699.45 | L125: =+K125-I125 -> -8231.7967
... B127: CE | C127: C | D127: Overheads | E127: 720401 | F127: 720401 - Noleggi Operativi | G127: 51694.26 | I127: 51694.26 | J127: 32444.49 | K127: =+J127/6*8 -> 43259.32 | L127: =+K127-I127 -> -8434.94
...

Sheet Sheet2
J1: =+SUM(J3:J1032) -> 27929.458 | K1: =+SUM(K3:K1032) -> 37239.277 | L1: =+SUM(L3:L1032) -> 38954.777
B2: Chiave | C2: Entity | D2: Seller | E2: BU | F2: Business Stream | G2: Type of contract | H2: Codice Financial Commesse | I2: Comuni | J2: Giugno | K2: RR Giugno | L2: Agosto | M2: Delta
B3: =+I3&H3 -> Varazze | C3: CVS | D3: Organic | E3: North West | F3: Public Streetlighting | G3: PPP | I3: Varazze | J3: =+_xlfn.XLOOKUP(B3,Sheet3!B:B,Sheet3!J:J,0) -> 0 | K3: =+J3/6*8 -> 0 | L3: 0 | M3: =+L3-K3 -> 0
B4: =+I4&H4 -> Lerici PL | C4: CVS | D4: Organic | E4: North West | F4: Public Streetlighting | G4: PPP | I4: Lerici PL | J4: =+_xlfn.XLOOKUP(B4,Sheet3!B:B,Sheet3!J:J,0) -> 0 | K4: =+J4/6*8 -> 0 | L4: 0 | M4: =+L4-K4 -> 0
B5: =+I5&H5 -> Levanto | C5: CVS | D5: Organic | E5: North West | F5: Public Streetlighting | G5: PPP | I5: Levanto | J5: =+_xlfn.XLOOKUP(B5,Sheet3!B:B,Sheet3!J:J,0) -> 0 | K5: =+J5/6*8 -> 0 | L5: 0 | M5: =+L5-K5 -> 0
B6: =+I6&H6 -> SoriPPP-IPU-I852-01 | C6: CVS | D6: Organic | E6: North West | F6: Public Streetlighting | G6: PPP | H6: PPP-IPU-I852-01 | I6: Sori | J6: =+_xlfn.XLOOKUP(B6,Sheet3!B:B,Sheet3!J:J,0) -> 0 | K6: =+J6/6*8 -> 0 | L6: 0 | M6: =+L6-K6 -> 0
B7: =+I7&H7 -> Avezzano 3SEC-PHV-A515-01 | C7: CVS | D7: Organic | E7: Centre | F7: Photovoltaic | G7: Photovoltaic | H7: SEC-PHV-A515-01 | I7: Avezzano 3 | J7: =+_xlfn.XLOOKUP(B7,Sheet3!B:B,Sheet3!J:J,0) -> 0 | K7: =+J7/6*8 -> 0 | L7: 0 | M7: =+L7-K7 -> 0
B8: =+I8&H8 -> Avezzano 4SEC-PHV-A515-02 | C8: CVS | D8: Organic | E8: Centre | F8: Photovoltaic | G8: Photovoltaic | H8: SEC-PHV-A515-02 | I8: Avezzano 4 | J8: =+_xlfn.XLOOKUP(B8,Sheet3!B:B,Sheet3!J:J,0) -> 0 | K8: =+J8/6*8 -> 0 | L8: 0 | M8: =+L8-K8 -> 0
B9: =+I9&H9 -> GiulianovaSEC-PHV-E058-01 | C9: CVS | D9: Organic | E9: Centre | F9: Photovoltaic | G9: Photovoltaic | H9: SEC-PHV-E058-01 | I9: Giulianova | J9: =+_xlfn.XLOOKUP(B9,Sheet3!B:B,Sheet3!J:J,0) -> 0 | K9: =+J9/6*8 -> 0 | L9: 0 | M9: =+L9-K9 -> 0
B10: =+I10&H10 -> Montorio 1SEC-PHV-F690-01 | C10: CVS | D10: Organic | E10: Centre | F10: Photovoltaic | G10: Photovoltaic | H10: SEC-PHV-F690-01 | I10: Montorio 1 | J10: =+_xlfn.XLOOKUP(B10,Sheet3!B:B,Sheet3!J:J,0) -> 0 | K10: =+J10/6*8 -> 0 | L10: 0 | M10: =+L10-K10 -> 0
B11: =+I11&H11 -> Montorio 3SEC-PHV-F690-02 | C11: CVS | D11: Organic | E11: Centre | F11: Photovoltaic | G11: Photovoltaic | H11: SEC-PHV-F690-02 | I11: Montorio 3 | J11: =+_xlfn.XLOOKUP(B11,Sheet3!B:B,Sheet3!J:J,0) -> 0 | K11: =+J11/6*8 -> 0 | L11: 0 | M11: =+L11-K11 -> 0
B12: =+I12&H12 -> Montorio 4SEC-PHV-F690-03 | C12: CVS | D12: Organic | E12: Centre | F12: Photovoltaic | G12: Photovoltaic | H12: SEC-PHV-F690-03 | I12: Montorio 4 | J12: =+_xlfn.XLOOKUP(B12,Sheet3!B:B,Sheet3!J:J,0) -> 0 | K12: =+J12/6*8 -> 0 | L12: 0 | M12: =+L12-K12 -> 0
B13: =+I13&H13 -> Sant'Arpino | C13: CVS | D13: Organic | E13: South | F13: Public Streetlighting | G13: PPP | I13: Sant'Arpino | J13: =+_xlfn.XLOOKUP(B13,Sheet3!B:B,Sheet3!J:J,0) -> 0 | K13: =+J13/6*8 -> 0 | L13: 0 | M13: =+L13-K13 -> 0
B14: =+I14&H14 -> Avigliano Cemetery | C14: CVS | D14: Organic | E14: South | F14: Cemetary Services | G14: PPP | I14: Avigliano Cemetery | J14: =+_xlfn.XLOOKUP(B14,Sheet3!B:B,Sheet3!J:J,0) -> 0 | K14: =+J14/6*8 -> 0 | L14: 0 | M14: =+L14-K14 -> 0
B15: =+I15&H15 -> Filiano Cemetery | C15: CVS | D15: Organic | E15: South | F15: Cemetary Services | G15: PPP | I15: Filiano Cemetery | J15: =+_xlfn.XLOOKUP(B15,Sheet3!B:B,Sheet3!J:J,0) -> 0 | K15: =+J15/6*8 -> 0 | L15: 0 | M15: =+L15-K15 -> 0
B16: =+I16&H16 -> San Marzano di San GiuseppePPP-IPU-I018-01 | C16: CVS | D16: Organic | E16: South | F16: Public Streetlighting | G16: PPP | H16: PPP-IPU-I018-01 | I16: San Marzano di San Giuseppe | J16: =+_xlfn.XLOOKUP(B16,Sheet3!B:B,Sheet3!J:J,0) -> 0 | K16: =+J16/6*8 -> 0 | L16: 0 | M16: =+L16-K16 -> 0
B17: =+I17&H17 -> Frignano | C17: CVS | D17: Organic | E17: South | F17: Public Streetlighting | G17: PPP | I17: Frignano | J17: =+_xlfn.XLOOKUP(B17,Sheet3!B:B,Sheet3!J:J,0) -> 0 | K17: =+J17/6*8 -> 0 | L17: 0 | M17: =+L17-K17 -> 0
B18: =+I18&H18 -> Gricignano di Aversa | C18: CVS | D18: Organic | E18: South | F18: Public Streetlighting | G18: PPP | I18: Gricignano di Aversa | J18: =+_xlfn.XLOOKUP(B18,Sheet3!B:B,Sheet3!J:J,0) -> 0 | K18: =+J18/6*8 -> 0 | L18: 0 | M18: =+L18-K18 -> 0
B19: =+I19&H19 -> Torano Castello | C19: CVS | D19: Organic | E19: South | F19: Public Streetlighting | G19: PPP | I19: Torano Castello | J19: =+_xlfn.XLOOKUP(B19,Sheet3!B:B,Sheet3!J:J,0) -> 0 | K19: =+J19/6*8 -> 0 | L19: 0 | M19: =+L19-K19 -> 0
B20: =+I20&H20 -> Piano di SorrentoPPP-IPU-G568-01 | C20: CVS | D20: Organic | E20: South | F20: Public Streetlighting | G20: PPP | H20: PPP-IPU-G568-01 | I20: Piano di Sorrento | J20: =+_xlfn.XLOOKUP(B20,Sheet3!B:B,Sheet3!J:J,0) -> 0 | K20: =+J20/6*8 -> 0 | L20: 0 | M20: =+L20-K20 -> 0
B21: =+I21&H21 -> Giardini-Naxos | C21: CVS | D21: Organic | E21: South | F21: Public Streetlighting | G21: PPP | I21: Giardini-Naxos | J21: =+_xlfn.XLOOKUP(B21,Sheet3!B:B,Sheet3!J:J,0) -> 0 | K21: =+J21/6*8 -> 0 | L21: 0 | M21: =+L21-K21 -> 0
B22: =+I22&H22 -> Copertino 1SEC-PHV-C978-01 | C22: CVS | D22: Organic | E22: South | F22: Photovoltaic | G22: Photovoltaic | H22: SEC-PHV-C978-01 | I22: Copertino 1 | J22: =+_xlfn.XLOOKUP(B22,Sheet3!B:B,Sheet3!J:J,0) -> 0 | K22: =+J22/6*8 -> 0 | L22: 0 | M22: =+L22-K22 -> 0
B23: =+I23&H23 -> Copertino 2SEC-PHV-C978-02 | C23: CVS | D23: Organic | E23: South | F23: Photovoltaic | G23: Photovoltaic | H23: SEC-PHV-C978-02 | I23: Copertino 2 | J23: =+_xlfn.XLOOKUP(B23,Sheet3!B:B,Sheet3!J:J,0) -> 0 | K23: =+J23/6*8 -> 0 | L23: 0 | M23: =+L23-K23 -> 0
B24: =+I24&H24 -> Campi 1 | C24: CVS | D24: Organic | E24: South | F24: Photovoltaic | G24: Photovoltaic | I24: Campi 1 | J24: =+_xlfn.XLOOKUP(B24,Sheet3!B:B,Sheet3!J:J,0) -> 0 | K24: =+J24/6*8 -> 0 | L24: 0 | M24: =+L24-K24 -> 0
B25: =+I25&H25 -> Belvedere Marittimo | C25: CVS | D25: Jovit | E25: South | F25: Public Streetlighting | G25: PPP | I25: Belvedere Marittimo | J25: =+_xlfn.XLOOKUP(B25,Sheet3!B:B,Sheet3!J:J,0) -> 0 | K25: =+J25/6*8 -> 0 | L25: 0 | M25: =+L25-K25 -> 0
B26: =+I26&H26 -> Roccamonfina | C26: CVS | D26: Jovit | E26: South | F26: Public Streetlighting | G26: PPP | I26: Roccamonfina | J26: =+_xlfn.XLOOKUP(B26,Sheet3!B:B,Sheet3!J:J,0) -> 0 | K26: =+J26/6*8 -> 0 | L26: 0 | M26: =+L26-K26 -> 0
B27: =+I27&H27 -> Sesto Campano | C27: CVS | D27: Jovit | E27: Centre | F27: Public Streetlighting | G27: PPP | I27: Sesto Campano | J27: =+_xlfn.XLOOKUP(B27,Sheet3!B:B,Sheet3!J:J,0) -> 0 | K27: =+J27/6*8 -> 0 | L27: 0 | M27: =+L27-K27 -> 0
B28: =+I28&H28 -> RivarossaPPP-IPU-H344-01 | C28: CVS | D28: Samsic | E28: North West | F28: Public Streetlighting | G28: PPP | H28: PPP-IPU-H344-01 | I28: Rivarossa | J28: =+_xlfn.XLOOKUP(B28,Sheet3!B:B,Sheet3!J:J,0) -> 0 | K28: =+J28/6*8 -> 0 | L28: 0 | M28: =+L28-K28 -> 0
B29: =+I29&H29 -> Torre D'IsolaPPP-IPU-L269-01 | C29: CVS | D29: Samsic | E29: North West | F29: Public Streetlighting | G29: PPP | H29: PPP-IPU-L269-01 | I29: Torre D'Isola | J29: =+_xlfn.XLOOKUP(B29,Sheet3!B:B,Sheet3!J:J,0) -> 0 | K29: =+J29/6*8 -> 0 | L29: 0 | M29: =+L29-K29 -> 0
B30: =+I30&H30 -> Santo Stefano LodigianoPPP-IPU-I362-01 | C30: CVS | D30: Samsic | E30: North West | F30: Public Streetlighting | G30: PPP | H30: PPP-IPU-I362-01 | I30: Santo Stefano Lodigiano | J30: =+_xlfn.XLOOKUP(B30,Sheet3!B:B,Sheet3!J:J,0) -> 0 | K30: =+J30/6*8 -> 0 | L30: 0 | M30: =+L30-K30 -> 0
B31: =+I31&H31 -> SecugnagoPPP-IPU-I561-01 | C31: CVS | D31: Samsic | E31: North West | F31: Public Streetlighting | G31: PPP | H31: PPP-IPU-I561-01 | I31: Secugnago | J31: =+_xlfn.XLOOKUP(B31,Sheet3!B:B,Sheet3!J:J,0) -> 0 | K31: =+J31/6*8 -> 0 | L31: 0 | M31: =+L31-K31 -> 0
B32: =+I32&H32 -> Loro CiuffennaPPP-IPU-E693-01 | C32: CVS | D32: Samsic | E32: Centre | F32: Public Streetlighting | G32: PPP | H32: PPP-IPU-E693-01 | I32: Loro Ciuffenna | J32: =+_xlfn.XLOOKUP(B32,Sheet3!B:B,Sheet3!J:J,0) -> 0 | K32: =+J32/6*8 -> 0 | L32: 0 | M32: =+L32-K32 -> 0
B33: =+I33&H33 -> Ricigliano | C33: CVS | D33: Alfano Luce | E33: South | F33: Public Streetlighting | G33: PPP | I33: Ricigliano | J33: =+_xlfn.XLOOKUP(B33,Sheet3!B:B,Sheet3!J:J,0) -> 0 | K33: =+J33/6*8 -> 0 | L33: 0 | M33: =+L33-K33 -> 0
B34: =+I34&H34 -> Serino | C34: CVS | D34: Alfano Luce | E34: South | F34: Public Streetlighting | G34: PPP | I34: Serino | J34: =+_xlfn.XLOOKUP(B34,Sheet3!B:B,Sheet3!J:J,0) -> 0 | K34: =+J34/6*8 -> 0 | L34: 0 | M34: =+L34-K34 -> 0
B35: =+I35&H35 -> San Cipriano PicentinoPPP-IPU-H800-01 | C35: CVS | D35: Alfano Luce | E35: South | F35: Public Streetlighting | G35: PPP | H35: PPP-IPU-H800-01 | I35: San Cipriano Picentino | J35: =+_xlfn.XLOOKUP(B35,Sheet3!B:B,Sheet3!J:J,0) -> 0 | K35: =+J35/6*8 -> 0 | L35: 0 | M35: =+L35-K35 -> 0
B36: =+I36&H36 -> Vietri sul Mare | C36: CVS | D36: Alfano Luce | E36: South | F36: Public Streetlighting | G36: PPP | I36: Vietri sul Mare | J36: =+_xlfn.XLOOKUP(B36,Sheet3!B:B,Sheet3!J:J,0) -> 0 | K36: =+J36/6*8 -> 0 | L36: 0 | M36: =+L36-K36 -> 0
B37: =+I37&H37 -> Umbertide | C37: CVS | D37: Tetra Engineering | E37: Centre | F37: Public Streetlighting | G37: PPP | I37: Umbertide | J37: =+_xlfn.XLOOKUP(B37,Sheet3!B:B,Sheet3!J:J,0) -> 0 | K37: =+J37/6*8 -> 0 | L37: 0 | M37: =+L37-K37 -> 0
B38: =+I38&H38 -> Lizzanello | C38: CVS | D38: Ege Global Service | E38: South | F38: Public Streetlighting | G38: PPP | I38: Lizzanello | J38: =+_xlfn.XLOOKUP(B38,Sheet3!B:B,Sheet3!J:J,0) -> 0 | K38: =+J38/6*8 -> 0 | L38: 0 | M38: =+L38-K38 -> 0
B39: =+I39&H39 -> San Donato Milanese | C39: CVS | D39: Ege Global Service | E39: South | F39: Public Streetlighting | G39: PPP | I39: San Donato Milanese | J39: =+_xlfn.XLOOKUP(B39,Sheet3!B:B,Sheet3!J:J,0) -> 0 | K39: =+J39/6*8 -> 0 | L39: 0 | M39: =+L39-K39 -> 0
B40: =+I40&H40 -> Altro Not identified (Sud) 1 | C40: CVS | D40: Pipeline | E40: South | F40: Public Streetlighting | G40: PPP | I40: Altro Not identified (Sud) 1 | J40: =+_xlfn.XLOOKUP(B40,Sheet3!B:B,Sheet3!J:J,0) -> 0 | K40: =+J40/6*8 -> 0 | L40: 0 | M40: =+L40-K40 -> 0
B41: =+I41&H41 -> Altro Not identified (Centre) | C41: CVS | D41: Pipeline | E41: Centre | F41: Public Streetlighting | G41: PPP | I41: Altro Not identified (Centre) | J41: =+_xlfn.XLOOKUP(B41,Sheet3!B:B,Sheet3!J:J,0) -> 0 | K41: =+J41/6*8 -> 0 | L41: 0 | M41: =+L41-K41 -> 0
B42: =+I42&H42 -> Altro Not identified (North West) | C42: CVS | D42: Pipeline | E42: North West | F42: Public Streetlighting | G42: PPP | I42: Altro Not identified (North West) | J42: =+_xlfn.XLOOKUP(B42,Sheet3!B:B,Sheet3!J:J,0) -> 0 | K42: =+J42/6*8 -> 0 | L42: 0 | M42: =+L42-K42 -> 0
B43: =+I43&H43 -> Altro Not identified (North East) | C43: ATL | D43: Pipeline | E43: North East | F43: Public Streetlighting | G43: PPP | I43: Altro Not identified (North East) | J43: =+_xlfn.XLOOKUP(B43,Sheet3!B:B,Sheet3!J:J,0) -> 0 | K43: =+J43/6*8 -> 0 | L43: 0 | M43: =+L43-K43 -> 0
B44: =+I44&H44 -> AQ1 not yet iidentified (NW) | C44: ATL | D44: Organic | E44: North West | F44: Public Streetlighting | G44: AQ1 | I44: AQ1 not yet iidentified (NW) | J44: =+_xlfn.XLOOKUP(B44,Sheet3!B:B,Sheet3!J:J,0) -> 0 | K44: =+J44/6*8 -> 0 | L44: 0 | M44: =+L44-K44 -> 0
B45: =+I45&H45 -> AQ1 not identified (NE) | C45: ATL | D45: Organic | E45: North East | F45: Public Streetlighting | G45: AQ1 | I45: AQ1 not identified (NE) | J45: =+_xlfn.XLOOKUP(B45,Sheet3!B:B,Sheet3!J:J,0) -> 0 | K45: =+J45/6*8 -> 0 | L45: 0 | M45: =+L45-K45 -> 0
B46: =+I46&H46 -> AQ1 not identified (CE) | C46: ATL | D46: Organic | E46: Centre | F46: Public Streetlighting | G46: AQ1 | I46: AQ1 not identified (CE) | J46: =+_xlfn.XLOOKUP(B46,Sheet3!B:B,Sheet3!J:J,0) -> 0 | K46: =+J46/6*8 -> 0 | L46: 0 | M46: =+L46-K46 -> 0
B47: =+I47&H47 -> Buildings not identified (NE) | C47: ATL | D47: Organic | E47: North East | F47: Smart Buildings | G47: Smart Buildings | I47: Buildings not identified (NE) | J47: =+_xlfn.XLOOKUP(B47,Sheet3!B:B,Sheet3!J:J,0) -> 0 | K47: =+J47/6*8 -> 0 | L47: 0 | M47: =+L47-K47 -> 0
... B51: =+I51&H51 -> San Mango Piemonte | C51: CVS | D51: Jovit | E51: South | F51: Public Streetlighting | G51: PPP | I51: San Mango Piemonte | J51: =+_xlfn.XLOOKUP(B51,Sheet3!B:B,Sheet3!J:J,0) -> 0 | K51: =+J51/6*8 -> 0 | L51: 0 | M51: =+L51-K51 -> 0
B52: =+I52&H52 -> Romagnano SesiaPPP-IPU-H502-01 | C52: CVS | D52: Samsic | E52: North West | F52: Public Streetlighting | G52: PPP | H52: PPP-IPU-H502-01 | I52: Romagnano Sesia | J52: =+_xlfn.XLOOKUP(B52,Sheet3!B:B,Sheet3!J:J,0) -> 0 | K52: =+J52/6*8 -> 0 | L52: 164.41114 | M52: =+L52-K52 -> 164.41114
B53: =+I53&H53 -> MassalengoPPP-IPU-F028-01 | C53: CVS | D53: Samsic | E53: North West | F53: Public Streetlighting | G53: PPP | H53: PPP-IPU-F028-01 | I53: Massalengo | J53: =+_xlfn.XLOOKUP(B53,Sheet3!B:B,Sheet3!J:J,0) -> 0 | K53: =+J53/6*8 -> 0 | L53: 0 | M53: =+L53-K53 -> 0
B54: =+I54&H54 -> Maiori | C54: CVS | D54: Alfano Luce | E54: South | F54: Public Streetlighting | G54: PPP | I54: Maiori | J54: =+_xlfn.XLOOKUP(B54,Sheet3!B:B,Sheet3!J:J,0) -> 0 | K54: =+J54/6*8 -> 0 | L54: 0 | M54: =+L54-K54 -> 0
B55: =+I55&H55 -> Minori | C55: CVS | D55: Alfano Luce | E55: South | F55: Public Streetlighting | G55: PPP | I55: Minori | J55: =+_xlfn.XLOOKUP(B55,Sheet3!B:B,Sheet3!J:J,0) -> 0 | K55: =+J55/6*8 -> 0 | L55: 0 | M55: =+L55-K55 -> 0
B56: =+I56&H56 -> Castel San Giorgio | C56: CVS | D56: Alfano Luce | E56: South | F56: Public Streetlighting | G56: PPP | I56: Castel San Giorgio | J56: =+_xlfn.XLOOKUP(B56,Sheet3!B:B,Sheet3!J:J,0) -> 0 | K56: =+J56/6*8 -> 0 | L56: 0 | M56: =+L56-K56 -> 0
B57: =+I57&H57 -> Ischia | C57: CVS | D57: Alfano Luce | E57: South | F57: Public Streetlighting | G57: PPP | I57: Ischia | J57: =+_xlfn.XLOOKUP(B57,Sheet3!B:B,Sheet3!J:J,0) -> 0 | K57: =+J57/6*8 -> 0 | L57: 0 | M57: =+L57-K57 -> 0
B58: =+I58&H58 -> Somma Vesuviana | C58: CVS | D58: Alfano Luce | E58: South | F58: Public Streetlighting | G58: PPP | I58: Somma Vesuviana | J58: =+_xlfn.XLOOKUP(B58,Sheet3!B:B,Sheet3!J:J,0) -> 0 | K58: =+J58/6*8 -> 0 | L58: 0 | M58: =+L58-K58 -> 0
B59: =+I59&H59 -> Dolo | C59: CVS | D59: SG Dynamic | E59: North East | F59: Public Streetlighting | G59: PPP | I59: Dolo | J59: =+_xlfn.XLOOKUP(B59,Sheet3!B:B,Sheet3!J:J,0) -> 0 | K59: =+J59/6*8 -> 0 | L59: 0 | M59: =+L59-K59 -> 0
B60: =+I60&H60 -> Vicari | C60: CVS | D60: SG Dynamic | E60: South | F60: Public Streetlighting | G60: PPP | I60: Vicari | J60: =+_xlfn.XLOOKUP(B60,Sheet3!B:B,Sheet3!J:J,0) -> 0 | K60: =+J60/6*8 -> 0 | L60: 0 | M60: =+L60-K60 -> 0
B61: =+I61&H61 -> Marsciano | C61: CVS | D61: Tetra Engineering | E61: Centre | F61: Public Streetlighting | G61: PPP | I61: Marsciano | J61: =+_xlfn.XLOOKUP(B61,Sheet3!B:B,Sheet3!J:J,0) -> 0 | K61: =+J61/6*8 -> 0 | L61: 0 | M61: =+L61-K61 -> 0
B62: =+I62&H62 -> Savona ComunePPP-IPU-I480-02 | C62: CVS | D62: Organic | E62: North West | F62: Public Streetlighting | G62: PPP | H62: PPP-IPU-I480-02 | I62: Savona Comune | J62: =+_xlfn.XLOOKUP(B62,Sheet3!B:B,Sheet3!J:J,0) -> 509.2645 | K62: =+J62/6*8 -> 679.01933 | L62: 679.01933 | M62: =+L62-K62 -> -3.3333333e-06
B63: =+I63&H63 -> Finale Ligure (Sav Prov)PPP-IPU-D600-01 | C63: CVS | D63: Organic | E63: North West | F63: Public Streetlighting | G63: PPP | H63: PPP-IPU-D600-01 | I63: Finale Ligure (Sav Prov) | J63: =+_xlfn.XLOOKUP(B63,Sheet3!B:B,Sheet3!J:J,0) -> 0 | K63: =+J63/6*8 -> 0 | L63: 0 | M63: =+L63-K63 -> 0
B64: =+I64&H64 -> Borghetto Santo Spirito (Sav Prov)PPP-IPU-A999-01 | C64: CVS | D64: Organic | E64: North West | F64: Public Streetlighting | G64: PPP | H64: PPP-IPU-A999-01 | I64: Borghetto Santo Spirito (Sav Prov) | J64: =+_xlfn.XLOOKUP(B64,Sheet3!B:B,Sheet3!J:J,0) -> 0 | K64: =+J64/6*8 -> 0 | L64: 0 | M64: =+L64-K64 -> 0
B65: =+I65&H65 -> Spotorno (Sav Prov)PPP-IPU-I926-01 | C65: CVS | D65: Organic | E65: North West | F65: Public Streetlighting | G65: PPP | H65: PPP-IPU-I926-01 | I65: Spotorno (Sav Prov) | J65: =+_xlfn.XLOOKUP(B65,Sheet3!B:B,Sheet3!J:J,0) -> 0 | K65: =+J65/6*8 -> 0 | L65: 0.75075 | M65: =+L65-K65 -> 0.75075
B66: =+I66&H66 -> Pontirolo NuovoPPP-IPU-G867-01 | C66: CVS | D66: Organic | E66: North West | F66: Public Streetlighting | G66: PPP | H66: PPP-IPU-G867-01 | I66: Pontirolo Nuovo | J66: =+_xlfn.XLOOKUP(B66,Sheet3!B:B,Sheet3!J:J,0) -> 50.92224 | K66: =+J66/6*8 -> 67.89632 | L66: 67.89632 | M66: =+L66-K66 -> 0
B67: =+I67&H67 -> Vedano OlonaAQ1-IPU-L703-01 | C67: ATL | D67: Organic | E67: North West | F67: Public Streetlighting | G67: AQ1 | H67: AQ1-IPU-L703-01 | I67: Vedano Olona | J67: =+_xlfn.XLOOKUP(B67,Sheet3!B:B,Sheet3!J:J,0) -> 0 | K67: =+J67/6*8 -> 0 | L67: 0 | M67: =+L67-K67 -> 0
B68: =+I68&H68 -> Savona Gallerie (Sav Prov)PPP-IPU-I480-03 | C68: CVS | D68: Organic | E68: North West | F68: Public Streetlighting | G68: PPP | H68: PPP-IPU-I480-03 | I68: Savona Gallerie (Sav Prov) | J68: =+_xlfn.XLOOKUP(B68,Sheet3!B:B,Sheet3!J:J,0) -> 0 | K68: =+J68/6*8 -> 0 | L68: 0 | M68: =+L68-K68 -> 0
B69: =+I69&H69 -> MezzagoPPP-IPU-F165-01 | C69: CVS | D69: Organic | E69: North West | F69: Public Streetlighting | G69: PPP | H69: PPP-IPU-F165-01 | I69: Mezzago | J69: =+_xlfn.XLOOKUP(B69,Sheet3!B:B,Sheet3!J:J,0) -> 30.519 | K69: =+J69/6*8 -> 40.692 | L69: 40.692 | M69: =+L69-K69 -> 0
B70: =+I70&H70 -> Stella (Sav Prov)PPP-IPU-I946-01 | C70: CVS | D70: Organic | E70: North West | F70: Public Streetlighting | G70: PPP | H70: PPP-IPU-I946-01 | I70: Stella (Sav Prov) | J70: =+_xlfn.XLOOKUP(B70,Sheet3!B:B,Sheet3!J:J,0) -> 0 | K70: =+J70/6*8 -> 0 | L70: 0 | M70: =+L70-K70 -> 0
B71: =+I71&H71 -> Settimo TorinesePPP-IPU-I703-01 | C71: CVS | D71: Organic | E71: North West | F71: Public Streetlighting | G71: PPP | H71: PPP-IPU-I703-01 | I71: Settimo Torinese | J71: =+_xlfn.XLOOKUP(B71,Sheet3!B:B,Sheet3!J:J,0) -> 0 | K71: =+J71/6*8 -> 0 | L71: 0 | M71: =+L71-K71 -> 0
B72: =+I72&H72 -> GavirateAQ1-IPU-D946-01 | C72: ATL | D72: Organic | E72: North West | F72: Public Streetlighting | G72: AQ1 | H72: AQ1-IPU-D946-01 | I72: Gavirate | J72: =+_xlfn.XLOOKUP(B72,Sheet3!B:B,Sheet3!J:J,0) -> 41.69322 | K72: =+J72/6*8 -> 55.59096 | L72: 55.59096 | M72: =+L72-K72 -> 0
B73: =+I73&H73 -> CantalupaATI-IPU-B628-01 | C73: CVS | D73: Organic | E73: North West | F73: Public Streetlighting | G73: PPP | H73: ATI-IPU-B628-01 | I73: Cantalupa | J73: =+_xlfn.XLOOKUP(B73,Sheet3!B:B,Sheet3!J:J,0) -> 15.13641 | K73: =+J73/6*8 -> 20.18188 | L73: 20.18188 | M73: =+L73-K73 -> 0
... B149: =+I149&H149 -> Senigallia PLPPP-IPU-I608-01 | C149: CVS | D149: Organic | E149: Centre | F149: Public Streetlighting | G149: PPP | H149: PPP-IPU-I608-01 | I149: Senigallia PL | J149: =+_xlfn.XLOOKUP(B149,Sheet3!B:B,Sheet3!J:J,0) -> 633.01633 | K149: =+J149/6*8 -> 844.02177 | L149: 835.09283 | M149: =+L149-K149 -> -8.9289433
B150: =+I150&H150 -> Roma Servizi per la Mobilità S.r.l. | C150: ATL | D150: Organic | E150: Centre | F150: Other Revenues | G150: PPP | I150: Roma Servizi per la Mobilità S.r.l. | J150: =+_xlfn.XLOOKUP(B150,Sheet3!B:B,Sheet3!J:J,0) -> 0 | K150: =+J150/6*8 -> 0 | L150: 0 | M150: =+L150-K150 -> 0
B151: =+I151&H151 -> Bussi sul Tirino HMPPP-EEE-B294-03 | C151: CVS | D151: Organic | E151: Centre | F151: Smart Buildings | G151: Smart Buildings | H151: PPP-EEE-B294-03 | I151: Bussi sul Tirino HM | J151: =+_xlfn.XLOOKUP(B151,Sheet3!B:B,Sheet3!J:J,0) -> 142.51806 | K151: =+J151/6*8 -> 190.02408 | L151: 190.02408 | M151: =+L151-K151 -> 0
B152: =+I152&H152 -> Acquaviva PicenaPPP-IPU-A047-01 | C152: CVS | D152: Organic | E152: Centre | F152: Public Streetlighting | G152: PPP | H152: PPP-IPU-A047-01 | I152: Acquaviva Picena | J152: =+_xlfn.XLOOKUP(B152,Sheet3!B:B,Sheet3!J:J,0) -> 77.59572 | K152: =+J152/6*8 -> 103.46096 | L152: 103.89204 | M152: =+L152-K152 -> 0.43108
B153: =+I153&H153 -> Piceno Consorzio ind.PPP-IPU-A462-01 | C153: CVS | D153: Organic | E153: Centre | F153: Public Streetlighting | G153: PPP | H153: PPP-IPU-A462-01 | I153: Piceno Consorzio ind. | J153: =+_xlfn.XLOOKUP(B153,Sheet3!B:B,Sheet3!J:J,0) -> 86.1931 | K153: =+J153/6*8 -> 114.92413 | L153: 126.4159 | M153: =+L153-K153 -> 11.491767
B154: =+I154&H154 -> AtriPPP-IPU-A488-01 | C154: CVS | D154: Organic | E154: Centre | F154: Public Streetlighting | G154: PPP | H154: PPP-IPU-A488-01 | I154: Atri | J154: =+_xlfn.XLOOKUP(B154,Sheet3!B:B,Sheet3!J:J,0) -> 336.48346 | K154: =+J154/6*8 -> 448.64461 | L154: 430.19312 | M154: =+L154-K154 -> -18.451493
B155: =+I155&H155 -> Bussi sul Tirino PLPPP-IPU-B294-01 | C155: CVS | D155: Organic | E155: Centre | F155: Public Streetlighting | G155: PPP | H155: PPP-IPU-B294-01 | I155: Bussi sul Tirino PL | J155: =+_xlfn.XLOOKUP(B155,Sheet3!B:B,Sheet3!J:J,0) -> 79.00706 | K155: =+J155/6*8 -> 105.34275 | L155: 105.37949 | M155: =+L155-K155 -> 0.036743333
B156: =+I156&H156 -> Carpineto SinelloPPP-IPU-B826-01 | C156: CVS | D156: Organic | E156: Centre | F156: Public Streetlighting | G156: PPP | H156: PPP-IPU-B826-01 | I156: Carpineto Sinello | J156: =+_xlfn.XLOOKUP(B156,Sheet3!B:B,Sheet3!J:J,0) -> 30.51626 | K156: =+J156/6*8 -> 40.688347 | L156: 38.75153 | M156: =+L156-K156 -> -1.9368167
B157: =+I157&H157 -> CerchioPPP-IPU-C492-01 | C157: CVS | D157: Organic | E157: Centre | F157: Public Streetlighting | G157: PPP | H157: PPP-IPU-C492-01 | I157: Cerchio | J157: =+_xlfn.XLOOKUP(B157,Sheet3!B:B,Sheet3!J:J,0) -> 35.47825 | K157: =+J157/6*8 -> 47.304333 | L157: 45.38943 | M157: =+L157-K157 -> -1.9149033
B158: =+I158&H158 -> LanuvioPPP-IPU-C767-01 | C158: CVS | D158: Organic | E158: Centre | F158: Public Streetlighting | G158: PPP | H158: PPP-IPU-C767-01 | I158: Lanuvio | J158: =+_xlfn.XLOOKUP(B158,Sheet3!B:B,Sheet3!J:J,0) -> 62.47737 | K158: =+J158/6*8 -> 83.30316 | L158: 106.87797 | M158: =+L158-K158 -> 23.57481
B159: =+I159&H159 -> LettomanoppelloPPP-IPU-E558-01 | C159: CVS | D159: Organic | E159: Centre | F159: Public Streetlighting | G159: PPP | H159: PPP-IPU-E558-01 | I159: Lettomanoppello | J159: =+_xlfn.XLOOKUP(B159,Sheet3!B:B,Sheet3!J:J,0) -> 73.15796 | K159: =+J159/6*8 -> 97.543947 | L159: 95.30496 | M159: =+L159-K159 -> -2.2389867
B160: =+I160&H160 -> MonteodorisioPPP-IPU-F582-01 | C160: CVS | D160: Organic | E160: Centre | F160: Public Streetlighting | G160: PPP | H160: PPP-IPU-F582-01 | I160: Monteodorisio | J160: =+_xlfn.XLOOKUP(B160,Sheet3!B:B,Sheet3!J:J,0) -> 45.19932 | K160: =+J160/6*8 -> 60.26576 | L160: 60.26576 | M160: =+L160-K160 -> 0
B161: =+I161&H161 -> Morro d'Oro PLPPP-IPU-F747-01 | C161: CVS | D161: Organic | E161: Centre | F161: Public Streetlighting | G161: PPP | H161: PPP-IPU-F747-01 | I161: Morro d'Oro PL | J161: =+_xlfn.XLOOKUP(B161,Sheet3!B:B,Sheet3!J:J,0) -> 51.25141 | K161: =+J161/6*8 -> 68.335213 | L161: 67.37643 | M161: =+L161-K161 -> -0.95878333
B162: =+I162&H162 -> Palombara SabinaPPP-IPU-G293-01 | C162: CVS | D162: Organic | E162: Centre | F162: Public Streetlighting | G162: PPP | H162: PPP-IPU-G293-01 | I162: Palombara Sabina | J162: =+_xlfn.XLOOKUP(B162,Sheet3!B:B,Sheet3!J:J,0) -> 140.54868 | K162: =+J162/6*8 -> 187.39824 | L162: 189.11515 | M162: =+L162-K162 -> 1.71691
... B180: =+I180&H180 -> Petriano Proroga tecnicaCL3-IPU-G514-02 | C180: ATL | D180: Organic | E180: Centre | F180: Public Streetlighting | G180: CL3 | H180: CL3-IPU-G514-02 | I180: Petriano Proroga tecnica | J180: =+_xlfn.XLOOKUP(B180,Sheet3!B:B,Sheet3!J:J,0) -> 0 | K180: =+J180/6*8 -> 0 | L180: 0 | M180: =+L180-K180 -> 0
B181: =+I181&H181 -> Potenza Picena Proroga tecnica | C181: ATL | D181: Organic | E181: Centre | F181: Public Streetlighting | G181: CL3 | I181: Potenza Picena Proroga tecnica | J181: =+_xlfn.XLOOKUP(B181,Sheet3!B:B,Sheet3!J:J,0) -> 0 | K181: =+J181/6*8 -> 0 | L181: 0 | M181: =+L181-K181 -> 0
B182: =+I182&H182 -> Potenza Picena PPPPPP-IPU-F632-01 | C182: CVS | D182: Organic | E182: Centre | F182: Public Streetlighting | G182: PPP | H182: PPP-IPU-F632-01 | I182: Potenza Picena PPP | J182: =+_xlfn.XLOOKUP(B182,Sheet3!B:B,Sheet3!J:J,0) -> 0 | K182: =+J182/6*8 -> 0 | L182: 0 | M182: =+L182-K182 -> 0
B183: =+I183&H183 -> Macerata PPPPPP-IPU-E783-01 | C183: CVS | D183: Organic | E183: Centre | F183: Public Streetlighting | G183: PPP | H183: PPP-IPU-E783-01 | I183: Macerata PPP | J183: =+_xlfn.XLOOKUP(B183,Sheet3!B:B,Sheet3!J:J,0) -> 0 | K183: =+J183/6*8 -> 0 | L183: 0 | M183: =+L183-K183 -> 0
B184: =+I184&H184 -> Pioraco PPPPPP-IPU-G690-01 | C184: CVS | D184: Organic | E184: Centre | F184: Public Streetlighting | G184: PPP | H184: PPP-IPU-G690-01 | I184: Pioraco PPP | J184: =+_xlfn.XLOOKUP(B184,Sheet3!B:B,Sheet3!J:J,0) -> 0 | K184: =+J184/6*8 -> 0 | L184: 0 | M184: =+L184-K184 -> 0
B185: =+I185&H185 -> Mondolfo PPPPPP-IPU-F348-01 | C185: CVS | D185: Organic | E185: Centre | F185: Public Streetlighting | G185: PPP | H185: PPP-IPU-F348-01 | I185: Mondolfo PPP | J185: =+_xlfn.XLOOKUP(B185,Sheet3!B:B,Sheet3!J:J,0) -> 0 | K185: =+J185/6*8 -> 0 | L185: 0 | M185: =+L185-K185 -> 0
B186: =+I186&H186 -> Roma Servizi per la Mobilità S.r.l. PPP-IPU-H501-02 | C186: ATL | D186: Organic | E186: Centre | F186: Service Contract | G186: PPP | H186: PPP-IPU-H501-02 | I186: Roma Servizi per la Mobilità S.r.l. | J186: =+_xlfn.XLOOKUP(B186,Sheet3!B:B,Sheet3!J:J,0) -> 20.88206 | K186: =+J186/6*8 -> 27.842747 | L186: 20.88207 | M186: =+L186-K186 -> -6.9606767
B187: =+I187&H187 -> Santa Maria di SalaPPP-IPU-I242-01 | C187: CVS | D187: Organic | E187: North East | F187: Public Streetlighting | G187: PPP | H187: PPP-IPU-I242-01 | I187: Santa Maria di Sala | J187: =+_xlfn.XLOOKUP(B187,Sheet3!B:B,Sheet3!J:J,0) -> 0 | K187: =+J187/6*8 -> 0 | L187: 8.7 | M187: =+L187-K187 -> 8.7
B188: =+I188&H188 -> Vier Scarl (Eco + Eco)SEC-PHV-L736-01 | C188: ATL | D188: Organic | E188: North East | F188: Photovoltaic | G188: Photovoltaic | H188: SEC-PHV-L736-01 | I188: Vier Scarl (Eco + Eco) | J188: =+_xlfn.XLOOKUP(B188,Sheet3!B:B,Sheet3!J:J,0) -> 39.47362 | K188: =+J188/6*8 -> 52.631493 | L188: 106.3128 | M188: =+L188-K188 -> 53.681307
B189: =+I189&H189 -> Venezia HMPPP-EEE-L736-01 | C189: ATL | D189: Organic | E189: North East | F189: Smart Buildings | G189: Smart Buildings | H189: PPP-EEE-L736-01 | I189: Venezia HM | J189: =+_xlfn.XLOOKUP(B189,Sheet3!B:B,Sheet3!J:J,0) -> 584.34707 | K189: =+J189/6*8 -> 779.12943 | L189: 801.04226 | M189: =+L189-K189 -> 21.912833
B190: =+I190&H190 -> Fiesso d'ArticoPPP-IPU-D578-01 | C190: CVS | D190: Organic | E190: North East | F190: Public Streetlighting | G190: PPP | H190: PPP-IPU-D578-01 | I190: Fiesso d'Artico | J190: =+_xlfn.XLOOKUP(B190,Sheet3!B:B,Sheet3!J:J,0) -> 2.72904 | K190: =+J190/6*8 -> 3.63872 | L190: 3.63872 | M190: =+L190-K190 -> 0
B191: =+I191&H191 -> FossòPPP-IPU-D748-01 | C191: CVS | D191: Organic | E191: North East | F191: Public Streetlighting | G191: PPP | H191: PPP-IPU-D748-01 | I191: Fossò | J191: =+_xlfn.XLOOKUP(B191,Sheet3!B:B,Sheet3!J:J,0) -> 18.57042 | K191: =+J191/6*8 -> 24.76056 | L191: 24.76056 | M191: =+L191-K191 -> 0
B192: =+I192&H192 -> MiraPPP-IPU-F229-01 | C192: CVS | D192: Organic | E192: North East | F192: Public Streetlighting | G192: PPP | H192: PPP-IPU-F229-01 | I192: Mira | J192: =+_xlfn.XLOOKUP(B192,Sheet3!B:B,Sheet3!J:J,0) -> 112.28669 | K192: =+J192/6*8 -> 149.71559 | L192: 149.71559 | M192: =+L192-K192 -> 3.3333333e-06
B193: =+I193&H193 -> MiranoPPP-IPU-F241-01 | C193: CVS | D193: Organic | E193: North East | F193: Public Streetlighting | G193: PPP | H193: PPP-IPU-F241-01 | I193: Mirano | J193: =+_xlfn.XLOOKUP(B193,Sheet3!B:B,Sheet3!J:J,0) -> 56.99496 | K193: =+J193/6*8 -> 75.99328 | L193: 75.99496 | M193: =+L193-K193 -> 0.00168
... B420: =+I420&H420 -> ColceresaEPC-IPU-M426-01 | C420: CVS | D420: Carollo | E420: North East | F420: Extra Revenues | G420: Extra Revenues | H420: EPC-IPU-M426-01 | I420: Colceresa | J420: =+_xlfn.XLOOKUP(B420,Sheet3!B:B,Sheet3!J:J,0) -> 0 | K420: =+J420/6*8 -> 0 | L420: 0 | M420: =+L420-K420 -> 0
B421: =+I421&H421 -> Belvedere Marittimo | C421: CVS | D421: Jovit | E421: South | F421: Extra Revenues | G421: Extra Revenues | I421: Belvedere Marittimo | J421: =+_xlfn.XLOOKUP(B421,Sheet3!B:B,Sheet3!J:J,0) -> 0 | K421: =+J421/6*8 -> 0 | L421: 0 | M421: =+L421-K421 -> 0
...

Sheet Sheet3
C2: Entity | D2: Org./Inorg. | E2: BU | F2: Business Stream | G2: Type of contract | H2: Codice Financial Commesse | I2: Comuni | J2: Giugno
B3: =+I3&H3 -> Varazze | C3: CVS | D3: Organic | E3: North West | F3: Public Streetlighting | G3: PPP | I3: Varazze | J3: 0
B4: =+I4&H4 -> Lerici PL | C4: CVS | D4: Organic | E4: North West | F4: Public Streetlighting | G4: PPP | I4: Lerici PL | J4: 0
B5: =+I5&H5 -> Levanto | C5: CVS | D5: Organic | E5: North West | F5: Public Streetlighting | G5: PPP | I5: Levanto | J5: 0
B6: =+I6&H6 -> SoriPPP-IPU-I852-01 | C6: CVS | D6: Organic | E6: North West | F6: Public Streetlighting | G6: PPP | H6: PPP-IPU-I852-01 | I6: Sori | J6: 0
B7: =+I7&H7 -> Avezzano 3SEC-PHV-A515-01 | C7: CVS | D7: Organic | E7: Centre | F7: Photovoltaic | G7: Photovoltaic | H7: SEC-PHV-A515-01 | I7: Avezzano 3 | J7: 0
B8: =+I8&H8 -> Avezzano 4SEC-PHV-A515-02 | C8: CVS | D8: Organic | E8: Centre | F8: Photovoltaic | G8: Photovoltaic | H8: SEC-PHV-A515-02 | I8: Avezzano 4 | J8: 0
B9: =+I9&H9 -> GiulianovaSEC-PHV-E058-01 | C9: CVS | D9: Organic | E9: Centre | F9: Photovoltaic | G9: Photovoltaic | H9: SEC-PHV-E058-01 | I9: Giulianova | J9: 0
B10: =+I10&H10 -> Montorio 1SEC-PHV-F690-01 | C10: CVS | D10: Organic | E10: Centre | F10: Photovoltaic | G10: Photovoltaic | H10: SEC-PHV-F690-01 | I10: Montorio 1 | J10: 0
B11: =+I11&H11 -> Montorio 3SEC-PHV-F690-02 | C11: CVS | D11: Organic | E11: Centre | F11: Photovoltaic | G11: Photovoltaic | H11: SEC-PHV-F690-02 | I11: Montorio 3 | J11: 0
B12: =+I12&H12 -> Montorio 4SEC-PHV-F690-03 | C12: CVS | D12: Organic | E12: Centre | F12: Photovoltaic | G12: Photovoltaic | H12: SEC-PHV-F690-03 | I12: Montorio 4 | J12: 0
B13: =+I13&H13 -> Sant'Arpino | C13: CVS | D13: Organic | E13: South | F13: Public Streetlighting | G13: PPP | I13: Sant'Arpino | J13: 0
B14: =+I14&H14 -> Avigliano Cemetery | C14: CVS | D14: Organic | E14: South | F14: Cemetary Services | G14: PPP | I14: Avigliano Cemetery | J14: 0
B15: =+I15&H15 -> Filiano Cemetery | C15: CVS | D15: Organic | E15: South | F15: Cemetary Services | G15: PPP | I15: Filiano Cemetery | J15: 0
B16: =+I16&H16 -> San Marzano di San GiuseppePPP-IPU-I018-01 | C16: CVS | D16: Organic | E16: South | F16: Public Streetlighting | G16: PPP | H16: PPP-IPU-I018-01 | I16: San Marzano di San Giuseppe | J16: 0
B17: =+I17&H17 -> Frignano | C17: CVS | D17: Organic | E17: South | F17: Public Streetlighting | G17: PPP | I17: Frignano | J17: 0
B18: =+I18&H18 -> Gricignano di Aversa | C18: CVS | D18: Organic | E18: South | F18: Public Streetlighting | G18: PPP | I18: Gricignano di Aversa | J18: 0
B19: =+I19&H19 -> Torano Castello | C19: CVS | D19: Organic | E19: South | F19: Public Streetlighting | G19: PPP | I19: Torano Castello | J19: 0
B20: =+I20&H20 -> Piano di SorrentoPPP-IPU-G568-01 | C20: CVS | D20: Organic | E20: South | F20: Public Streetlighting | G20: PPP | H20: PPP-IPU-G568-01 | I20: Piano di Sorrento | J20: 0
B21: =+I21&H21 -> Giardini-Naxos | C21: CVS | D21: Organic | E21: South | F21: Public Streetlighting | G21: PPP | I21: Giardini-Naxos | J21: 0
B22: =+I22&H22 -> Copertino 1SEC-PHV-C978-01 | C22: CVS | D22: Organic | E22: South | F22: Photovoltaic | G22: Photovoltaic | H22: SEC-PHV-C978-01 | I22: Copertino 1 | J22: 0
B23: =+I23&H23 -> Copertino 2SEC-PHV-C978-02 | C23: CVS | D23: Organic | E23: South | F23: Photovoltaic | G23: Photovoltaic | H23: SEC-PHV-C978-02 | I23: Copertino 2 | J23: 0
B24: =+I24&H24 -> Campi 1 | C24: CVS | D24: Organic | E24: South | F24: Photovoltaic | G24: Photovoltaic | I24: Campi 1 | J24: 0
B25: =+I25&H25 -> Belvedere Marittimo | C25: CVS | D25: Jovit | E25: South | F25: Public Streetlighting | G25: PPP | I25: Belvedere Marittimo | J25: 0
B26: =+I26&H26 -> Roccamonfina | C26: CVS | D26: Jovit | E26: South | F26: Public Streetlighting | G26: PPP | I26: Roccamonfina | J26: 0
B27: =+I27&H27 -> Sesto Campano | C27: CVS | D27: Jovit | E27: Centre | F27: Public Streetlighting | G27: PPP | I27: Sesto Campano | J27: 0
B28: =+I28&H28 -> RivarossaPPP-IPU-H344-01 | C28: CVS | D28: Samsic | E28: North West | F28: Public Streetlighting | G28: PPP | H28: PPP-IPU-H344-01 | I28: Rivarossa | J28: 0
B29: =+I29&H29 -> Torre D'IsolaPPP-IPU-L269-01 | C29: CVS | D29: Samsic | E29: North West | F29: Public Streetlighting | G29: PPP | H29: PPP-IPU-L269-01 | I29: Torre D'Isola | J29: 0
B30: =+I30&H30 -> Santo Stefano LodigianoPPP-IPU-I362-01 | C30: CVS | D30: Samsic | E30: North West | F30: Public Streetlighting | G30: PPP | H30: PPP-IPU-I362-01 | I30: Santo Stefano Lodigiano | J30: 0
B31: =+I31&H31 -> SecugnagoPPP-IPU-I561-01 | C31: CVS | D31: Samsic | E31: North West | F31: Public Streetlighting | G31: PPP | H31: PPP-IPU-I561-01 | I31: Secugnago | J31: 0
B32: =+I32&H32 -> Loro CiuffennaPPP-IPU-E693-01 | C32: CVS | D32: Samsic | E32: Centre | F32: Public Streetlighting | G32: PPP | H32: PPP-IPU-E693-01 | I32: Loro Ciuffenna | J32: 0
B33: =+I33&H33 -> Ricigliano | C33: CVS | D33: Alfano Luce | E33: South | F33: Public Streetlighting | G33: PPP | I33: Ricigliano | J33: 0
B34: =+I34&H34 -> Serino | C34: CVS | D34: Alfano Luce | E34: South | F34: Public Streetlighting | G34: PPP | I34: Serino | J34: 0
B35: =+I35&H35 -> San Cipriano PicentinoPPP-IPU-H800-01 | C35: CVS | D35: Alfano Luce | E35: South | F35: Public Streetlighting | G35: PPP | H35: PPP-IPU-H800-01 | I35: San Cipriano Picentino | J35: 0
B36: =+I36&H36 -> Vietri sul Mare | C36: CVS | D36: Alfano Luce | E36: South | F36: Public Streetlighting | G36: PPP | I36: Vietri sul Mare | J36: 0
B37: =+I37&H37 -> Umbertide | C37: CVS | D37: Tetra Engineering | E37: Centre | F37: Public Streetlighting | G37: PPP | I37: Umbertide | J37: 0
B38: =+I38&H38 -> Lizzanello | C38: CVS | D38: Ege Global Service | E38: South | F38: Public Streetlighting | G38: PPP | I38: Lizzanello | J38: 0
B39: =+I39&H39 -> San Donato Milanese | C39: CVS | D39: Ege Global Service | E39: South | F39: Public Streetlighting | G39: PPP | I39: San Donato Milanese | J39: 0
B40: =+I40&H40 -> Altro Not identified (Sud) 1 | C40: CVS | D40: Pipeline | E40: South | F40: Public Streetlighting | G40: PPP | I40: Altro Not identified (Sud) 1 | J40: 0
B41: =+I41&H41 -> Altro Not identified (Centre) | C41: CVS | D41: Pipeline | E41: Centre | F41: Public Streetlighting | G41: PPP | I41: Altro Not identified (Centre) | J41: 0
B42: =+I42&H42 -> Altro Not identified (North West) | C42: CVS | D42: Pipeline | E42: North West | F42: Public Streetlighting | G42: PPP | I42: Altro Not identified (North West) | J42: 0
B43: =+I43&H43 -> Altro Not identified (North East) | C43: ATL | D43: Pipeline | E43: North East | F43: Public Streetlighting | G43: PPP | I43: Altro Not identified (North East) | J43: 0
B44: =+I44&H44 -> AQ1 not yet iidentified (NW) | C44: ATL | D44: Organic | E44: North West | F44: Public Streetlighting | G44: AQ1 | I44: AQ1 not yet iidentified (NW) | J44: 0
B45: =+I45&H45 -> AQ1 not identified (NE) | C45: ATL | D45: Organic | E45: North East | F45: Public Streetlighting | G45: AQ1 | I45: AQ1 not identified (NE) | J45: 0
B46: =+I46&H46 -> AQ1 not identified (CE) | C46: ATL | D46: Organic | E46: Centre | F46: Public Streetlighting | G46: AQ1 | I46: AQ1 not identified (CE) | J46: 0
B47: =+I47&H47 -> Buildings not identified (NE) | C47: ATL | D47: Organic | E47: North East | F47: Smart Buildings | G47: Smart Buildings | I47: Buildings not identified (NE) | J47: 0
... B51: =+I51&H51 -> San Mango Piemonte | C51: CVS | D51: Jovit | E51: South | F51: Public Streetlighting | G51: PPP | I51: San Mango Piemonte | J51: 0
B52: =+I52&H52 -> Romagnano SesiaPPP-IPU-H502-01 | C52: CVS | D52: Samsic | E52: North West | F52: Public Streetlighting | G52: PPP | H52: PPP-IPU-H502-01 | I52: Romagnano Sesia | J52: 0
B53: =+I53&H53 -> MassalengoPPP-IPU-F028-01 | C53: CVS | D53: Samsic | E53: North West | F53: Public Streetlighting | G53: PPP | H53: PPP-IPU-F028-01 | I53: Massalengo | J53: 0
B54: =+I54&H54 -> Maiori | C54: CVS | D54: Alfano Luce | E54: South | F54: Public Streetlighting | G54: PPP | I54: Maiori | J54: 0
B55: =+I55&H55 -> Minori | C55: CVS | D55: Alfano Luce | E55: South | F55: Public Streetlighting | G55: PPP | I55: Minori | J55: 0
B56: =+I56&H56 -> Castel San Giorgio | C56: CVS | D56: Alfano Luce | E56: South | F56: Public Streetlighting | G56: PPP | I56: Castel San Giorgio | J56: 0
B57: =+I57&H57 -> Ischia | C57: CVS | D57: Alfano Luce | E57: South | F57: Public Streetlighting | G57: PPP | I57: Ischia | J57: 0
B58: =+I58&H58 -> Somma Vesuviana | C58: CVS | D58: Alfano Luce | E58: South | F58: Public Streetlighting | G58: PPP | I58: Somma Vesuviana | J58: 0
B59: =+I59&H59 -> Dolo | C59: CVS | D59: SG Dynamic | E59: North East | F59: Public Streetlighting | G59: PPP | I59: Dolo | J59: 0
B60: =+I60&H60 -> Vicari | C60: CVS | D60: SG Dynamic | E60: South | F60: Public Streetlighting | G60: PPP | I60: Vicari | J60: 0
B61: =+I61&H61 -> Marsciano | C61: CVS | D61: Tetra Engineering | E61: Centre | F61: Public Streetlighting | G61: PPP | I61: Marsciano | J61: 0
B62: =+I62&H62 -> Savona ComunePPP-IPU-I480-02 | C62: CVS | D62: Organic | E62: North West | F62: Public Streetlighting | G62: PPP | H62: PPP-IPU-I480-02 | I62: Savona Comune | J62: 509.2645
B63: =+I63&H63 -> Finale Ligure (Sav Prov)PPP-IPU-D600-01 | C63: CVS | D63: Organic | E63: North West | F63: Public Streetlighting | G63: PPP | H63: PPP-IPU-D600-01 | I63: Finale Ligure (Sav Prov) | J63: 0
B64: =+I64&H64 -> Borghetto Santo Spirito (Sav Prov)PPP-IPU-A999-01 | C64: CVS | D64: Organic | E64: North West | F64: Public Streetlighting | G64: PPP | H64: PPP-IPU-A999-01 | I64: Borghetto Santo Spirito (Sav Prov) | J64: 0
B65: =+I65&H65 -> Spotorno (Sav Prov)PPP-IPU-I926-01 | C65: CVS | D65: Organic | E65: North West | F65: Public Streetlighting | G65: PPP | H65: PPP-IPU-I926-01 | I65: Spotorno (Sav Prov) | J65: 0
B66: =+I66&H66 -> Pontirolo NuovoPPP-IPU-G867-01 | C66: CVS | D66: Organic | E66: North West | F66: Public Streetlighting | G66: PPP | H66: PPP-IPU-G867-01 | I66: Pontirolo Nuovo | J66: 50.92224
B67: =+I67&H67 -> Vedano OlonaAQ1-IPU-L703-01 | C67: ATL | D67: Organic | E67: North West | F67: Public Streetlighting | G67: AQ1 | H67: AQ1-IPU-L703-01 | I67: Vedano Olona | J67: 0
B68: =+I68&H68 -> Savona Gallerie (Sav Prov)PPP-IPU-I480-03 | C68: CVS | D68: Organic | E68: North West | F68: Public Streetlighting | G68: PPP | H68: PPP-IPU-I480-03 | I68: Savona Gallerie (Sav Prov) | J68: 0
B69: =+I69&H69 -> MezzagoPPP-IPU-F165-01 | C69: CVS | D69: Organic | E69: North West | F69: Public Streetlighting | G69: PPP | H69: PPP-IPU-F165-01 | I69: Mezzago | J69: 30.519
B70: =+I70&H70 -> Stella (Sav Prov)PPP-IPU-I946-01 | C70: CVS | D70: Organic | E70: North West | F70: Public Streetlighting | G70: PPP | H70: PPP-IPU-I946-01 | I70: Stella (Sav Prov) | J70: 0
B71: =+I71&H71 -> Settimo TorinesePPP-IPU-I703-01 | C71: CVS | D71: Organic | E71: North West | F71: Public Streetlighting | G71: PPP | H71: PPP-IPU-I703-01 | I71: Settimo Torinese | J71: 0
B72: =+I72&H72 -> GavirateAQ1-IPU-D946-01 | C72: ATL | D72: Organic | E72: North West | F72: Public Streetlighting | G72: AQ1 | H72: AQ1-IPU-D946-01 | I72: Gavirate | J72: 41.69322
B73: =+I73&H73 -> CantalupaATI-IPU-B628-01 | C73: CVS | D73: Organic | E73: North West | F73: Public Streetlighting | G73: PPP | H73: ATI-IPU-B628-01 | I73: Cantalupa | J73: 15.13641
... B149: =+I149&H149 -> Senigallia PLPPP-IPU-I608-01 | C149: CVS | D149: Organic | E149: Centre | F149: Public Streetlighting | G149: PPP | H149: PPP-IPU-I608-01 | I149: Senigallia PL | J149: 633.01633
B150: =+I150&H150 -> Roma Servizi per la Mobilità S.r.l. | C150: ATL | D150: Organic | E150: Centre | F150: Other Revenues | G150: PPP | I150: Roma Servizi per la Mobilità S.r.l. | J150: 0
B151: =+I151&H151 -> Bussi sul Tirino HMPPP-EEE-B294-03 | C151: CVS | D151: Organic | E151: Centre | F151: Smart Buildings | G151: Smart Buildings | H151: PPP-EEE-B294-03 | I151: Bussi sul Tirino HM | J151: 142.51806
B152: =+I152&H152 -> Acquaviva PicenaPPP-IPU-A047-01 | C152: CVS | D152: Organic | E152: Centre | F152: Public Streetlighting | G152: PPP | H152: PPP-IPU-A047-01 | I152: Acquaviva Picena | J152: 77.59572
B153: =+I153&H153 -> Piceno Consorzio ind.PPP-IPU-A462-01 | C153: CVS | D153: Organic | E153: Centre | F153: Public Streetlighting | G153: PPP | H153: PPP-IPU-A462-01 | I153: Piceno Consorzio ind. | J153: 86.1931
B154: =+I154&H154 -> AtriPPP-IPU-A488-01 | C154: CVS | D154: Organic | E154: Centre | F154: Public Streetlighting | G154: PPP | H154: PPP-IPU-A488-01 | I154: Atri | J154: 336.48346
B155: =+I155&H155 -> Bussi sul Tirino PLPPP-IPU-B294-01 | C155: CVS | D155: Organic | E155: Centre | F155: Public Streetlighting | G155: PPP | H155: PPP-IPU-B294-01 | I155: Bussi sul Tirino PL | J155: 79.00706
B156: =+I156&H156 -> Carpineto SinelloPPP-IPU-B826-01 | C156: CVS | D156: Organic | E156: Centre | F156: Public Streetlighting | G156: PPP | H156: PPP-IPU-B826-01 | I156: Carpineto Sinello | J156: 30.51626
B157: =+I157&H157 -> CerchioPPP-IPU-C492-01 | C157: CVS | D157: Organic | E157: Centre | F157: Public Streetlighting | G157: PPP | H157: PPP-IPU-C492-01 | I157: Cerchio | J157: 35.47825
B158: =+I158&H158 -> LanuvioPPP-IPU-C767-01 | C158: CVS | D158: Organic | E158: Centre | F158: Public Streetlighting | G158: PPP | H158: PPP-IPU-C767-01 | I158: Lanuvio | J158: 62.47737
B159: =+I159&H159 -> LettomanoppelloPPP-IPU-E558-01 | C159: CVS | D159: Organic | E159: Centre | F159: Public Streetlighting | G159: PPP | H159: PPP-IPU-E558-01 | I159: Lettomanoppello | J159: 73.15796
B160: =+I160&H160 -> MonteodorisioPPP-IPU-F582-01 | C160: CVS | D160: Organic | E160: Centre | F160: Public Streetlighting | G160: PPP | H160: PPP-IPU-F582-01 | I160: Monteodorisio | J160: 45.19932
B161: =+I161&H161 -> Morro d'Oro PLPPP-IPU-F747-01 | C161: CVS | D161: Organic | E161: Centre | F161: Public Streetlighting | G161: PPP | H161: PPP-IPU-F747-01 | I161: Morro d'Oro PL | J161: 51.25141
B162: =+I162&H162 -> Palombara SabinaPPP-IPU-G293-01 | C162: CVS | D162: Organic | E162: Centre | F162: Public Streetlighting | G162: PPP | H162: PPP-IPU-G293-01 | I162: Palombara Sabina | J162: 140.54868
... B420: =+I420&H420 -> ColceresaEPC-IPU-M426-01 | C420: CVS | D420: Carollo | E420: North East | F420: Extra Revenues | G420: Extra Revenues | H420: EPC-IPU-M426-01 | I420: Colceresa | J420: 0
B421: =+I421&H421 -> Belvedere Marittimo | C421: CVS | D421: Jovit | E421: South | F421: Extra Revenues | G421: Extra Revenues | I421: Belvedere Marittimo | J421: 0
B422: =+I422&H422 -> Roccamonfina | C422: CVS | D422: Jovit | E422: South | F422: Extra Revenues | G422: Extra Revenues | I422: Roccamonfina | J422: 0
B423: =+I423&H423 -> Sesto Campano | C423: CVS | D423: Jovit | E423: Centre | F423: Extra Revenues | G423: Extra Revenues | I423: Sesto Campano | J423: 0
B424: =+I424&H424 -> San Mango Piemonte | C424: CVS | D424: Jovit | E424: South | F424: Extra Revenues | G424: Extra Revenues | I424: San Mango Piemonte | J424: 0
B425: =+I425&H425 -> Romagnano Sesia | C425: CVS | D425: Samsic | E425: North West | F425: Extra Revenues | G425: Extra Revenues | I425: Romagnano Sesia | J425: 0
B426: =+I426&H426 -> Massalengo | C426: CVS | D426: Samsic | E426: North West | F426: Extra Revenues | G426: Extra Revenues | I426: Massalengo | J426: 0
B427: =+I427&H427 -> Rivarossa | C427: CVS | D427: Samsic | E427: North West | F427: Extra Revenues | G427: Extra Revenues | I427: Rivarossa | J427: 0
B428: =+I428&H428 -> Torre D'Isola | C428: CVS | D428: Samsic | E428: North West | F428: Extra Revenues | G428: Extra Revenues | I428: Torre D'Isola | J428: 0
B429: =+I429&H429 -> Santo Stefano Lodigiano | C429: CVS | D429: Samsic | E429: North West | F429: Extra Revenues | G429: Extra Revenues | I429: Santo Stefano Lodigiano | J429: 0
B430: =+I430&H430 -> Secugnago | C430: CVS | D430: Samsic | E430: North West | F430: Extra Revenues | G430: Extra Revenues | I430: Secugnago | J430: 0
B431: =+I431&H431 -> Loro Ciuffenna | C431: CVS | D431: Samsic | E431: Centre | F431: Extra Revenues | G431: Extra Revenues | I431: Loro Ciuffenna | J431: 0
B432: =+I432&H432 -> SannicolaEPC-IPU-I059-01 | C432: CVS | D432: Alfano Luce | E432: South | F432: Extra Revenues | G432: Extra Revenues | H432: EPC-IPU-I059-01 | I432: Sannicola | J432: 0
B433: =+I433&H433 -> Montalbano JonicoEPC-IPU-F399-01 | C433: CVS | D433: Alfano Luce | E433: South | F433: Extra Revenues | G433: Extra Revenues | H433: EPC-IPU-F399-01 | I433: Montalbano Jonico | J433: 0
B434: =+I434&H434 -> Ricigliano | C434: CVS | D434: Alfano Luce | E434: South | F434: Extra Revenues | G434: Extra Revenues | I434: Ricigliano | J434: 0
B435: =+I435&H435 -> Serino | C435: CVS | D435: Alfano Luce | E435: South | F435: Extra Revenues | G435: Extra Revenues | I435: Serino | J435: 0
B436: =+I436&H436 -> San Martino D'AgriEPC-IPU-H994-01 | C436: CVS | D436: Alfano Luce | E436: South | F436: Extra Revenues | G436: Extra Revenues | H436: EPC-IPU-H994-01 | I436: San Martino D'Agri | J436: 0
...
