Workbook

Sheet Riepilogo Non Recurring
B1: 46023 | C1: 46054 | D1: 46082 | E1: 46113 | F1: 46143 | G1: 46174 | H1: 46204 | I1: 46235 | J1: 46266 | K1: 46296 | L1: 46327 | M1: 46357
A2: Non recurring | B2: =SUM(B3:B7) -> 162230.02 | C2: =SUM(C3:C7) -> 41762.22 | D2: =SUM(D3:D7) -> 171506.47 | E2: =SUM(E3:E7) -> 850823.35 | F2: =SUM(F3:F7) -> 226333.65 | G2: =SUM(G3:G7) -> 254433.28 | H2: =SUM(H3:H7) -> 119088.85 | I2: =SUM(I3:I7) -> 225190.18 | ... M2: =SUM(M3:M7) -> 0 | N2: =SUM(B2:M2) -> 2051368
A3: 700405 - Comp. Prof. Attinenti Attivita' Senza Rit. | B3: 0 | C3: 0 | D3: =+'700405'!I29+'700405'!I32 -> 3328 | E3: 0 | F3: 0 | G3: 0 | H3: =+'700405'!I85 -> 7589.77 | I3: 0
A4: 700407 - Comp. Prof. Attinenti Attivita' C/Rit. | B4: =+'700407'!I11+'700407'!I13 -> 5760.32 | C4: =+'700407'!I16 -> 979.17 | D4: 0 | E4: =+'700407'!I28+'700407'!I29+'700407'!I30+'700407'!I31+'700407'!I32+'700407'!I33+'700407'!I34 -> 579950.15 | F4: =+'700407'!I40+'700407'!I43 -> 31200 | G4: =+'700407'!I47+'700407'!I48+'700407'!I50+'700407'!I57+'700407'!I58+'700407'!I59 -> 35323.24 | H4: =+'700407'!I65+'700407'!I66+'700407'!I67 -> 26988 | I4: =+'700407'!I72+'700407'!I73+'700407'!I74+'700407'!I76+'700407'!I79 -> 43680
A5: 700409 - Comp. Prof. Attinenti Attivita' | B5: =+'700409'!I16 -> 112500 | C5: 0 | D5: =+'700409'!I22 -> 9920 | E5: =+'700409'!I35 -> 31250 | F5: 0 | G5: =+'700409'!I49+'700409'!I57 -> 31250 | H5: 0 | I5: =+'700409'!I73 -> 9280
A6: 702001 - Spese Di Consulenza | B6: =+'702001'!I13+'702001'!I16 -> 42012 | C6: =+'702001'!I19+'702001'!I20+'702001'!I22 -> 38760 | D6: =+'702001'!I29+'702001'!I30+'702001'!I31+'702001'!I32+'702001'!I33+'702001'!I37+'702001'!I38+'702001'!I39+'702001'!I40+'702001'!I41+'702001'!I43+'702001'!I44 -> 156644.11 | E6: =+'702001'!I49+'702001'!I50+'702001'!I52+'702001'!I56 -> 238032 | F6: =+'702001'!I57+'702001'!I60+'702001'!I61+'702001'!I63+'702001'!I64+'702001'!I67 -> 195133.65 | G6: =+'702001'!I70+'702001'!I71+'702001'!I74+'702001'!I75+'702001'!I76+'702001'!I78+'702001'!I81+'702001'!I82+'702001'!I83+'702001'!I85 -> 186622.54 | H6: =+'702001'!I90+'702001'!I92+'702001'!I93+'702001'!I94+'702001'!I95+'702001'!I96+'702001'!I101+'702001'!I105+'702001'!I107 -> 81173.09 | I6: =+'702001'!I112+'702001'!I113+'702001'!I114+'702001'!I120+'702001'!I121 -> 171372
A7: 700815 - Spese Per Trasferte | B7: =+'700815'!I50+'700815'!I101+'700815'!I107+'700815'!I125 -> 1957.7 | C7: =+'700815'!I200+'700815'!I211+'700815'!I238+'700815'!I267 -> 2023.05 | D7: =+'700815'!I319+'700815'!I381+'700815'!I398+'700815'!I399 -> 1614.36 | E7: =+'700815'!I577+'700815'!I684+'700815'!I694+'700815'!I703+'700815'!I708+'700815'!I717 -> 1591.2 | F7: 0 | G7: =+'700815'!I1155 -> 1237.5 | H7: =+'700815'!I1211+'700815'!I1223+'700815'!I1244+'700815'!I1271+'700815'!I1351+'700815'!I1354+'700815'!I1395 -> 3337.99 | I7: =+'700815'!I1403 -> 858.18

Sheet Costi di Prog.one
A1: COSTI DI PROGETTAZIONE | B1: DATA | C1: FORNITORE | D1: TOTALE
A2: 700405 - Comp. Prof. Attinenti Attivita' Senza Rit. | B2: 46053 | C2: MI10STUDIO SRL | D2: =+'700405'!I13 -> 16153.85
A3: 700405 - Comp. Prof. Attinenti Attivita' Senza Rit. | B3: 46053 | C3: RESTART GREEN SOLUTIONS SRL | D3: =+'700405'!I15 -> 8943.2
A4: 700405 - Comp. Prof. Attinenti Attivita' Senza Rit. | B4: 46053 | C4: RESTART ENGINEERING SRL | D4: =+'700405'!I17 -> 4230.24
A5: 700405 - Comp. Prof. Attinenti Attivita' Senza Rit. | B5: 46064 | C5: F-04337 MI10STUDIO SRL | D5: =+'700405'!I18 -> 646.15
A6: 700405 - Comp. Prof. Attinenti Attivita' Senza Rit. | B6: 46092 | C6: F-01930 RESTART GREEN SOLUTIONS SRL | D6: =+'700405'!I27 -> 26000
A7: 700405 - Comp. Prof. Attinenti Attivita' Senza Rit. | B7: 46132 | C7: F-01930 RESTART GREEN SOLUTIONS SRL | D7: =+'700405'!I40 -> 4095
A8: 700405 - Comp. Prof. Attinenti Attivita' Senza Rit. | B8: 46142 | C8: F-01930 RESTART GREEN SOLUTIONS SRL | D8: =+'700405'!I43 -> 9464
A9: 700407 - Comp. Prof. Attinenti Attivita' C/Rit. | B9: 46119 | C9: F-03690 STEFANO CALIGARA | D9: =+'700407'!I28 -> 17640
A10: Total - 700405 - Comp. Prof. Attinenti Attivita' Senza Rit. | B10: 46148 | C10: F-03613 BCM ENGINEERING S.R.L. | D10: =+'700405'!I45 -> 2652
A11: 700407 - Comp. Prof. Attinenti Attivita' C/Rit. | B11: 46168 | C11: F-04443 GMS ST.ASSOCIATO GUANELLA MONTANI SUSS | D11: =+'700407'!I43 -> 18720
A12: 700405 - Comp. Prof. Attinenti Attivita' Senza Rit. | B12: 46173 | C12: F-01911 RESTART ENERGY LAB S.R.L. | D12: =+'700405'!I50 -> 14050.85
A13: 700405 - Comp. Prof. Attinenti Attivita' Senza Rit. | B13: 46173 | C13: F-01930 RESTART GREEN SOLUTIONS SRL | D13: =+'700405'!I51 -> 13650.61
A14: 700405 - Comp. Prof. Attinenti Attivita' Senza Rit. | B14: 46173 | C14: F-01911 RESTART ENERGY LAB S.R.L. e F-01930 RESTART GREEN SOLUTIONS SRL | D14: =+'700405'!I55 -> 18281.6
A15: 700405 - Comp. Prof. Attinenti Attivita' Senza Rit. | B15: 46182 | C15: F-01911 RESTART ENERGY LAB S.R.L. | D15: 26000
A16: 700405 - Comp. Prof. Attinenti Attivita' Senza Rit. | B16: 46182 | C16: F-01911 RESTART ENERGY LAB S.R.L. | D16: 5265
A17: 700405 - Comp. Prof. Attinenti Attivita' Senza Rit. | B17: 46182 | C17: F-01911 RESTART ENERGY LAB S.R.L. | D17: 2600
A18: 700405 - Comp. Prof. Attinenti Attivita' Senza Rit. | B18: 46182 | C18: F-01911 RESTART ENERGY LAB S.R.L. | D18: 16640
A19: 700405 - Comp. Prof. Attinenti Attivita' Senza Rit. | B19: 46184 | C19: F-01930 RESTART GREEN SOLUTIONS SRL | D19: =+'700405'!I66 -> 10337.6
A20: 700405 - Comp. Prof. Attinenti Attivita' Senza Rit. | B20: 46196 | C20: F-01930 RESTART GREEN SOLUTIONS SRL | D20: =+'700405'!I68 -> 4303.94
A21: 700405 - Comp. Prof. Attinenti Attivita' Senza Rit. | B21: 46202 | C21: F-01930 RESTART GREEN SOLUTIONS SRL | D21: =+'700405'!I70 -> 3706.56
A22: 700409 - Comp. Prof. Attinenti Attivita' | B22: 46203 | C22: F-02941 MY_E_SERVICES SRLS | D22: =+'700409'!I56 -> 9828
A23: Total - 700407 - Comp. Prof. Attinenti Attivita' C/Rit. | B23: 46211 | C23: F-04443 GMS ST.ASSOCIATO GUANELLA MONTANI SUSS | D23: =+'700407'!I62 -> 30680
A24: Total - 700405 - Comp. Prof. Attinenti Attivita' Senza Rit. | B24: 46213 | C24: F-01911 RESTART ENERGY LAB S.R.L. | D24: =+'700405'!I80 -> 6179.26
A25: Total - 700405 - Comp. Prof. Attinenti Attivita' Senza Rit. | B25: 46213 | C25: F-01911 RESTART ENERGY LAB S.R.L. | D25: =+'700405'!I81 -> 19650.18
A26: Total - 700405 - Comp. Prof. Attinenti Attivita' Senza Rit. | B26: 46213 | C26: F-01911 RESTART ENERGY LAB S.R.L. | D26: =+'700405'!I82 -> 20273.34
A27: Total - 700407 - Comp. Prof. Attinenti Attivita' C/Rit. | B27: 46240 | C27: F-03690 STEFANO CALIGARA | D27: =+'700407'!I77 -> 6300
A28: Total - 700405 - Comp. Prof. Attinenti Attivita' Senza Rit. | B28: 46254 | C28: F-01911 RESTART ENERGY LAB S.R.L. | D28: =+'700405'!I90 -> 5200
A29: Total - 700405 - Comp. Prof. Attinenti Attivita' Senza Rit. | B29: 46254 | C29: F-01911 RESTART ENERGY LAB S.R.L. | D29: =+'700405'!I91 -> 14734.72
A30: Total - 700405 - Comp. Prof. Attinenti Attivita' Senza Rit. | B30: 46254 | C30: F-01911 RESTART ENERGY LAB S.R.L. | D30: =+'700405'!I92 -> 7280
A31: Total - 700405 - Comp. Prof. Attinenti Attivita' Senza Rit. | B31: 46254 | C31: F-01911 RESTART ENERGY LAB S.R.L. | D31: =+'700405'!I93 -> 16640
A32: Total - 700405 - Comp. Prof. Attinenti Attivita' Senza Rit. | B32: 46254 | C32: F-01911 RESTART ENERGY LAB S.R.L. | D32: =+'700405'!I94 -> 3120
A54: TOTALE | D54: =SUM(D2:D53) -> 363266.1

Sheet 700405
A1: CiviSmart
A2: Parent Company : CiviSmart S.p.A.
A3: CIV| Schede Contabili
A4: 1 January 2026 - 31 August 2026
A7: Account | B7: Type | C7: Date | D7: Document Number | E7: Name | F7: Memo | G7: [IL] Reference Date | H7: [IL] Reference # | I7: Debit | J7: NATURA DEL COSTO | K7: Credit | L7: Balance
A8: 70 - COSTI PER SERVIZI | L8: 0
A9: 7004 - Servizi Di Lavoro Parasub | L9: 0
A10: 700405 - Comp. Prof. Attinenti Attivita' Senza Rit. | L10: 1060008.2
B11: Journal | C11: 46053 | D11: JE-CIV-19439 | E11: Delfino Roberto Nicola e Stefano Romano | I11: 4320 | L11: 1064238.5
B12: Journal | C12: 46053 | D12: JE-CIV-19442 | I12: 72 | L12: 1064310.5
B13: Journal | C13: 46053 | D13: JE-CIV-19446 | E13: MI10STUDIO SRL | F13: Predisposizione studio di fattibilita tecnico-economica per il Comune di Canegrate (MI) nell ambito della riqualifica illuminotecnica e normativa degli impianti di pubblica illuminazione | I13: 16153.85 | J13: Costi di progettazione | L13: 1080464.3
B14: Journal | C14: 46053 | D14: JE-CIV-19987 | I14: 211.51 | L14: 1080675.8
B15: Journal | C15: 46053 | D15: JE-CIV-19087 | E15: RESTART GREEN SOLUTIONS SRL | F15: Progetto di Fattibilità Comune di Borgetto (PA) | I15: 8943.2 | J15: Costi di progettazione | L15: 1089619
B16: Journal | C16: 46053 | D16: JE-CIV-19438 | I16: 2168.98 | L16: 1091788
B17: Journal | C17: 46053 | D17: JE-CIV-19149 | E17: RESTART ENGINEERING SRL | F17: Progetto di Fattibilità Comune di San Teodoro | I17: 4230.24 | J17: Costi di progettazione | L17: 1096108
B18: Bill | C18: 46064 | D18: S/2026/0913/A | E18: F-04337 MI10STUDIO SRL | F18: Predisposizione studio di fattibilita tecnico-economica per il Comune di Canegrate (MI) nell ambito della riqualifica illuminotecnica e normativa degli impianti di pubblica illuminazione. | G18: 46049 | H18: 00013/26 | I18: 646.15 | J18: Costi di progettazione | L18: 1096754.2
B19: Bill | C19: 46064 | D19: S/2026/0910/A | E19: F-01125 Miguel Alberto Montesano | F19: Acconto Onorario D.L. e Coord. Sic. in fase di Esec., opere rifunzionalizzazione, efficientamento, manut. e gestione dell Imp.di Pubb. illuminazione (ampliamenti), del Comune di Maratea (PZ). | G19: 46058 | H19: FPR 1/26 | I19: 264 | L19: 1097018.2
B20: Bill | C20: 46073 | D20: S/2026/1361/A | E20: F-01803 NOE' COMI | G20: 46072 | H20: 6 | I20: 8112 | L20: 1105130.2
B21: Bill | C21: 46076 | D21: S/2026/1408/A | E21: F-01789 Daniele Monteduro | G21: 46073 | H21: FPR-I17/26 | I21: 4512.99 | L21: 1109643.1
B22: Journal | C22: 46081 | D22: JE-CIV-19152 | E22: Delfino Roberto Nicola | I22: 10169 | L22: 1119812.1
B23: Journal | C23: 46081 | D23: JE-CIV-19142 | E23: Delfino Roberto Nicola | I23: 20225 | L23: 1126827.1
B24: Journal | C24: 46081 | D24: JE-CIV-19160 | E24: archimede s.r.l | F24: Collaudo tecnico amministrativo Vicopisano | I24: 7015 | L24: 1128699.1
B25: Journal | C25: 46081 | D25: JE-CIV-19449 | I25: 1872 | L25: 1148924.1
B26: Journal | C26: 46081 | D26: JE-CIV-19506 | I26: 2900.35 | L26: 1151824.5
B27: Bill | C27: 46092 | D27: S/2026/1815/A | E27: F-01930 RESTART GREEN SOLUTIONS SRL | F27: Progetti di fattibilità - Comune di Milazzo, Marsala, San Marco D'Alunzio, Riesi, Caltanisetta | G27: 46081 | H27: 6 /I | I27: 26000 | J27: Costi di progettazione | L27: 1177824.5
B28: Bill | C28: 46093 | D28: S/2026/1897/A | E28: F-03613 BCM ENGINEERING S.R.L. | F28: Piano Economico e Finanziario per Promotore e/o partecipazione a Gara in Project Financing per Pubblica Illuminazione // N. 15 PEF: San Felice a Cancello, Messina, Trecchina, Cagnano Varano, Campobello di Mazzara, Borghetto, Recalbuto, Piana degli Albanesi, Sant Angelo Le Fratte, Sab Nicola Arcella, Calvanico, Roggiano Gravina, Faggiano, Pignola, Sommatino | G28: 46093 | H28: 1 | I28: 3900 | L28: 1181724.5
B29: Bill | C29: 46097 | D29: S/2026/2054/A | E29: F-03954 STELLA NAPOLEONE | F29: calcoli illuminotecnici del bando AREST per il comune di Saronno | G29: 46090 | H29: 04/2026 | I29: 2340 | J29: Consulenza tecnica | L29: 1184064.5
B30: Bill | C30: 46098 | D30: S/2026/2113/A | E30: F-01928 STEFANO ROMANO | F30: Attività di consulenza tecnica per le attività di informatizzazione degli impianti di illuminazione pubblica Cellino San Marco BR | G30: 46090 | H30: 2/2026 | I30: 2100 | L30: 1186164.5
B31: Bill | C31: 46105 | D31: S/2026/2396/A | E31: F-04414 GREENWICH S.R.L. | F31: fattura per direzione lavori Ing. Ivan De Bonis - LAVORI MONGRASSANO EFFICIENTAMENTO PUBBLICA ILLUMINAZIONE | G31: 46101 | H31: 1 | I31: 15062 | L31: 1201226.5
B32: Bill | C32: 46108 | D32: S/2026/2472/A | E32: F-04412 DAMATO GIANLUCA | F32: Consulenza strutturale // Consulenza per progettazione di plinto di fondazione per torre faro in Via Buozzi Savona Codice commessa PPP-IPU-I480-02 | G32: 46100 | H32: 12 | I32: 988 | J32: Consulenza tecnica | L32: 1202214.5
B33: Bill | C33: 46108 | D33: S/2026/2469/A | E33: F-02360 DELFINO ROBERTO NICOLA | G33: 46108 | H33: 4/FE | I33: 1872 | L33: 1204086.5
B34: Journal | C34: 46112 | D34: JE-CIV-21053 | I34: 36 | L34: 1204122.5
B35: Journal | C35: 46112 | D35: JE-CIV-21052 | I35: 900 | L35: 1205022.5
B36: Bill | C36: 46120 | D36: S/2026/2743/A | E36: F-01928 STEFANO ROMANO | F36: Attività di consulenza tecnica-comune di Manduria TA | G36: 46120 | H36: 3/2026 | I36: 2100 | L36: 1207122.5
B37: Bill | C37: 46127 | D37: S/2026/3089/A | E37: F-04308 FRANCESCO MEZZOPRETE | G37: 46126 | H37: 20 | I37: 9450 | L37: 1216572.5
B38: Bill Credit | C38: 46128 | D38: S/2026/3117/A | E38: F-04308 FRANCESCO MEZZOPRETE | G38: 46127 | H38: 2 | L38: 1217519.5
B39: Bill | C39: 46128 | D39: S/2026/3151/A | E39: F-04308 FRANCESCO MEZZOPRETE | F39: Prestazione tecnica per riconfinazione area impianto di pubblica illuminazione del Comune di Scurcola Marsicana (AQ) / | G39: 46127 | H39: 29 | I39: 947 | K39: 9450 | L39: 1208069.5
B40: Bill | C40: 46132 | D40: S/2026/3215/A | E40: F-01930 RESTART GREEN SOLUTIONS SRL | F40: PREPARAZIONE DOCUMENTAZIONE GARA AFFIDAMENTO-COMUNE DI MILAZZO (ME) | G40: 46132 | H40: 10 /I | I40: 4095 | J40: Costi di progettazione | L40: 1212164.5
B41: Journal | C41: 46142 | D41: JE-CIV-22352 | I41: 100 | L41: 1212264.5
B42: Journal | C42: 46142 | D42: JE-CIV-22353 | I42: 2502 | L42: 1221728.5
B43: Journal | C43: 46142 | D43: JE-CIV-22447 | E43: F-01930 RESTART GREEN SOLUTIONS SRL | F43: PREPARAZIONE DOCUMENTAZIONE GARA AFFIDAMENTO-COMUNE DI MILAZZO (ME) | I43: 9464 | J43: Costi di progettazione | L43: 1224230.5
B44: Bill | C44: 46142 | D44: S/2026/3507/A | E44: F-02360 DELFINO ROBERTO NICOLA | F44: Rimborso spese mese di aprile | G44: 46141 | H44: 5/FE | I44: 1872 | L44: 1226102.5
B45: Bill | C45: 46148 | D45: S/2026/3673/A | E45: F-03613 BCM ENGINEERING S.R.L. | F45: PEF Canosa di Puglia, Miglionico, Buonabitacolo, Borgetto e Vairano Patenora | G45: 46146 | H45: 2 | I45: 2652 | J45: Costi di progettazione | L45: 1228754.5
B46: Bill | C46: 46154 | D46: S/2026/3836/A | E46: F-01928 STEFANO ROMANO | G46: 46154 | H46: 4/2026 | I46: 2240 | L46: 1230994.5
B47: Bill | C47: 46167 | D47: S/2026/4260/A | E47: F-04138 DI BUO' GIANLUCA | G47: 46166 | H47: 5 | I47: 3122 | L47: 1234116.5
B48: Bill | C48: 46171 | D48: S/2026/4369/A | E48: F-02360 DELFINO ROBERTO NICOLA | G48: 46171 | H48: 6/FE | I48: 1872 | L48: 1235988.5
B49: Journal | C49: 46173 | D49: JE-CIV-23869 | I49: 3089.18 | L49: 1239077.7
B50: Journal | C50: 46173 | D50: JE-CIV-23866 | E50: F-01911 RESTART ENERGY LAB S.R.L. | I50: 14050.85 | J50: Costi di progettazione | L50: 1253128.5
B51: Journal | C51: 46173 | D51: JE-CIV-23864 | E51: F-01930 RESTART GREEN SOLUTIONS SRL | I51: 13650.61 | J51: Costi di progettazione | L51: 1266779.1
B52: Journal | C52: 46173 | D52: JE-CIV-23872 | I52: 5387.2 | L52: 1272166.3
B53: Journal | C53: 46173 | D53: JE-CIV-23870 | I53: 479.59 | L53: 1272645.9
B54: Journal | C54: 46173 | D54: JE-CIV-23867 | I54: 4554.8 | L54: 1277200.7
B55: Journal | C55: 46173 | D55: JE-CIV-23874 | E55: F-01911 RESTART ENERGY LAB S.R.L. e F-01930 RESTART GREEN SOLUTIONS SRL | I55: 18281.6 | J55: Costi di progettazione | L55: 1295482.3
B56: Journal | C56: 46173 | D56: JE-CIV-24005 | I56: 467.17 | L56: 1295949.5
B57: Bill | C57: 46177 | D57: S/2026/4488/A | E57: F-01928 STEFANO ROMANO | G57: 46174 | H57: 5/2026 | I57: 1680 | L57: 1297629.5
B58: Bill Credit | C58: 46178 | D58: S/2026/4526/A | E58: F-01928 STEFANO ROMANO | G58: 46174 | H58: 6/2026 | J58: 1680 | K58: 1680 | L58: 1295949.5
B59: Bill | C59: 46181 | D59: S/2026/4570/A | E59: F-04529 ROCCO DONATO LORUSSO | F59: Operazione non soggetta a ritenuta alla fonte a titolo di acconto ai sensi dell articolo 1, comma 67, l. n. 190 del 2014 e successive modificazioni | G59: 46179 | H59: FPR 21/26 | I59: 999.6 | L59: 1296949.1
B60: Bill | C60: 46182 | D60: S/2026/4615/A | E60: F-01911 RESTART ENERGY LAB S.R.L. | F60: FATTURA | G60: 46173 | H60: 9 /I | I60: 26000 | J60: Costi di progettazione | L60: 1322949.1
B61: Bill | C61: 46182 | D61: S/2026/4614/A | E61: F-01911 RESTART ENERGY LAB S.R.L. | F61: FATTURA | G61: 46173 | H61: 8 /I | I61: 5265 | J61: Costi di progettazione | L61: 1328214.1
B62: Bill | C62: 46182 | D62: S/2026/4618/A | E62: F-01911 RESTART ENERGY LAB S.R.L. | F62: FATTURA | G62: 46173 | H62: 4 /I | I62: 2600 | J62: Costi di progettazione | L62: 1330814.1
B63: Bill | C63: 46182 | D63: S/2026/4609/A | E63: F-01911 RESTART ENERGY LAB S.R.L. | F63: FATTURA | G63: 46173 | H63: 3 /I | I63: 16640 | J63: Costi di progettazione | L63: 1347454.1
B64: Bill | C64: 46182 | D64: S/2026/4626/A | E64: F-04531 PAOLO SCOTTO | F64: C.S.E. Comune di Savona | G64: 46181 | H64: FPR 14/26 | I64: 25155 | L64: 1372609.1
B65: Bill Credit | C65: 46184 | D65: S/2026/4712/A | E65: F-01930 RESTART GREEN SOLUTIONS SRL | F65: NOTA CREDITO | G65: 46173 | H65: 18 /I | J65: 14029.6 | K65: 14029.6 | L65: 1358579.5
B66: Bill | C66: 46184 | D66: S/2026/4713/A | E66: F-01930 RESTART GREEN SOLUTIONS SRL | F66: FATTURA | G66: 46173 | H66: 19 /I | I66: 10337.6 | J66: Costi di progettazione | L66: 1368917.1
B67: Bill | C67: 46191 | D67: S/2026/5041/A | E67: F-00304 ACCETTA CRISTIAN | F67: Operazione non soggetta a ritenuta alla fonte a titolo di acconto ai sensi dell articolo 1, comma 67, l. n. 190 del 2014 e successive modificazioni | G67: 46191 | H67: FPR 23/26 | I67: 400 | L67: 1369317.1
B68: Bill | C68: 46196 | D68: S/2026/5106/A | E68: F-01930 RESTART GREEN SOLUTIONS SRL | F68: FATTURA | G68: 46196 | H68: 20 /I | I68: 4303.94 | J68: Costi di progettazione | L68: 1373621
B69: Bill | C69: 46202 | D69: S/2026/5228/A | E69: F-02360 DELFINO ROBERTO NICOLA | G69: 46202 | H69: 7/FE | I69: 1872 | L69: 1375493
B70: Bill | C70: 46202 | D70: S/2026/5204/A | E70: F-01930 RESTART GREEN SOLUTIONS SRL | F70: FATTURA | G70: 46199 | H70: 21 /I | I70: 3706.56 | J70: Costi di progettazione | L70: 1379199.6
B71: Journal | C71: 46203 | D71: JE-CIV-25637 | I71: 40 | L71: 1379239.6
B72: Journal | C72: 46203 | D72: JE-CIV-25476 | I72: 500 | L72: 1379489.6
B73: Journal | C73: 46203 | D73: JE-CIV-25482 | I73: 250 | L73: 1379749.6
B74: Journal | C74: 46203 | D74: JE-CIV-25475 | I74: 30 | L74: 1380009.6
B75: Journal | C75: 46203 | D75: JE-CIV-25484 | I75: 750 | L75: 1380759.6
B76: Journal | C76: 46203 | D76: JE-CIV-25479 | I76: 260 | L76: 1380789.6
B77: Journal | C77: 46203 | D77: JE-CIV-25478 | I77: 260 | L77: 1381039.6
B78: Journal | C78: 46203 | D78: JE-CIV-25487 | I78: 250 | L78: 1381539.6
B79: Bill | C79: 46212 | D79: S/2026/5488/A | E79: F-03611 RESET S.R.L. | G79: 46211 | H79: 25 | I79: 2808 | L79: 1384347.6
B80: Bill | C80: 46213 | D80: S/2026/5536/A | E80: F-01911 RESTART ENERGY LAB S.R.L. | F80: FATTURA | G80: 46203 | H80: 15 /I | I80: 6179.26 | J80: Costi di progettazione | L80: 1390526.9
B81: Bill | C81: 46213 | D81: S/2026/5531/A | E81: F-01911 RESTART ENERGY LAB S.R.L. | F81: FATTURA | G81: 46203 | H81: 12 /I | I81: 19650.18 | J81: Costi di progettazione | L81: 1410177
B82: Bill | C82: 46213 | D82: S/2026/5541/A | E82: F-01911 RESTART ENERGY LAB S.R.L. | F82: FATTURA | G82: 46203 | H82: 13 /I | I82: 20273.34 | J82: Costi di progettazione | L82: 1430450.4
B83: Bill | C83: 46216 | D83: S/2026/5692/A | E83: F-04412 DAMATO GIANLUCA | G83: 46212 | H83: 24 | I83: 2912 | L83: 1433362.4
B84: Bill | C84: 46230 | D84: S/2026/6049/A | E84: F-04624 ANTONIO FISCINA | G84: 46228 | H84: FPR 5/26 | I84: 8400 | L84: 1441762.4
B85: Bill | C85: 46230 | D85: S/2026/6046/A | E85: F-03833 A3S PROGETTI S.R.L. | F85: Comune di Alassio (SV) - Servizi di ingegneria e progettazione di impianti di illuminazione pubblica, semaforici e smart | G85: 46218 | H85: 69-FE_2026 | I85: 7589.77 | J85: Consulenza tecnica | L85: 1449352.2
B86: Bill | C86: 46233 | D86: S/2026/6125/A | E86: F-02360 DELFINO ROBERTO NICOLA | G86: 46233 | H86: 8/FE | I86: 1872 | L86: 1451224.2
B87: Bill | C87: 46234 | D87: S/2026/6146/A | E87: F-01928 STEFANO ROMANO | G87: 46234 | H87: 9/2026 | I87: 3680 | L87: 1454904.2
B88: Bill | C88: 46237 | D88: S/2026/6158/A | E88: F-04160 Studio Marinelli Progettazioni | F88: Operazione non soggetta a ritenuta alla fonte a titolo di acconto ai sensi dell articolo 1, comma 67, l. n. 190 del 2014 e successive modificazioni | G88: 46225 | H88: FPR 9/26 | I88: 262 | L88: 1455166.2
B89: Bill | C89: 46237 | D89: S/2026/6181/A | E89: F-04337 MI10STUDIO SRL | F89: PROGETTAZIONE PFTE ILLUMINAZIONE PUBBLICA GARA COMUNE CREMONA | G89: 46230 | H89: 00084/26 | I89: 95992 | L89: 1551158.2
B90: Bill | C90: 46254 | D90: S/2026/6390/A | E90: F-01911 RESTART ENERGY LAB S.R.L. | F90: FATTURA | G90: 46234 | H90: 21 /I | I90: 5200 | J90: Costi di progettazione | L90: 1556358.2
B91: Bill | C91: 46254 | D91: S/2026/6393/A | E91: F-01911 RESTART ENERGY LAB S.R.L. | F91: FATTURA | G91: 46234 | H91: 19 /I | I91: 14734.72 | J91: Costi di progettazione | L91: 1571092.9
B92: Bill | C92: 46254 | D92: S/2026/6392/A | E92: F-01911 RESTART ENERGY LAB S.R.L. | F92: FATTURA | G92: 46234 | H92: 23 /I | I92: 7280 | J92: Costi di progettazione | L92: 1578372.9
B93: Bill | C93: 46254 | D93: S/2026/6391/A | E93: F-01911 RESTART ENERGY LAB S.R.L. | F93: FATTURA | G93: 46234 | H93: 22 /I | I93: 16640 | J93: Costi di progettazione | L93: 1595012.9
B94: Bill | C94: 46258 | D94: S/2026/6520/A | E94: F-04138 DI BUO' GIANLUCA | G94: 46258 | H94: 9 | I94: 3120 | J94: Costi di progettazione | L94: 1598132.9
B95: Bill | C95: 46258 | D95: S/2026/6609/A | E95: F-04407 P.M. DI LAZZARO ANTONIO | G95: 46258 | H95: 15 | I95: 5720 | L95: 1603852.9
B96: Bill | C96: 46259 | D96: S/2026/6705/A | E96: F-01911 RESTART ENERGY LAB S.R.L. | F96: FATTURA | G96: 46234 | H96: 20 /I | I96: 7800 | L96: 1611652.9
B97: Bill Credit | C97: 46260 | D97: S/2026/6761/A | E97: F-01911 RESTART ENERGY LAB S.R.L. | F97: NOTA CREDITO | G97: 46260 | H97: 25 /I | K97: 7800 | L97: 1603852.9
B98: Bill Credit | C98: 46260 | D98: S/2026/6762/A | E98: F-01911 RESTART ENERGY LAB S.R.L. | F98: NOTA CREDITO | G98: 46260 | H98: 26 /I | K98: 5200 | L98: 1598652.9
B99: Bill | C99: 46265 | D99: S/2026/6829/A | E99: F-02360 DELFINO ROBERTO NICOLA | G99: 46265 | H99: 9/FE | I99: 1872 | L99: 1600524.9
A100: Total - 700405 - Comp. Prof. Attinenti Attivita' Senza Rit. | I100: =SUM(I10:I99) -> 578676.24 | K100: =SUM(K10:K99) -> 38159.6 | L100: =L99 -> 1600524.9
A101: Total - 7004 - Servizi Di Lavoro Parasub | I101: =SUM(I9,I100) -> 578676.24 | K101: =SUM(K9,K100) -> 38159.6 | L101: =L9+L100 -> 1600524.9
A102: Total - 70 - COSTI PER SERVIZI | I102: =SUM(I8,I101) -> 578676.24 | K102: =SUM(K8,K101) -> 38159.6 | L102: =L8+L101 -> 1600524.9

Sheet 700407
A1: CiviSmart
A2: Parent Company : CiviSmart S.p.A.
A3: CIV| Schede Contabili
A4: 1 January 2026 - 31 August 2026
A7: Account | B7: Type | C7: Date | D7: Document Number | E7: Name | F7: Memo | G7: [IL] Reference Date | H7: [IL] Reference # | I7: Debit | J7: NATURA DEL COSTO | K7: Credit | L7: Balance
A8: 70 - COSTI PER SERVIZI | L8: 0
A9: 7004 - Servizi Di Lavoro Parasub | L9: 0
A10: 700407 - Comp. Prof. Attinenti Attivita' C/Rit. | L10: 1443204.9
B11: Bill | C11: 46044 | D11: S/2026/0498/A | E11: F-01411 ATLANTE - CERASI Studio Notarile Associato | F11: Attività svolta dal Notaio Nicola Atlante di Roma: (*) visura camerale pre stipula; (*) verifica poteri; (*) revisione minuta; (*) stipula atto; (*) autentiche di firma; PROCURA SPECIALE (a Pietro SA NFILIPPO per conferimento poteri) rep. 73.161 racc. 37.910 in data 9 gennaio 2026; successivi adempimenti: (*) registrazione c/o l Agenzia delle Entrate di Roma 5; (*) rilascio di una copia autentica digitale per il Notaio Schiavone. | G11: 46041 | H11: 75 | I11: 560.32 | J11: 1.Spese di consulenza | L11: =L10+I11-K11 -> 1443765.2
B12: Bill | C12: 46052 | D12: S/2026/0682/A | E12: F-00348 TELESCA ROCCO DONATO | G12: 46050 | H12: FPR 1/26 | I12: 2080 | L12: =L11+I12-K12 -> 1445845.2
B13: Journal | C13: 46053 | D13: JE-CIV-19118 | F13: CONCESSIONE DEL SERVIZIO DI GESTIONE, MANUTENZIONE, EFFICIENTAMENTO ENEREGETICO E RIQUALIFICAZIONE DEGLI IMPIANTI DI PUBBLICA ILLUMINAZIONE- Vibonati | I13: 5200 | J13: 1.Spese di consulenza | L13: =L12+I13-K13 -> 1451045.2
B14: Journal | C14: 46053 | D14: JE-CIV-18132 | I14: 10550 | L14: =L13+I14-K14 -> 1461595.2
B15: Journal | C15: 46053 | D15: JE-CIV-19438 | I15: 8000 | L15: =L14+I15-K15 -> 1469595.2
B16: Bill | C16: 46058 | D16: S/2026/0800/A | E16: F-01411 ATLANTE - CERASI Studio Notarile Associato | F16: ATTIVITA SVOLTA DAL NOTAIO NICOLA ATLANTE DI ROMA: (*) visura camerale pre stipula; (*) verifica poteri; (*) predisposizione, redazione, revisione e correzione minute; (*) stipula atti; (*) autentich e di firma; 1) PROCURA (a Vito Telesca per conferimento poteri) rep. 73.259 racc. 37.946 in data 29 gennaio 2026; successivi adempimenti: (*) registrazione c/o l Agenzia delle Entrate di Roma 5; (* ) rilascio di una copia autentica cartacea per la società: 2) PROCURA SPECIALE in bollo (a Vito Telesca per acquistare area urbana in Comune di Campi Salentina) rep. 72.069 in data 29 gennaio 2026; ( *) rilascio originale alla società. | G16: 46057 | H16: 195 | I16: 979.17 | J16: 1.Spese di consulenza | L16: =L15+I16-K16 -> 1470574.4
B17: Bill | C17: 46070 | D17: S/2026/1235/A | E17: F-03093 QUI ASSICURAZIONI S.R.L. | G17: 46062 | H17: AF01 159/26 | I17: 419.29 | L17: =L16+I17-K17 -> 1470993.7
B18: Bill | C18: 46071 | D18: S/2026/1285/A | E18: F-04366 ING.RUSSO DOMENICO | G18: 46063 | H18: 01 | I18: 832 | L18: =L17+I18-K18 -> 1471825.7
B19: Bill | C19: 46076 | D19: S/2026/1407/A | E19: F-04363 LUIGI DI PAOLO | G19: 46063 | H19: 2/FE | I19: 9204 | L19: =L18+I19-K19 -> 1481029.7
B20: Bill | C20: 46078 | D20: S/2026/1478/A | E20: F-03890 GIULIO FAZIO | G20: 46057 | H20: FPR 3/26 | I20: 8320 | L20: =L19+I20-K20 -> 1489349.7
B21: Bill | C21: 46078 | D21: S/2026/1480/A | E21: F-03890 GIULIO FAZIO | G21: 46057 | H21: FPR 2/26 | I21: 320 | L21: =L20+I21-K21 -> 1489669.7
B22: Bill Credit | C22: 46079 | D22: S/2026/1560/A | E22: F-03890 GIULIO FAZIO | G22: 46066 | H22: FPR 4/26 | K22: 8320 | L22: =L21+I22-K22 -> 1481349.7
B23: Bill | C23: 46079 | D23: S/2026/1550/A | E23: F-00348 TELESCA ROCCO DONATO | G23: 46078 | H23: FPR 5/26 | I23: 2080 | L23: =L22+I23-K23 -> 1483429.7
B24: Bill | C24: 46097 | D24: S/2026/2093/A | E24: F-03093 QUI ASSICURAZIONI S.R.L. | F24: %fornito | G24: 46097 | H24: AF01 383/26 | I24: 419.29 | L24: =L23+I24-K24 -> 1483848.9
B25: Bill | C25: 46097 | D25: S/2026/2089/A | E25: F-03890 GIULIO FAZIO | G25: 46085 | H25: FPR 5/26 | I25: 8320 | L25: =L24+I25-K25 -> 1492168.9
B26: Bill | C26: 46111 | D26: S/2026/2529/A | E26: F-00348 TELESCA ROCCO DONATO | G26: 46111 | H26: FPR 13/26 | I26: 2704 | L26: =L25+I26-K26 -> 1494872.9
B27: Bill | C27: 46114 | D27: S/2026/2613/A | E27: F-03093 QUI ASSICURAZIONI S.R.L. | G27: 46099 | H27: AF01 436/26 | I27: 104.82 | L27: =L26+I27-K27 -> 1494977.8
B28: Bill | C28: 46119 | D28: S/2026/2692/A | E28: F-03690 STEFANO CALIGARA | F28: Redazione del Progetto di Fattibilità Tecnico-Economica (PFTE)da presentare presso lAmministrazione Comunale di Gallarate (VA). VS incarico del 04.03.2026. Acconto. | G28: 46119 | H28: 29/E | I28: 17640 | J28: Costi di Progettazione | L28: =L27+I28-K28 -> 1512617.8
B29: Bill | C29: 46120 | D29: S/2026/2726/A | E29: F-01526 CARMINE VERLOTTA | F29: Indagine Geologica - Comune di Ruoti | G29: 46119 | H29: 3 | I29: 1500 | J29: 1.Spese di consulenza | L29: =L28+I29-K29 -> 1514117.8
B30: Bill | C30: 46122 | D30: S/2026/2797/A | E30: F-03890 GIULIO FAZIO | F30: consulenza contratto 2024 - servizi resi a marzo 2026 | G30: 46120 | H30: FPR 6/26 | I30: 8320 | J30: 1.Spese di consulenza | L30: =L29+I30-K30 -> 1522437.8
B31: Bill | C31: 46126 | D31: S/2026/3023/A | E31: F-01185 Antonio Venneri | F31: PROGETTAZIONE ESECUTIVA, COORDINAMENTO DELLA SICUREZZA IN FASE DI PROGETTAZIONE, DIREZIONE LAVORI E COORDINAMENTO DELLA SICUREZZA IN FASE DI ESECUZIONE- E.L.EN.A. CONTRATTO LOTTO 3 | G31: 46125 | H31: FPR 9/26 | I31: 125721.61 | J31: 1.Spese di consulenza | L31: =L30+I31-K31 -> 1648159.4
B32: Bill | C32: 46126 | D32: S/2026/3022/A | E32: F-01185 Antonio Venneri | F32: E.L.EN.A. CONTRATTO LOTTO 4 | G32: 46125 | H32: FPR 10/26 | I32: 71259.91 | J32: 1.Spese di consulenza | L32: =L31+I32-K32 -> 1719419.3
B33: Bill | C33: 46126 | D33: S/2026/3020/A | E33: F-01185 Antonio Venneri | F33: E.L.EN.A. CONTRATTO LOTTO 1 | G33: 46125 | H33: FPR 7/26 | I33: 190626.82 | J33: 1.Spese di consulenza | L33: =L32+I33-K33 -> 1910046.1
B34: Bill | C34: 46126 | D34: S/2026/3016/A | E34: F-01185 Antonio Venneri | F34: E.L.EN.A. CONTRATTO LOTTO 2 | G34: 46125 | H34: FPR 8/26 | I34: 164881.81 | J34: 1.Spese di consulenza | L34: =L33+I34-K34 -> 2074927.9
B35: Bill | C35: 46139 | D35: S/2026/3419/A | E35: F-00348 TELESCA ROCCO DONATO | G35: 46136 | H35: FPR 15/26 | I35: 2589.6 | L35: =L34+I35-K35 -> 2077517.5
B36: Bill | C36: 46140 | D36: S/2026/3460/A | E36: F-01623 Donato Miano | G36: 46137 | H36: FPR 30/26 | I36: 2080 | L36: =L35+I36-K36 -> 2079597.5
B37: Bill | C37: 46141 | D37: S/2026/3469/A | E37: F-04443 GMS ST.ASSOCIATO GUANELLA MONTANI SUSS | G37: 46119 | H37: 53/E | I37: 30680 | L37: =L36+I37-K37 -> 2110277.5
B38: Journal | C38: 46142 | D38: JE-CIV-22352 | I38: 5766.28 | L38: =L37+I38-K38 -> 2116043.8
B39: Bill | C39: 46154 | D39: S/2026/3862/A | E39: F-03890 GIULIO FAZIO | G39: 46154 | H39: FPR 9/26 | I39: 8606.83 | L39: =L38+I39-K39 -> 2124650.6
B40: Bill | C40: 46161 | D40: S/2026/4139/A | E40: F-02352 DE CHECCHI ANDREA | F40: Collaudo illuminazione pubblica Lanuvio | G40: 46160 | H40: FPR 2/26 | I40: 12480 | J40: 1.Spese di consulenza | L40: =L39+I40-K40 -> 2137130.6
B41: Bill | C41: 46167 | D41: S/2026/4275/A | E41: F-03093 QUI ASSICURAZIONI S.R.L. | F41: %fornito | G41: 46167 | H41: AF01 1078/26 | I41: 209.64 | L41: =L40+I41-K41 -> 2137340.3
B42: Bill | C42: 46167 | D42: S/2026/4274/A | E42: F-03093 QUI ASSICURAZIONI S.R.L. | F42: %fornito | G42: 46167 | H42: AF01 1076/26 | I42: 434.05 | L42: =L41+I42-K42 -> 2137774.3
B43: Bill | C43: 46168 | D43: S/2026/4292/A | E43: F-04443 GMS ST.ASSOCIATO GUANELLA MONTANI SUSS | F43: Progetto tecnico di gara - Parco Archeologico Pompei | G43: 46167 | H43: 64/E | I43: 18720 | J43: Costi di Progettazione | L43: =L42+I43-K43 -> 2156494.3
B44: Bill | C44: 46168 | D44: S/2026/4287/A | E44: F-03093 QUI ASSICURAZIONI S.R.L. | F44: %fornito | G44: 46167 | H44: AF01 1095/26 | I44: 419.29 | L44: =L43+I44-K44 -> 2156913.6
B45: Journal | C45: 46173 | D45: JE-CIV-23864 | I45: 7580 | L45: =L44+I45-K45 -> 2164493.6
B46: Journal | C46: 46173 | D46: JE-CIV-23874 | I46: 220 | L46: =L45+I46-K46 -> 2164713.6
B47: Bill | C47: 46184 | D47: S/2026/4698/A | E47: F-01185 Antonio Venneri | G47: 46184 | H47: FPR 21/26 | I47: 8320 | J47: 1.Spese di consulenza | L47: =L46+I47-K47 -> 2173033.6
B48: Bill | C48: 46184 | D48: S/2026/4699/A | E48: F-01185 Antonio Venneri | G48: 46184 | H48: FPR 20/26 | I48: 3120 | J48: 1.Spese di consulenza | L48: =L47+I48-K48 -> 2176153.6
B49: Bill | C49: 46184 | D49: S/2026/4707/A | E49: F-03890 GIULIO FAZIO | G49: 46184 | H49: FPR 10/26 | I49: 8320 | L49: =L48+I49-K49 -> 2184473.6
B50: Bill | C50: 46184 | D50: S/2026/4700/A | E50: F-01185 Antonio Venneri | G50: 46184 | H50: FPR 19/26 | I50: 13208 | J50: 1.Spese di consulenza | L50: =L49+I50-K50 -> 2197681.6
B51: Bill | C51: 46184 | D51: S/2026/4695/A | E51: F-04532 ROBERTO MONDINI | F51: AFFIDAMENTO SERVIZI TECNICI DI DIREZIONE LAVORI E COORDINAMENTO DELLA SICUREZZA IN FASE DI ESECUZIONE PER L INTERVENTO DI RIQUALIFICAZIONE DELL IMPIANTO D ILLUMINAZIONE PUBBLICA - DIREZIONE LAVORI | G51: 46176 | H51: 11/001 | I51: 9360 | L51: =L50+I51-K51 -> 2207041.6
B52: Bill | C52: 46190 | D52: S/2026/5002/A | E52: F-01783 CARMINE DI GIACOMO | G52: 46189 | H52: FPR 7/26 | I52: 13520 | L52: =L51+I52-K52 -> 2220561.6
B53: Bill | C53: 46190 | D53: S/2026/5017/A | E53: F-04545 LUCA SPORTELLI | G53: 46142 | H53: 7 | I53: 41533.44 | L53: =L52+I53-K53 -> 2262095.1
B54: Bill Credit | C54: 46191 | D54: S/2026/5032/A | E54: F-04545 LUCA SPORTELLI | G54: 46190 | H54: 9 | K54: 41533.44 | L54: =L53+I54-K54 -> 2220561.6
B55: Bill | C55: 46191 | D55: S/2026/5039/A | E55: F-04546 ROBERTO ADOSIO | G55: 46182 | H55: 25 | I55: 32648.44 | L55: =L54+I55-K55 -> 2253210.1
B56: Bill | C56: 46195 | D56: S/2026/5082/A | E56: F-03093 QUI ASSICURAZIONI S.R.L. | F56: %fornito | G56: 46191 | H56: AF01 1367/26 | I56: 128.33 | L56: =L55+I56-K56 -> 2253338.4
B57: Bill | C57: 46197 | D57: S/2026/5132/A | E57: F-01939 Bonelli Erede Lombardi Pappalardo - Studio Legale | F57: In relazione all attività di Organismo di Vigilanza per il I° trimestre 2026. | G57: 46196 | H57: 2536/2026/01EL | I57: 2246.4 | J57: 1.Spese di consulenza | L57: =L56+I57-K57 -> 2255584.8
B58: Bill | C58: 46198 | D58: S/2026/5168/A | E58: F-04561 CARUSO E ANDREATINI - NOTAI ASSOCIATI | F58: CESSIONE DI PARTECIPAZIONE NELLA SOCIETA DIAMOND SMART CITY S.R.L. IN AUTENTICA | G58: 46196 | H58: 1898/2026 | I58: 4676.62 | J58: 1.Spese di consulenza | L58: =L57+I58-K58 -> 2260261.4
B59: Bill | C59: 46198 | D59: S/2026/5169/A | E59: F-04561 CARUSO E ANDREATINI - NOTAI ASSOCIATI | F59: CESSIONI DI PARTECIPAZIONI NELLA SOCIETA RSEE ROMAGNANO SESIA EFFICIENZA ENERGETICA S.R.L. IN AUTENTICA | G59: 46196 | H59: 1897/2026 | I59: 3752.22 | J59: 1.Spese di consulenza | L59: =L58+I59-K59 -> 2264013.6
B60: Journal | C60: 46203 | D60: JE-CIV-25484 | I60: 5500 | L60: =L59+I60-K60 -> 2269513.6
B61: Bill | C61: 46209 | D61: S/2026/5369/A | E61: F-04571 EMANUELE GIANNINI | F61: Progetto nuova sede Civismart Spa in Ascoli Piceno | G61: 46205 | H61: FPR 17/26 | I61: 2496 | J61: 1.Spese di consulenza | L61: =L60+I61-K61 -> 2272009.6
B62: Bill | C62: 46211 | D62: S/2026/5455/A | E62: F-04443 GMS ST.ASSOCIATO GUANELLA MONTANI SUSS | F62: OFFERTA AFFIDAMENTO IN CONCESSIONE DEGLI IMPIANTI DI PUBBLICA ILLUMINAZIONE E SEMAFORICI AI FINI DELLA REALIZZAZIONE DI INTERVENTI DI RIQUALIFICAZIONE ENERGETICA, ADEGUAMENTO NORMATIVO NONCHÈ DI GESTIONE DEGLI STESSI PER IL COMUNE DI RIVOLI | G62: 46203 | H62: 93/E | I62: 30680 | J62: Costi di Progettazione | L62: =L61+I62-K62 -> 2302689.6
B63: Bill | C63: 46211 | D63: S/2026/5449/A | E63: F-03890 GIULIO FAZIO | G63: 46210 | H63: FPR 11/26 | I63: 8320 | L63: =L62+I63-K63 -> 2311009.6
B64: Bill | C64: 46211 | D64: S/2026/5451/A | E64: F-00348 TELESCA ROCCO DONATO | G64: 46210 | H64: FPR 26/26 | I64: 2080 | L64: =L63+I64-K64 -> 2313089.6
B65: Bill | C65: 46212 | D65: S/2026/5485/A | E65: F-01185 Antonio Venneri | G65: 46211 | H65: FPR 30/26 | I65: 7800 | J65: 1.Spese di consulenza | L65: =L64+I65-K65 -> 2320889.6
B66: Bill | C66: 46212 | D66: S/2026/5487/A | E66: F-01185 Antonio Venneri | G66: 46211 | H66: FPR 31/26 | I66: 4108 | J66: 1.Spese di consulenza | L66: =L65+I66-K66 -> 2324997.6
B67: Bill | C67: 46212 | D67: S/2026/5486/A | E67: F-01185 Antonio Venneri | G67: 46211 | H67: FPR 29/26 | I67: 15080 | J67: 1.Spese di consulenza | L67: =L66+I67-K67 -> 2340077.6
B68: Journal | C68: 46223 | D68: JE-CIV-26293 | I68: 2500 | L68: =L67+I68-K68 -> 2342577.6
B69: Bill | C69: 46223 | D69: S/2026/5939/A | E69: F-04531 PAOLO SCOTTO | G69: 46223 | H69: FPR 21/26 | I69: 25155 | L69: =L68+I69-K69 -> 2367732.6
B70: Bill | C70: 46224 | D70: S/2026/5964/A | E70: F-04546 ROBERTO ADOSIO | G70: 46224 | H70: 30 | I70: 32648.44 | L70: =L69+I70-K70 -> 2400381.1
B71: Bill | C71: 46230 | D71: S/2026/6027/A | E71: F-03093 QUI ASSICURAZIONI S.R.L. | F71: fattura già pagata | G71: 46227 | H71: AF01 1676/26 | I71: 419.29 | L71: =L70+I71-K71 -> 2400800.4
B72: Bill | C72: 46237 | D72: S/2026/6174/A | E72: F-01243 DEGLI ATTI PASQUALE | F72: Progetto G.R.O.W.S. - ELENA - Lotto 2 - San Cesario di Lecce | G72: 46233 | H72: FPR 6/26 | I72: 14040 | J72: 1.Spese di consulenza | L72: =L71+I72-K72 -> 2414840.4
B73: Bill | C73: 46237 | D73: S/2026/6170/A | E73: F-01243 DEGLI ATTI PASQUALE | F73: Progetto G.R.O.W.S. - ELENA - Lotto 3 - Ugento | G73: 46232 | H73: FPR 4/26 | I73: 6760 | J73: 1.Spese di consulenza | L73: =L72+I73-K73 -> 2421600.4
B74: Bill | C74: 46237 | D74: S/2026/6173/A | E74: F-01243 DEGLI ATTI PASQUALE | F74: Progetto G.R.O.W.S. - ELENA - Lotto 2 - Gallipoli | G74: 46233 | H74: FPR 5/26 | I74: 14560 | J74: 1.Spese di consulenza | L74: =L73+I74-K74 -> 2436160.4
B75: Bill | C75: 46237 | D75: S/2026/6182/A | E75: F-00348 TELESCA ROCCO DONATO | G75: 46237 | H75: FPR 32/26 | I75: 2080 | L75: =L74+I75-K75 -> 2438240.4
B76: Bill | C76: 46237 | D76: S/2026/6167/A | E76: F-01243 DEGLI ATTI PASQUALE | F76: Progetto G.R.O.W.S. - ELENA - Lotto 3 - Campi Salentina | G76: 46232 | H76: FPR 3/26 | I76: 7800 | J76: 1.Spese di consulenza | L76: =L75+I76-K76 -> 2446040.4
B77: Bill | C77: 46240 | D77: S/2026/6353/A | E77: F-03690 STEFANO CALIGARA | G77: 46238 | H77: 68/E | I77: 6300 | J77: Costi di Progettazione | L77: =L76+I77-K77 -> 2452340.4
B78: Bill | C78: 46241 | D78: S/2026/6367/A | E78: F-03890 GIULIO FAZIO | G78: 46240 | H78: FPR 13/26 | I78: 8320 | L78: =L77+I78-K78 -> 2460660.4
B79: Bill | C79: 46258 | D79: S/2026/6613/A | E79: F-01816 Domenico Benincasa | F79: Attivit professionali relative al deposito di pensilini prefabbricate per autorizzazione sismica -Impianto fotovoltaico FV1_SANT ARCANGELO | G79: 46234 | H79: 1/137 | I79: 520 | J79: 1.Spese di consulenza | L79: =L78+I79-K79 -> 2461180.4
A80: Total - 700407 - Comp. Prof. Attinenti Attivita' C/Rit. | I80: =SUM(I10:I79) -> 1067828.9 | K80: =SUM(K10:K79) -> 49853.44 | L80: =L79 -> 2461180.4
A81: Total - 7004 - Servizi Di Lavoro Parasub | I81: =SUM(I9,I80) -> 1067828.9 | K81: =SUM(K9,K80) -> 49853.44 | L81: =L9+L80 -> 2461180.4
A82: Total - 70 - COSTI PER SERVIZI | I82: =SUM(I8,I81) -> 1067828.9 | K82: =SUM(K8,K81) -> 49853.44 | L82: =L8+L81 -> 2461180.4

Sheet 700409
A1: CiviSmart
A2: Parent Company : CiviSmart S.p.A.
A3: CIV| Schede Contabili
A4: 1 January 2026 - 31 August 2026
A7: Account | B7: Type | C7: Date | D7: Document Number | E7: Name | F7: Memo | G7: [IL] Reference Date | H7: [IL] Reference # | I7: Debit | J7: DESCRIZIONE | K7: NATURA DEL COSTO | L7: Credit | M7: Balance
A8: 70 - COSTI PER SERVIZI | M8: 0
A9: 7004 - Servizi Di Lavoro Parasub | M9: 0
A10: 700409 - Comp. Prof. Attinenti Attivita' | M10: 1091707.9
B11: Bill | C11: 46043 | D11: S/2026/0443/A | E11: F-00335 OMNIA FIDUCIARIA S.R.L. | F11: Si emette fattura per asseverazioni Piano Economico e Finanziario svolte per vs conto relative alle proposte di project finance presentate in partenariato con A2A ILLUMINAZIONE PUBBLICA SRL | G11: 46031 | H11: 25 | I11: 2800 | M11: 1094507.9
B12: Bill | C12: 46050 | D12: S/2026/0661/A | E12: F-00183 IMQ S.P.A. | F12: Oggetto: MANTENIMENTO 1° TRIMESTRE 2026 - CERTIFICATO 9191.STTR - NORMA ISO 14001 | G12: 46043 | H12: 226003611 | I12: 279.96 | M12: 1094787.8
B13: Bill | C13: 46050 | D13: S/2026/0662/A | E13: F-00183 IMQ S.P.A. | F13: Oggetto: MANTENIMENTO 1° TRIMESTRE 2026 - CERTIFICATO 9196.SLT1 - NORMA ISO 50001 | G13: 46043 | H13: 226003612 | I13: 286.98 | M13: 1095074.8
B14: Journal | C14: 46053 | D14: JE-CIV-18185 | E14: F-03748 CONSORZIO KREA SRL | F14: Avvallimento E.L.E.NA | I14: 37500 | M14: 1132574.8
B15: Journal | C15: 46053 | D15: JE-CIV-19070 | E15: F-04249 ATLANTICO S.p.A | I15: 10000 | M15: 1142574.8
B16: Journal | C16: 46053 | D16: JE-CIV-18184 | E16: F-03748 CONSORZIO KREA SRL | F16: Avvallimento E.L.E.NA | I16: 112500 | K16: 8.Altro | M16: 1255074.8
B17: Bill | C17: 46063 | D17: S/2026/0876/A | E17: F-00527 ARGENTA S.O.A. SPA | G17: 46059 | H17: 0000102 | I17: 1389.49 | M17: 1256464.3
B18: Bill | C18: 46078 | D18: S/2026/1533/A | E18: F-01831 TOTUM SRL | G18: 46078 | H18: FPR 3/26 | I18: 3500 | M18: 1259964.3
B19: Journal | C19: 46081 | D19: JE-CIV-19123 | E19: F-04249 ATLANTICO S.p.A | I19: 10200 | M19: 1270164.3
B20: Bill | C20: 46085 | D20: S/2026/1704/A | E20: F-00335 OMNIA FIDUCIARIA S.R.L. | F20: Si emette fattura per asseverazioni Piano Economico e Finanziario svolte per vs conto relative ai seguenti comuni: | G20: 46083 | H20: 5 | I20: 5600 | M20: 1275764.3
B21: Bill | C21: 46099 | D21: S/2026/2206/A | E21: F-00407 LABORATORIO ANALISI DI A. COVIELLO & C. S.A.S. | G21: 46091 | H21: 2026/10 | I21: 80 | M21: 1275844.3
B22: Bill | C22: 46099 | D22: S/2026/2226/A | E22: F-00247 QUALILAB S.R.L. | F22: RILIEVO FOTOMETRICO - 673-QL25 | G22: 46081 | H22: 183/2026 | I22: 9920 | K22: Verifiche qualità su lampade | M22: 1285764.3
B23: Bill | C23: 46100 | D23: S/2026/2305/A | E23: F-02168 ARCADIA 888 SRL | G23: 46091 | H23: 50 | I23: 1575 | M23: 1287339.3
B24: Bill | C24: 46106 | D24: S/2026/2409/A | E24: F-00183 IMQ S.P.A. | F24: Oggetto: VARIAZIONE CERTIFICATI PER LA NORMA ISO 14001 (CERTIFICATO 9191.STTR) | G24: 46104 | H24: 826007183 | I24: 50 | M24: 1287389.3
B25: Bill | C25: 46107 | D25: S/2026/2443/A | E25: F-01605 CREDITSAFE ITALIA SRL | G25: 46104 | H25: SID000236468 | I25: 800 | M25: 1288189.3
B26: Bill | C26: 46122 | D26: S/2026/2784/A | E26: F-00335 OMNIA FIDUCIARIA S.R.L. | F26: Si emette fattura per asseverazioni Piano Economico e Finanziario svolte per vs conto in partenariato con A2A ILLUMINAZIONE PUBBLICA SRL | G26: 46120 | H26: 11 | I26: 2100 | M26: 1290289.3
B27: Bill | C27: 46122 | D27: S/2026/2785/A | E27: F-00335 OMNIA FIDUCIARIA S.R.L. | F27: Si emette fattura per asseverazioni Piano Economico e Finanziario svolte per vs conto relative ai seguenti comuni: | G27: 46120 | H27: 12 | I27: 3900 | M27: 1294189.3
B28: Bill | C28: 46128 | D28: S/2026/3124/A | E28: F-00183 IMQ S.P.A. | F28: Oggetto: MANTENIMENTO 2° TRIMESTRE 2026 - CERTIFICATO 9196.SLT1 - NORMA ISO 50001 | G28: 46127 | H28: 226010856 | I28: 286.98 | M28: 1294476.3
B29: Bill | C29: 46128 | D29: S/2026/3123/A | E29: F-00183 IMQ S.P.A. | F29: Oggetto: MANTENIMENTO 2° TRIMESTRE 2026 - CERTIFICATO 9191.STTR - NORMA ISO 14001 | G29: 46127 | H29: 226010857 | I29: 279.96 | M29: 1294756.2
B30: Bill | C30: 46129 | D30: S/2026/3169/A | E30: F-04249 ATLANTICO S.p.A | F30: Servizi per indennizzo garanzie assicurative mese di marzo 2026 | G30: 46128 | H30: 000017 | I30: 10000 | M30: 1304756.2
B31: Bill | C31: 46134 | D31: S/2026/3270/A | E31: F-00183 IMQ S.P.A. | F31: Oggetto: RIESAME PRATICA PER RICERTIFICAZIONE PER LA NORMA ISO 14001 (CERTIFICATO 9191.STTR) | G31: 46132 | H31: 826009588 | I31: 200 | M31: 1304956.2
B32: Bill | C32: 46139 | D32: S/2026/3397/A | E32: F-01831 TOTUM SRL | F32: fattura per assistenza Vs sistemi aziendali (ISO 9001 - ISO 14001 - ISO 45001 - ISO 50001 - UNI CEI 11352 - PdR 125 e SA8000) | G32: 46136 | H32: FPR 5/26 | I32: 3500 | M32: 1308456.2
B33: Bill | C33: 46139 | D33: S/2026/3393/A | E33: F-02168 ARCADIA 888 SRL | F33: Asseverazione Piano Economico - Proposta PPP Riqualificazione energetica Comune di Saronno | G33: 46133 | H33: 75 | I33: 3150 | M33: 1311606.2
B34: Bill | C34: 46140 | D34: S/2026/3429/A | E34: F-01605 CREDITSAFE ITALIA SRL | F34: VISURA CAMERALE-DATABASE INTERNAZIONALE HOME-STANDARD PACK -Report Investigato Post-Affidamento-VISURA CAMERALE STORICA | G34: 46135 | H34: SID000242411 | I34: 800 | M34: 1312406.2
B35: Journal | C35: 46142 | D35: JE-CIV-22467 | E35: F-04476 VLN ENGINEERING SRL-F-04249 ATLANTICO S.p.A | F35: consulenza strategica gara SACILE-Servizi per indennizzo garanzie assicurative mese di aprile 2026 .- contratto IE59-26 preparazione busta tecnica gara SACILE (PN) | I35: 31250 | K35: 1.Spese di consulenza | M35: 1343656.2
B36: Bill | C36: 46155 | D36: S/2026/3913/A | E36: F-00335 OMNIA FIDUCIARIA S.R.L. | F36: Si emette fattura per asseverazioni Piano Economico e Finanziario svolte per vs conto relative ai seguenti comuni: | G36: 46154 | H36: 18 | I36: 2600 | M36: 1346256.2
B37: Bill | C37: 46157 | D37: S/2026/4070/A | E37: F-00183 IMQ S.P.A. | F37: Oggetto: RIESAME PRATICA PER RICERTIFICAZIONE PER LA NORMA ISO 45001 (CERTIFICATO 9192.STT3) | G37: 46155 | H37: 826011801 | I37: 200 | M37: 1346456.2
B38: Bill | C38: 46169 | D38: S/2026/4320/A | E38: F-01605 CREDITSAFE ITALIA SRL | G38: 46167 | H38: SID000247970 | I38: 800 | M38: 1347256.2
B39: Journal | C39: 46173 | D39: JE-CIV-23874 | I39: 5000 | M39: 1352256.2
B40: Bill | C40: 46176 | D40: S/2026/4440/A | E40: F-01831 TOTUM SRL | G40: 46174 | H40: FPR 7/26 | I40: 3500 | M40: 1355756.2
B41: Bill | C41: 46181 | D41: S/2026/4586/A | E41: F-00335 OMNIA FIDUCIARIA S.R.L. | F41: Si emette fattura per asseverazioni Piano Economico e Finanziario svolte per vs conto in partenariato con A2A ILLUMINAZIONE PUBBLICA SRL | G41: 46181 | H41: 22 | I41: 800 | M41: 1356556.2
B42: Bill | C42: 46181 | D42: S/2026/4589/A | E42: F-00335 OMNIA FIDUCIARIA S.R.L. | F42: Si emette fattura per asseverazioni Piano Economico e Finanziario svolte per vs conto relative ai seguenti comuni: | G42: 46181 | H42: 21 | I42: 2900 | M42: 1359456.2
B43: Bill | C43: 46181 | D43: S/2026/4552/A | E43: F-02168 ARCADIA 888 SRL | G43: 46176 | H43: 116 | I43: 3150 | M43: 1362606.2
B44: Bill | C44: 46183 | D44: S/2026/4660/A | E44: F-00843 STUDIO ERGANI SRL | F44: Visite mediche personale | G44: 46182 | H44: 213 | I44: 2838 | M44: 1365444.2
B45: Bill | C45: 46188 | D45: S/2026/4886/A | E45: F-02168 ARCADIA 888 SRL | G45: 46185 | H45: 127 | I45: 3150 | M45: 1368594.2
B46: Bill | C46: 46189 | D46: S/2026/4928/A | E46: F-04538 BUREAU VERITAS ITALIA Spa | F46: CTR 14915847 Bilanci Materici Verifica Iniziale Documentale del 22/05/2026 Verifica disciplinare, Verifica progetto pilota e Report del 03-04/06/2026 Nostro riferimento: BU 0079667 | G46: 46184 | H46: 26024590 | I46: 5450 | M46: 1374044.2
B47: Bill | C47: 46190 | D47: S/2026/5004/A | E47: F-04543 ANDREA BERRI | G47: 46188 | H47: 8/A | I47: 1252 | M47: 1375296.2
B48: Bill | C48: 46197 | D48: S/2026/5121/A | E48: F-01831 TOTUM SRL | G48: 46197 | H48: FPR 9/26 | I48: 3500 | M48: 1378796.2
B49: Bill | C49: 46202 | D49: S/2026/5209/A | E49: F-04476 VLN ENGINEERING SRL | F49: Preparazione busta tecnica gara di Sacile | G49: 46198 | H49: 22/2026 | I49: 11250 | K49: 1.Spese di consulenza | M49: 1390046.2
B50: Bill | C50: 46202 | D50: S/2026/5202/A | E50: F-04558 ALBATROS SRL | G50: 46198 | H50: FPR 17/26 | I50: 200 | M50: 1390246.2
B51: Bill | C51: 46202 | D51: S/2026/5208/A | E51: F-01605 CREDITSAFE ITALIA SRL | G51: 46196 | H51: SID000253486 | I51: 800 | M51: 1391046.2
B52: Journal | C52: 46203 | D52: JE-CIV-25475 | I52: 8000 | M52: 1399046.2
B53: Bill | C53: 46203 | D53: S/2026/5248/A | E53: F-04553 GEMO SERVICE SRL | F53: Compenso forfettario onnicomprensivo | G53: 46195 | H53: 18 | I53: 4000 | M53: 1403046.2
B54: Bill | C54: 46203 | D54: S/2026/5241/A | E54: F-04542 AEQUILIBRIA SRL | F54: Certificazione Matrec | G54: 46188 | H54: 181/2026 | I54: 5800 | M54: 1408846.2
B55: Bill | C55: 46203 | D55: S/2026/5242/A | E55: F-04542 AEQUILIBRIA SRL | G55: 46195 | H55: 220/2026 | I55: 600 | M55: 1409446.2
B56: Bill | C56: 46203 | D56: S/2026/5255/A | E56: F-02941 MY_E_SERVICES SRLS | F56: CENSIMENTO IMPIANTI DI IP COMUNE DI NICHELINO | G56: 46202 | H56: 19 | I56: 9828 | M56: 1419274.2
B57: Bill | C57: 46203 | D57: S/2026/5244/A | E57: F-04476 VLN ENGINEERING SRL | F57: Predisposizione PFTE Gussago | G57: 46192 | H57: 21/2026 | I57: 20000 | K57: 1.Spese di consulenza | M57: 1439274.2
B58: Journal | C58: 46203 | D58: JE-CIV-25637 | I58: 1980 | M58: 1441254.2
B59: Bill | C59: 46206 | D59: S/2026/5324/A | E59: F-01926 CREDIT AGRICOLE LEASING ITALIA S.R.L. | F59: Cd cliente 02551021 Nr contratto 01612023/001 | G59: 46205 | H59: V1 /2026/26012974 | I59: 335 | M59: 1441589.2
B60: Bill | C60: 46209 | D60: S/2026/5378/A | E60: F-04549 ASTRA SRL | G60: 46206 | H60: 127 | I60: 600 | M60: 1442189.2
B61: Bill | C61: 46209 | D61: S/2026/5358/A | E61: F-04578 CARPOINT S.p.A. | F61: Veicolo - Targa: GH615SJ , Telaio: WV1ZZZSYZM9058782 , KM: 1 , Descr Veicolo: VIC - E-Crafter 35 FURG 100 kW | G61: 46206 | H61: 308 / 1241 | I61: 1485 | M61: 1443674.2
B62: Bill | C62: 46212 | D62: S/2026/5504/A | E62: F-00183 IMQ S.P.A. | F62: Oggetto: MANTENIMENTO 3° TRIMESTRE 2026 - CERTIFICATO 9196.SLT1 - NORMA ISO 50001 | G62: 46211 | H62: 226016077 | I62: 286.98 | M62: 1443961.2
B63: Bill | C63: 46213 | D63: S/2026/5520/A | E63: F-00183 IMQ S.P.A. | F63: Oggetto: MANTENIMENTO 3° TRIMESTRE 2026 - CERTIFICATO 9191.STTR - NORMA ISO 14001 | G63: 46211 | H63: 226016078 | I63: 279.96 | M63: 1444241.2
B64: Bill | C64: 46217 | D64: S/2026/5780/A | E64: F-04553 GEMO SERVICE SRL | G64: 46213 | H64: 19 | I64: 4000 | M64: 1448241.2
B65: Bill | C65: 46223 | D65: S/2026/5918/A | E65: F-00287 RINA SERVICES S.P.A. | F65: DARE PER LE SEGUENTI PRESTAZIONI: Periodica UNI EN ISO 9001 - SISTEMA DI GESTIONE PER LA QUALITA Cliente: 1091524 Contratto: 2025 CITTA 129 Rif. Amministrazione: AOC@rina.org | G65: 46219 | H65: 26T9-001174 | I65: 1650 | M65: 1449891.2
B66: Bill | C66: 46230 | D66: S/2026/6041/A | E66: F-04621 SGS ICS Italia S.r.l. | G66: 46227 | H66: 26710622 | I66: 4434 | M66: 1454325.2
B67: Bill | C67: 46231 | D67: S/2026/6060/A | E67: F-01605 CREDITSAFE ITALIA SRL | G67: 46226 | H67: SID000258776 | I67: 800 | M67: 1455125.2
B68: Bill | C68: 46231 | D68: S/2026/6085/A | E68: F-00335 OMNIA FIDUCIARIA S.R.L. | F68: Si emette fattura per asseverazioni Piano Economico e Finanziario svolte per vs conto relative ai seguenti comuni: | G68: 46231 | H68: 29 | I68: 6000 | M68: 1461125.2
B69: Bill | C69: 46231 | D69: S/2026/6080/A | E69: F-00335 OMNIA FIDUCIARIA S.R.L. | F69: Si emette fattura per asseverazioni Piano Economico e Finanziario svolte per vs conto in partenariato con A2A ILLUMINAZIONE PUBBLICA SRL | G69: 46231 | H69: 27 | I69: 500 | M69: 1461625.2
B70: Bill | C70: 46231 | D70: S/2026/6079/A | E70: F-00335 OMNIA FIDUCIARIA S.R.L. | F70: Si emette fattura per asseverazioni Piano Economico e Finanziario svolte per vs conto in partenariato con CDF SRL | G70: 46231 | H70: 28 | I70: 500 | M70: 1462125.2
B71: Bill | C71: 46233 | D71: S/2026/6126/A | E71: F-01831 TOTUM SRL | G71: 46233 | H71: FPR 11/26 | I71: 3500 | M71: 1465625.2
B72: Bill | C72: 46237 | D72: S/2026/6191/A | E72: F-03792 FIT CONSULTING S.R.L. | F72: Contratto quadro per advisor tecnico e supporto per servizi di ingegneria legati a progetti di elettrificazione del trasporto pubblico. | G72: 46233 | H72: 45 | I72: 8000 | M72: 1473625.2
B73: Bill | C73: 46237 | D73: S/2026/6157/A | E73: F-02941 MY_E_SERVICES SRLS | F73: SALDO PREVENTIVO PER ATTIVAZIONE DELLOFFERTA PER ATTIVITÀ DI CENSIMENTO IMPIANTI DI IP COMUNE DI NICHELINO TO | G73: 46224 | H73: 21 | I73: 9280 | K73: 1.Spese di consulenza | M73: 1482905.2
B74: Bill | C74: 46254 | D74: S/2026/6425/A | E74: F-00183 IMQ S.P.A. | F74: Oggetto: VARIAZIONE CERTIFICATI PER LA NORMA ISO 50001 (CERTIFICATO 9196.SLT1) | G74: 46240 | H74: 826020103 | I74: 50 | M74: 1482955.2
B75: Bill | C75: 46258 | D75: S/2026/6611/A | E75: F-04553 GEMO SERVICE SRL | G75: 46244 | H75: 22 | I75: 4000 | M75: 1486955.2
B76: Bill | C76: 46259 | D76: S/2026/6665/A | E76: F-03942 MACROAZIENDA INN. E SVIL. SRL | G76: 46234 | H76: 2254/26 | I76: 750 | M76: 1487705.2
B77: Bill | C77: 46259 | D77: S/2026/6667/A | E77: F-03942 MACROAZIENDA INN. E SVIL. SRL | G77: 46234 | H77: 2320/26 | I77: 900 | M77: 1488605.2
B78: Bill | C78: 46259 | D78: S/2026/6698/A | E78: F-04558 ALBATROS SRL | G78: 46259 | H78: FPR 28/26 | I78: 1200 | M78: 1489805.2
B79: Bill | C79: 46260 | D79: S/2026/6758/A | E79: F-01831 TOTUM SRL | G79: 46260 | H79: FPR 13/26 | I79: 3500 | M79: 1493305.2
A80: Total - 700409 - Comp. Prof. Attinenti Attivita' | I80: =SUM(I10:I79) -> 401597.31 | L80: =SUM(L10:L79) -> 0 | M80: 1493305.2
A81: Total - 7004 - Servizi Di Lavoro Parasub | I81: =SUM(I9,I80) -> 401597.31 | L81: =SUM(L9,L80) -> 0 | M81: 1493305.2
A82: Total - 70 - COSTI PER SERVIZI | I82: =SUM(I8,I81) -> 401597.31 | L82: =SUM(L8,L81) -> 0 | M82: 1493305.2

Sheet 702001
A1: CiviSmart
A2: Parent Company : CiviSmart S.p.A.
A3: CIV| Schede Contabili
A4: 1 January 2026 - 31 August 2026
A7: Account | B7: Type | C7: Date | D7: Document Number | E7: Name | F7: Memo | G7: [IL] Reference Date | H7: [IL] Reference # | I7: Debit | J7: NATURA DEL COSTO | K7: Credit | L7: Balance
A8: 70 - COSTI PER SERVIZI | L8: 0
A9: 7020 - Spese Di Consulenza | L9: 0
A10: 702001 - Spese Di Consulenza | L10: 5735855.1
B11: Bill | C11: 46044 | D11: S/2026/0505/A | E11: F-03883 GIOVANNI RONDINA | G11: 46029 | H11: 1 | I11: 6000 | L11: =L10+I11-K11 -> 5741855.1
B12: Bill | C12: 46048 | D12: S/2026/0565/A | E12: F-04138 DI BUO' GIANLUCA | G12: 46046 | H12: 1 | I12: 3122 | L12: =L11+I12-K12 -> 5744977.1
B13: Bill | C13: 46048 | D13: S/2026/0568/A | E13: F-03802 DELOITTE AND TOUCHE S.p.A. | G13: 46045 | H13: 2630001291 | I13: 16200 | J13: Financial DD | L13: =L12+I13-K13 -> 5761177.1
B14: Bill | C14: 46048 | D14: S/2026/0571/A | E14: F-01831 TOTUM SRL | G14: 46045 | H14: FPR 1/26 | I14: 3500 | L14: =L13+I14-K14 -> 5764677.1
B15: Journal | C15: 46053 | D15: JE-CIV-18128 | I15: 2600 | L15: =L14+I15-K15 -> 5767277.1
B16: Journal | C16: 46053 | D16: JE-CIV-19987 | E16: F-01657 KPMG S.p.A. | I16: 25812 | J16: Attività pre-bid | L16: =L15+I16-K16 -> 5793089.1
B17: Journal | C17: 46053 | D17: JE-CIV-21018 | I17: 3400 | L17: =L16+I17-K17 -> 5796489.1
B18: Bill | C18: 46058 | D18: S/2026/0786/A | E18: F-03883 GIOVANNI RONDINA | G18: 46056 | H18: 2 | I18: 6000 | L18: =L17+I18-K18 -> 5802489.1
B19: Bill | C19: 46063 | D19: S/2026/0867/A | E19: F-04028 Marco La Diega s.r.l. | G19: 46049 | H19: 5 | I19: 900 | J19: Servizio DPO su Regolamento Privacy | L19: =L18+I19-K19 -> 5803389.1
B20: Bill | C20: 46063 | D20: S/2026/0862/A | E20: F-03645 DOMENICO MASTROLIA | G20: 46056 | H20: 7 | I20: 9360 | J20: 2.Assistenza Legale | L20: =L19+I20-K20 -> 5812749.1
B21: Bill | C21: 46078 | D21: S/2026/1456/A | E21: F-04138 DI BUO' GIANLUCA | G21: 46077 | H21: 2 | I21: 3122 | L21: =L20+I21-K21 -> 5815871.1
B22: Journal | C22: 46081 | D22: JE-CIV-19449 | E22: F-04354 GENERA INTEGRATED SOLUTIONS SRL | I22: 28500 | J22: Consulenza e Assistenza tecnica su Spezzano e Crosia | L22: =L21+I22-K22 -> 5844371.1
B23: Journal | C23: 46081 | D23: JE-CIV-19152 | I23: 223.8 | L23: =L22+I23-K23 -> 5844594.9
B24: Journal | C24: 46081 | D24: JE-CIV-19125 | I24: 3400 | L24: =L23+I24-K24 -> 5847994.9
B25: Journal | C25: 46081 | D25: JE-CIV-19160 | I25: 2600 | L25: =L24+I25-K25 -> 5850594.9
B26: Journal | C26: 46081 | D26: JE-CIV-23357 | I26: 5595 | L26: =L25+I26-K26 -> 5856189.9
B27: Bill | C27: 46083 | D27: S/2026/1647/A | E27: F-03642 AMAPOLA SRL SB | G27: 46080 | H27: 2600049 | I27: 8000 | L27: =L26+I27-K27 -> 5864189.9
B28: Bill | C28: 46084 | D28: S/2026/1683/A | E28: F-03949 FAVACCIO CORRADO | G28: 46083 | H28: FPR 1/26 | I28: 5200 | L28: =L27+I28-K28 -> 5869389.9
B29: Bill | C29: 46091 | D29: S/2026/1763/A | E29: F-01411 ATLANTE - CERASI Studio Notarile Associato | F29: Comunicazione di nomina (opzione 1 Crosia Smart City S.r.l.) rep. 73.288 racc. 37.963 in data 9 febbraio 2026, atto in autentica Notaio Nicola ATLANTE di Roma; successivi adempimenti: (*) registrazion e c/o l Agenzia delle Entrate du Roma 5 in data 10/2/2026; (*) rilascio di una copia autentica digitale per le parti in data 10/2/2026. | G29: 46087 | H29: 408 | I29: 801.05 | J29: 2.Assistenza Legale | L29: =L28+I29-K29 -> 5870190.9
B30: Bill | C30: 46091 | D30: S/2026/1765/A | E30: F-01411 ATLANTE - CERASI Studio Notarile Associato | F30: Comunicazione di nomina (opzione 2 Città Metropolitana di Venezia II Smart City S.r.l.) rep. 73.287 racc. 37.962 in data 9 febbraio 2026, atto in autentica Notaio Nicola ATLANTE di Roma; successivi ad empimenti: (*) registrazione c/o l Agenzia delle Entrate du Roma 5 in data 10/2/2026; (*) rilascio di una copia autentica digitale per le parti in data 10/2/2026. | G30: 46087 | H30: 407 | I30: 801.05 | J30: 2.Assistenza Legale | L30: =L29+I30-K30 -> 5870992
B31: Bill | C31: 46091 | D31: S/2026/1762/A | E31: F-01411 ATLANTE - CERASI Studio Notarile Associato | F31: Comunicazione di nomina (opzione 2 Crosia Smart City S.r.l.) rep. 73.289 racc. 37.964 in data 9 febbraio 2026, atto in autentica Notaio Nicola ATLANTE di Roma; successivi adempimenti: (*) registrazion e c/o l Agenzia delle Entrate du Roma 5 in data 10/2/2026; (*) rilascio di una copia autentica digitale per le parti in data 10/2/2026. | G31: 46087 | H31: 410 | I31: 801.05 | J31: 2.Assistenza Legale | L31: =L30+I31-K31 -> 5871793
B32: Bill | C32: 46091 | D32: S/2026/1764/A | E32: F-01411 ATLANTE - CERASI Studio Notarile Associato | F32: Comunicazione di nomina (opzione 1 società Spezzano Albanese Smart City S.r.l.) rep. 73.285 racc. 37.960 in data 9 febbraio 2026, atto in autentica Notaio Nicola ATLANTE di Roma; * COPIA DOCUMENTO in bollo (certificazione di conformità della procura a rogito Notaio Donatomarco Pirro di Roma del 5/2/2026 rep. 2936 racc.1744, contenuta su supporto informatico) rep. 73.283 in data 6/2/2026; successiv i adempimenti: (*) registrazione c/o l Agenzia delle Entrate du Roma 5 in data 10/2/2026; (*) rilascio di una copia autentica digitale per le parti in data 10/2/2026. | G32: 46087 | H32: 409 | I32: 824.71 | J32: 2.Assistenza Legale | L32: =L31+I32-K32 -> 5872617.7
B33: Bill | C33: 46091 | D33: S/2026/1766/A | E33: F-01411 ATLANTE - CERASI Studio Notarile Associato | F33: Comunicazione di nomina (opzione 1 Città Metropolitana di Venezia II Smart City S.r.l.) rep. 73.286 racc. 37.961 in data 9 febbraio 2026, atto in autentica Notaio Nicola ATLANTE di Roma; successivi ad empimenti: (*) registrazione c/o l Agenzia delle Entrate du Roma 5 in data 10/2/2026; (*) rilascio di una copia autentica digitale per le parti in data 10/2/2026. | G33: 46087 | H33: 406 | I33: 801.05 | J33: 2.Assistenza Legale | L33: =L32+I33-K33 -> 5873418.8
B34: Bill | C34: 46097 | D34: S/2026/2036/A | E34: F-01657 KPMG S.p.A. Revisione e organizzazione contabile | G34: 46080 | H34: 2026102156 | I34: 4320 | J34: Attività pre-bid | L34: =L33+I34-K34 -> 5877738.8
B35: Bill | C35: 46097 | D35: S/2026/2061/A | E35: F-03883 GIOVANNI RONDINA | G35: 46090 | H35: 3 | I35: 6000 | L35: =L34+I35-K35 -> 5883738.8
B36: Bill | C36: 46100 | D36: S/2026/2304/A | E36: F-04408 BELLEMO ERNANI | G36: 46094 | H36: 29 | I36: 2163 | L36: =L35+I36-K36 -> 5885901.8
B37: Bill | C37: 46100 | D37: S/2026/2309/A | E37: F-02464 EY ADVISORY S.P.A. | G37: 46085 | H37: IT03I3B2602108 | I37: 75900 | J37: Spese di consulenza | L37: =L36+I37-K37 -> 5961801.8
B38: Bill | C38: 46105 | D38: S/2026/2398/A | E38: F-03485 KPMG Advisory S.p.A | G38: 46101 | H38: 2026302126 | I38: 15000 | J38: Spese di consulenza | L38: =L37+I38-K38 -> 5976801.8
B39: Bill | C39: 46105 | D39: S/2026/2400/A | E39: F-03857 LEXIA | F39: Oggetto Project Sunset; fase 2 - acquisizione; compensi di cui alla lettera di incarico del 16 maggio 2025. | G39: 46100 | H39: 1099 | I39: 22880 | J39: Due Diligence | L39: =L38+I39-K39 -> 5999681.8
B40: Bill | C40: 46105 | D40: S/2026/2399/A | E40: F-04405 LEXIA AVVOCATI TRIBUTARIO E FINA NZA PUBBLICA | F40: Assistenza nella notifica Goldenpower relativa all acquisizione da parte di Civismart di societ� di Samsic. RGS 5480 | G40: 46099 | H40: 1/12 | I40: 7280 | J40: Due Diligence | L40: =L39+I40-K40 -> 6006961.8
B41: Bill | C41: 46106 | D41: S/2026/2420/A | E41: F-04423 STUDIO RSNOTAI | F41: Rep. 19563 del 10/03/2026 - Raggruppamento Temporaneo di Imprese Data operazione o incasso: 23/03/2026 | G41: 46104 | H41: 832 | I41: 1197.6 | J41: 2.Assistenza Legale | L41: =L40+I41-K41 -> 6008159.4
B42: Bill | C42: 46106 | D42: S/2026/2402/A | E42: F-04138 DI BUO' GIANLUCA | G42: 46105 | H42: 3 | I42: 3122 | L42: =L41+I42-K42 -> 6011281.4
B43: Bill | C43: 46106 | D43: S/2026/2419/A | E43: F-04423 STUDIO RSNOTAI | F43: Rep. 19564 del 10/03/2026 - Raggruppamento Temporaneo di Imprese Data operazione o incasso: 23/03/2026 | G43: 46104 | H43: 831 | I43: 1197.6 | J43: 2.Assistenza Legale | L43: =L42+I43-K43 -> 6012479
B44: Bill | C44: 46107 | D44: S/2026/2436/A | E44: F-02464 EY ADVISORY S.P.A. | G44: 46106 | H44: IT03I3B2602809 | I44: 29160 | J44: Due Diligence | L44: =L43+I44-K44 -> 6041639
B45: Bill | C45: 46111 | D45: S/2026/2510/A | E45: F-01831 TOTUM SRL | G45: 46111 | H45: FPR 4/26 | I45: 3500 | L45: =L44+I45-K45 -> 6045139
B46: Journal | C46: 46112 | D46: JE-CIV-24801 | I46: 5749.64 | L46: =L45+I46-K46 -> 6050888.6
B47: Bill | C47: 46114 | D47: S/2026/2623/A | E47: F-03642 AMAPOLA SRL SB | G47: 46112 | H47: 2600076 | I47: 1850 | L47: =L46+I47-K47 -> 6052738.6
B48: Bill | C48: 46121 | D48: S/2026/2776/A | E48: F-03204 RIVOSECCHI CHIARA AVV.TO | G48: 46111 | H48: 4 | I48: 2600 | L48: =L47+I48-K48 -> 6055338.6
B49: Bill | C49: 46126 | D49: S/2026/3051/A | E49: F-03802 DELOITTE AND TOUCHE S.p.A. | G49: 46125 | H49: 2630007028 | I49: 16200 | J49: Due Diligence | L49: =L48+I49-K49 -> 6071538.6
B50: Bill | C50: 46127 | D50: S/2026/3109/A | E50: F-02464 EY ADVISORY S.P.A. | G50: 46122 | H50: IT03I3B2603451 | I50: 177100 | J50: Due Diligence | L50: =L49+I50-K50 -> 6248638.6
B51: Bill | C51: 46132 | D51: S/2026/3202/A | E51: F-03883 GIOVANNI RONDINA | G51: 46118 | H51: 4 | I51: 6000 | L51: =L50+I51-K51 -> 6254638.6
B52: Bill | C52: 46134 | D52: S/2026/3278/A | E52: F-04299 ROBERTO COLUCCI | F52: ESTRATTO AUTENTICO REP. 47288 DEL 9.4.2026 REPERTORIO: 47288/ DEL 09/04/2026 COLUCCI ROBERTO | G52: 46121 | H52: 248 | I52: 12 | J52: Spese legali | L52: =L51+I52-K52 -> 6254650.6
B53: Bill | C53: 46139 | D53: S/2026/3387/A | E53: F-04138 DI BUO' GIANLUCA | G53: 46136 | H53: 4 | I53: 3122 | L53: =L52+I53-K53 -> 6257772.6
B54: Bill | C54: 46139 | D54: S/2026/3384/A | E54: F-03949 FAVACCIO CORRADO | F54: Operazione non soggetta a ritenuta alla fonte a titolo di acconto ai sensi dell articolo 1, comma 67, l. n. 190 del 2014 e successive modificazioni | G54: 46137 | H54: FPR 12/26 | I54: 3310.29 | L54: =L53+I54-K54 -> 6261082.9
B55: Bill | C55: 46140 | D55: S/2026/3454/A | E55: F-03642 AMAPOLA SRL SB | G55: 46139 | H55: 2600093 | I55: 8000 | L55: =L54+I55-K55 -> 6269082.9
B56: Bill | C56: 46142 | D56: S/2026/3506/A | E56: F-03636 CHIOMENTI STUDIO LEGALE | G56: 46140 | H56: 2026FC-1997 | I56: 44720 | J56: Spese legali | L56: =L55+I56-K56 -> 6313802.9
B57: Bill | C57: 46147 | D57: S/2026/3644/A | E57: F-02464 EY ADVISORY S.P.A. | G57: 46147 | H57: IT03I3B2604266 | I57: 29160 | J57: Due Diligence | L57: =L56+I57-K57 -> 6342962.9
B58: Bill Credit | C58: 46147 | D58: S/2026/3651/A | E58: F-03636 CHIOMENTI STUDIO LEGALE | G58: 46146 | H58: 2026NC-0071 | K58: 44720 | L58: =L57+I58-K58 -> 6298242.9
B59: Bill | C59: 46148 | D59: S/2026/3671/A | E59: F-03645 DOMENICO MASTROLIA | F59: da non pagare | G59: 46146 | H59: 25 | I59: 9360 | L59: =L58+I59-K59 -> 6307602.9
B60: Bill | C60: 46161 | D60: S/2026/4148/A | E60: F-01411 ATLANTE - CERASI Studio Notarile Associato | F60: ATTIVITA SVOLTA DAL NOTAIO NICOLA ATLANTE DI ROMA (*) consulenza per tutta l operazione e assistenza pre e post atto notarile, conferenze e colloqui telefonici, mail; (*) predisposizione, redazione e revisione minute; (*) redazione atto; (*) stipula atto; (*) esecuzione di visure camerali pre stipula. - VERBALE DI ASSEMBLEA DI S.p.A. (modifica degli articoli 3 e 6 dello statuto sociale senza c ontenuto patrimoniale) rep. 73.676 racc. 38.161 in data 30 aprile 2026; - adempimenti successivi: (*) registrazione c/o l Agenzia delle Entrate di Roma 5; (*) deposito in data 4/5/2026 e successiva is crizione c/o il Registro delle Imprese di Milano; (*) rilascio di 1 copia autentica digitale per la società. | G60: 46160 | H60: 885 | I60: 4002.05 | J60: Spese legali | L60: =L59+I60-K60 -> 6311605
B61: Bill | C61: 46163 | D61: S/2026/4195/A | E61: F-03485 KPMG Advisory S.p.A | G61: 46157 | H61: 2026304276 | I61: 27000 | J61: Due Diligence | L61: =L60+I61-K61 -> 6338605
B62: Bill | C62: 46164 | D62: S/2026/4239/A | E62: F-03949 FAVACCIO CORRADO | F62: Operazione non soggetta a ritenuta alla fonte a titolo di acconto ai sensi dell articolo 1, comma 67, l. n. 190 del 2014 e successive modificazioni | G62: 46164 | H62: FPR 15/26 | I62: 5200 | L62: =L61+I62-K62 -> 6343805
B63: Bill | C63: 46167 | D63: S/2026/4265/A | E63: F-02464 EY ADVISORY S.P.A. | F63: - - | G63: 46161 | H63: IT03I3B2604805 | I63: 29330 | J63: Due Diligence | L63: =L62+I63-K63 -> 6373135
B64: Bill | C64: 46167 | D64: S/2026/4263/A | E64: F-04508 PRAXI SPA | G64: 46157 | H64: 1863/T | I64: 45000 | J64: Due Diligence | L64: =L63+I64-K64 -> 6418135
B65: Bill | C65: 46171 | D65: S/2026/4358/A | E65: F-03642 AMAPOLA SRL SB | G65: 46169 | H65: 2600130 | I65: 4125 | L65: =L64+I65-K65 -> 6422260
B66: Journal | C66: 46173 | D66: JE-CIV-23867 | I66: 6000 | L66: =L65+I66-K66 -> 6428260
B67: Journal | C67: 46173 | D67: JE-CIV-23868 | I67: 60641.6 | J67: Due Diligence | L67: =L66+I67-K67 -> 6488901.6
B68: Journal | C68: 46173 | D68: JE-CIV-23869 | I68: 552 | L68: =L67+I68-K68 -> 6489453.6
B69: Bill | C69: 46177 | D69: S/2026/4484/A | E69: F-03883 GIOVANNI RONDINA | G69: 46177 | H69: 6 | I69: 6000 | L69: =L68+I69-K69 -> 6495453.6
B70: Bill | C70: 46177 | D70: S/2026/4475/A | E70: F-04405 LEXIA AVVOCATI TRIBUTARIO E FINA NZA PUBBLICA | F70: Acc comp profesle nel ricorso contro il Comune di Porto San Giorgio e di SGDS Multiservizi S.r.l. - TAR Marche, sez. II, r.g. n. 284/2026 - fase cautelare (cc 07/4 - 7/5/26) rgs 5481 | G70: 46176 | H70: 1/52 | I70: 12558 | J70: Due Diligence | L70: =L69+I70-K70 -> 6508011.6
B71: Bill | C71: 46182 | D71: S/2026/4636/A | E71: F-01411 ATLANTE - CERASI Studio Notarile Associato | F71: Attività svolta dal Nicola ATLANTE di Roma: - PROCURA in bollo (a Vito Telesca per vendere terreno sito nel Comune di Pietragalla (PZ), ubicato nella zona PIP, di circa mq. 4.517) rep. 73.782 in data 22 maggio 2026; (*) visura camerale pre stipula; (*) verifica poteri; (*) predisposizione, redazione minuta; (*) stipula; (*) autentica di firma; (*) anticipo di una copia PDF per email alla società; (*) rilascio di una copia digitale al Notaio Francesco Zotta; (*) rilascio originale alla società. | G71: 46182 | H71: 967 | I71: 149.85 | J71: Spese legali | L71: =L70+I71-K71 -> 6508161.4
B72: Bill | C72: 46184 | D72: S/2026/4692/A | E72: F-03954 STELLA NAPOLEONE | F72: Operazione effettuata ai sensi dell articolo 1, commi da 54 a 89, della Legge n. 190-2014 così come modificato dalla Legge numero 208-2015. Imposta di bollo da 2 euro assolta sull originale per importi maggiori di 77,47 euro | G72: 46184 | H72: 10/2026 | I72: 4680 | L72: =L71+I72-K72 -> 6512841.4
B73: Bill | C73: 46184 | D73: S/2026/4676/A | E73: F-04028 Marco La Diega s.r.l. | G73: 46183 | H73: 155 | I73: 1400 | L73: =L72+I73-K73 -> 6514241.4
B74: Bill | C74: 46189 | D74: S/2026/4979/A | E74: F-01411 ATLANTE - CERASI Studio Notarile Associato | F74: ATTIVITA SVOLTA DAL NOTAIO NICOLA ATLANTE DI ROMA (*) assistenza pre e post atto notarile, conferenze e colloqui telefonici, mail; (*) redazione, revisione e correzione minuta; (*) verifica poteri di firma delle parti; (*) stipula atto; (*) esecuzione di visure camerali pre e post stipula. - ATTO DI CESSIONE DI QUOTE DI S.R.L. (SOFEIN S.P.A. cede a CIVISMART S.p.A. la quota di nominali euro 6. 750,00 della CROSIA SMART CITY SOCIETA A RESPONSABILITA LIMITATA , per il prezzo di euro 6.750,00) rep. 73.806 racc. 38.215 in data 11 giugno 2026; * COPIA DOCUMENTO (certificazione di conformità d ella procura in autentica Notaio Federico Occelli di Pinerolo del giorno 9/6/2026 rep. 15157, contenuta su supporto informatico) rep. 73.790 del 10/6/2026; - adempimenti successivi: (*) registrazione c/o l Agenzia delle Entrate di Roma 5; (*) deposito cessione e successiva iscrizione c/o il Registro delle Imprese di Imprese di Milano; (*) rilascio di una copia digitale per le parti. | G74: 46185 | H74: 1016 | I74: 2478.75 | J74: Spese legali | L74: =L73+I74-K74 -> 6516720.2
B75: Bill | C75: 46189 | D75: S/2026/4980/A | E75: F-01411 ATLANTE - CERASI Studio Notarile Associato | F75: Attività svolta dal Nicola ATLANTE di Roma: - PROCURA in bollo (a Giacomo Ferdinando ZENNARO, Bruno Edoardo MARSEGLIA e Carla NUZZOLO per stipulare il contratto di risoluzione parziale per mutuo disse nso dell atto di cessione di ramo d azienda autenticato nelle firme dal Notaio Lorenzo Colizzi di Milano il 23 dicembre 2024 rep. 12.749 racc. 5.544) rep. 73.807 in data 11 giugno 2026; (*) visura ca merale pre stipula; (*) verifica poteri; (*) predisposizione, redazione minuta; (*) stipula; (*) autentica di firma; (*) anticipo di una copia digitale per email alla società; (*) rilascio di una copi a digitale al Notaio Lorenzo Colizzi. (*) rilascio originale alla società. | G75: 46185 | H75: 1015 | I75: 146.85 | J75: Spese legali | L75: =L74+I75-K75 -> 6516867
B76: Bill | C76: 46192 | D76: S/2026/5058/A | E76: F-04345 PwC Legal STA Srl | F76: Assistenza legale societaria in relazione alla cessazione del rapporto di lavoro con un dipendente come da lettera di incarico del 4 marzo 2026. Spese pari al 6 del corrispettivo complessivo come da lettera di incarico. | G76: 46191 | H76: 6101001069 | I76: 22048 | J76: Spese legali | L76: =L75+I76-K76 -> 6538915
B77: Bill | C77: 46195 | D77: S/2026/5087/A | E77: F-00440 NICODEMO GIOVANNI FRANCESCO | G77: 46195 | H77: 33 | I77: 1040 | L77: =L76+I77-K77 -> 6539955
B78: Bill | C78: 46196 | D78: S/2026/5110/A | E78: F-01411 ATLANTE - CERASI Studio Notarile Associato | F78: ATTIVITA SVOLTA DAL NOTAIO NICOLA ATLANTE DI ROMA (*) assistenza pre e post atto notarile, conferenze e colloqui telefonici, mail; (*) redazione, revisione e correzione minuta; (*) verifica poteri di firma delle parti; (*) stipula atto; (*) esecuzione di visure camerali pre e post stipula. - ATTO DI CESSIONE DI QUOTE DI S.R.L. (CYNERGI S.R.L. cede a CIVISMART S.p.A. la quota di nominali euro 2 .250,00 della CROSIA SMART CITY SOCIETA A RESPONSABILITA LIMITATA , per il prezzo di euro 2.250,00 (prima firma su due)) rep. 73.808 in data 11 giugno 2026; - a completamento precedente repertorio, raccolta ultima firma rep. 73.847 racc. 38.231 in data 18 giugno 2026; - adempimenti successivi: (*) registrazione c/o l Agenzia delle Entrate di Roma 5; (*) deposito cessione e successiva iscrizione c/o il Registro delle Imprese di Imprese di Milano; (*) rilascio di una copia digitale per le parti. | G78: 46195 | H78: 1061 | I78: 2473.09 | J78: Spese legali | L78: =L77+I78-K78 -> 6542428.1
B79: Bill | C79: 46197 | D79: S/2026/5125/A | E79: F-04138 DI BUO' GIANLUCA | G79: 46197 | H79: 7 | I79: 3122 | L79: =L78+I79-K79 -> 6545550.1
B80: Bill | C80: 46197 | D80: S/2026/5128/A | E80: F-04192 ETA Ingegneria S.r.l. | G80: 46172 | H80: 00 / 0000237 | I80: 2496 | L80: =L79+I80-K80 -> 6548046.1
B81: Bill | C81: 46198 | D81: S/2026/5170/A | E81: F-04405 LEXIA AVVOCATI TRIBUTARIO E FINA NZA PUBBLICA | F81: Compenso profle per appello dinanzi al C.D.S., sez. V, r.g. n. 4435/2026 avverso sent Tar Marche n 122/26 - def con ordin n 2242/2026 Com Porto S Giorgio - SGDS srl - rgs 5563 | G81: 46198 | H81: 1/58 | I81: 9568 | J81: Due Diligence | L81: =L80+I81-K81 -> 6557614.1
B82: Bill | C82: 46199 | D82: S/2026/5179/A | E82: F-04562 E.A.M. S.R.L. | F82: Consulenza | G82: 46199 | H82: 3 | I82: 50000 | J82: Due Diligence | L82: =L81+I82-K82 -> 6607614.1
B83: Journal | C83: 46203 | D83: JE-CIV-25637 | I83: 43600 | J83: Due Diligence | L83: =L82+I83-K83 -> 6651214.1
B84: Journal | C84: 46203 | D84: JE-CIV-25478 | I84: 5800 | L84: =L83+I84-K84 -> 6657014.1
B85: Journal | C85: 46203 | D85: JE-CIV-25484 | E85: F-01657 KPMG S.p.A. Revisione e organizzazione contabile | I85: 43600 | J85: Due Diligence | L85: =L84+I85-K85 -> 6700614.1
B86: Journal | C86: 46203 | D86: JE-CIV-25487 | I86: 220 | L86: =L85+I86-K86 -> 6700834.1
B87: Bill | C87: 46203 | D87: S/2026/5245/A | E87: F-04028 Marco La Diega s.r.l. | G87: 46203 | H87: 174 | I87: 1400 | L87: =L86+I87-K87 -> 6702234.1
B88: Bill | C88: 46203 | D88: S/2026/5246/A | E88: F-01657 KPMG S.p.A. Revisione e organizzazione contabile | F88: Predisposizione di Linee Guida perl identificazione e il trattamento contabile delle operazioni in ambito IFRS 3 | G88: 46195 | H88: 2026107827 | I88: 5000 | L88: =L87+I88-K88 -> 6707234.1
B89: Bill | C89: 46209 | D89: S/2026/5349/A | E89: F-03883 GIOVANNI RONDINA | G89: 46206 | H89: 7 | I89: 6000 | L89: =L88+I89-K89 -> 6713234.1
B90: Bill | C90: 46209 | D90: S/2026/5370/A | E90: F-03802 DELOITTE AND TOUCHE S.p.A. | G90: 46206 | H90: 2630012903 | I90: 20450 | J90: attività di Financial e Tax DD | L90: =L89+I90-K90 -> 6733684.1
B91: Bill | C91: 46211 | D91: S/2026/5454/A | E91: F-03942 MACROAZIENDA INN. E SVIL. SRL | G91: 46203 | H91: 1932/26 | I91: 750 | L91: =L90+I91-K91 -> 6734434.1
B92: Bill | C92: 46213 | D92: S/2026/5509/A | E92: F-04587 LUCIBELLO ASSOCIATI STUDIO LEGALE | F92: Modello di organizzazione, gestione e controllo Redazione della Procedura di Whistleblowing | G92: 46211 | H92: 231/001 | I92: 8320 | J92: Spese di consulenza | L92: =L91+I92-K92 -> 6742754.1
B93: Bill | C93: 46216 | D93: S/2026/5665/A | E93: F-01411 ATLANTE - CERASI Studio Notarile Associato | F93: Attività svolta dal Nicola ATLANTE di Roma: - PROCURA in bollo (a Marco Marippi per sottoscrivere con il Comune di Spotorno il CONTRATTO ATTUATIVO DI CONCESSIONE DI SERVIZI AVENTE AD OGGETTO I SERVIZI DI PRESTAZIONE ENERGETICA, INCLUSI LA RIQUALIFICAZIONE ENERGETICA E LA GESTIONE DELL IMPIANTO DI PUBBLICA ILLUMINAZIONE, CON LA PREDISPOSIZIONE DELLO STESSO AI SERVIZI SMART CITY) rep. 73.934 in data 8 luglio 2026; (*) visura camerale pre stipula; (*) verifica poteri; (*) predisposizione, redazione minuta; (*) stipula; (*) anticipo di una copia PDF per email alla società; (*) rilascio di una cop ia digitale per il comune di Spotorno; (*) rilascio originale alla società. | G93: 46213 | H93: 1187 | I93: 146.85 | J93: Spese legali | L93: =L92+I93-K93 -> 6742901
B94: Bill | C94: 46216 | D94: S/2026/5666/A | E94: F-01411 ATLANTE - CERASI Studio Notarile Associato | F94: Attività svolta dal Nicola ATLANTE di Roma: - PROCURA in bollo (a Pietro SANFILIPPO per sottoscrivere con ROSSI contratto definitivo di costituzione diritto di superficie e servitù su terreni in Scurc ola Marsicana) rep. 73.935 in data 8 luglio 2026; (*) visura camerale pre stipula; (*) verifica poteri; (*) predisposizione, redazione minuta; (*) stipula; (*) autentica di firma; (*) anticipo di una copia PDF per email alla società; (*) rilascio originale alla società. | G94: 46213 | H94: 1186 | I94: 149.85 | J94: Spese legali | L94: =L93+I94-K94 -> 6743050.8
B95: Bill | C95: 46223 | D95: S/2026/5916/A | E95: F-04593 OSBORNE CLARKE STUDIO LEGALE | G95: 46216 | H95: 2026000002070-F | I95: 9360 | J95: Spese legali | L95: =L94+I95-K95 -> 6752410.8
B96: Bill | C96: 46223 | D96: S/2026/5915/A | E96: F-04601 ISABELLA MARTINELLO | F96: Atlantic 1 S.r.l. Campello S.p.a. consulenza e assistenza conciliazione stragiudiziale 18.6.2025 | G96: 46216 | H96: 44 | I96: 2450.39 | J96: Spese legali | L96: =L95+I96-K96 -> 6754861.2
B97: Bill | C97: 46225 | D97: S/2026/5975/A | E97: F-04612 PAOLO MORELLI | F97: ATTO DI TRASFERIMENTO QUOTA rep 154.915 del 13/07/2026 | G97: 46223 | H97: 642 | I97: 3838.46 | L97: =L96+I97-K97 -> 6758699.7
B98: Bill | C98: 46225 | D98: S/2026/5976/A | E98: F-04612 PAOLO MORELLI | F98: ATTO DI TRASFERIMENTO QUOTA rep 154.916 del 13/07/2026 | G98: 46223 | H98: 643 | I98: 1581.87 | L98: =L97+I98-K98 -> 6760281.5
B99: Bill | C99: 46225 | D99: S/2026/5974/A | E99: F-04612 PAOLO MORELLI | F99: ATTO DI TRASFERIMENTO QUOTA rep 154.914 del 13/07/2026 | G99: 46223 | H99: 641 | I99: 2954.35 | L99: =L98+I99-K99 -> 6763235.9
B100: Bill | C100: 46227 | D100: S/2026/6016/A | E100: F-04138 DI BUO' GIANLUCA | G100: 46227 | H100: 8 | I100: 3122 | L100: =L99+I100-K100 -> 6766357.9
B101: Bill | C101: 46227 | D101: S/2026/6010/A | E101: F-03485 KPMG Advisory S.p.A | F101: Fees previste da EL più 8 spese | G101: 46224 | H101: 2026306844 | I101: 37800 | J101: Fees previste da EL più 8 spese | L101: =L100+I101-K101 -> 6804157.9
B102: Journal | C102: 46230 | D102: JE-CIV-27009 | I102: 250 | L102: =L101+I102-K102 -> 6804407.9
...

Sheet 700815
A1: CiviSmart
A2: Parent Company : CiviSmart S.p.A.
A3: CIV| Schede Contabili
A4: 1 January 2026 - 31 August 2026
A7: Account | B7: Type | C7: Date | D7: Document Number | E7: Name | F7: Memo | G7: [IL] Reference Date | H7: [IL] Reference # | I7: Debit | J7: NATURA DEL COSTO | K7: Credit | L7: Balance
A8: 70 - COSTI PER SERVIZI | L8: 0
A9: 7008 - Spese Generali | L9: 0
A10: 700815 - Spese Per Trasferte | L10: 249262.19
B11: Journal | C11: 46023 | D11: JE-CIV-18652 | I11: 3 | L11: =L10+I11-K11 -> 249265.19
B12: Journal | C12: 46024 | D12: JE-CIV-18653 | I12: 9.5 | L12: =L11+I12-K12 -> 249274.69
B13: Journal | C13: 46024 | D13: JE-CIV-18654 | I13: 2.9 | L13: =L12+I13-K13 -> 249277.59
B14: Journal | C14: 46027 | D14: JE-CIV-18661 | I14: 20.8 | L14: =L13+I14-K14 -> 249298.39
B15: Journal | C15: 46029 | D15: JE-CIV-18460 | I15: 12 | L15: =L14+I15-K15 -> 249310.39
B16: Journal | C16: 46029 | D16: JE-CIV-18672 | I16: 42 | L16: =L15+I16-K16 -> 249352.39
B17: Journal | C17: 46029 | D17: JE-CIV-18337 | I17: 2 | L17: =L16+I17-K17 -> 249354.39
B18: Journal | C18: 46029 | D18: JE-CIV-18497 | I18: 6 | L18: =L17+I18-K18 -> 249360.39
B19: Journal | C19: 46030 | D19: JE-CIV-18499 | I19: 2.2 | L19: =L18+I19-K19 -> 249362.59
B20: Journal | C20: 46030 | D20: JE-CIV-18586 | I20: 13.9 | L20: =L19+I20-K20 -> 249376.49
B21: Journal | C21: 46030 | D21: JE-CIV-18461 | I21: 4.1 | L21: =L20+I21-K21 -> 249380.59
B22: Journal | C22: 46031 | D22: JE-CIV-18587 | I22: 16.5 | L22: =L21+I22-K22 -> 249397.09
... B49: Journal | C49: 46038 | D49: JE-CIV-18462 | I49: 4.9 | L49: =L48+I49-K49 -> 250216.07
B50: Journal | C50: 46038 | D50: JE-CIV-18525 | E50: Trenitalia SpA | I50: 899 | J50: Spese per trasferta | L50: =L49+I50-K50 -> 251115.07
B51: Journal | C51: 46039 | D51: JE-CIV-18691 | I51: 55 | L51: =L50+I51-K51 -> 251170.07
B52: Journal | C52: 46039 | D52: JE-CIV-18697 | I52: 143.11 | L52: =L51+I52-K52 -> 251313.18
B53: Journal | C53: 46040 | D53: JE-CIV-18702 | I53: 19.16 | L53: =L52+I53-K53 -> 251332.34
B54: Journal | C54: 46041 | D54: JE-CIV-18597 | I54: 20.6 | L54: =L53+I54-K54 -> 251352.94
B55: Journal | C55: 46041 | D55: JE-CIV-18501 | I55: 8 | L55: =L54+I55-K55 -> 251360.94
B56: Journal | C56: 46041 | D56: JE-CIV-18527 | I56: 18.1 | L56: =L55+I56-K56 -> 251379.04
B57: Journal | C57: 46041 | D57: JE-CIV-18591 | I57: 7 | L57: =L56+I57-K57 -> 251386.04
B58: Journal | C58: 46041 | D58: JE-CIV-18395 | I58: 6.46 | L58: =L57+I58-K58 -> 251392.5
B59: Journal | C59: 46041 | D59: JE-CIV-18529 | I59: 2.2 | L59: =L58+I59-K59 -> 251394.7
B60: Journal | C60: 46042 | D60: JE-CIV-18358 | I60: 32.26 | L60: =L59+I60-K60 -> 251426.96
B61: Journal | C61: 46042 | D61: JE-CIV-18502 | I61: 23.2 | L61: =L60+I61-K61 -> 251450.16
B62: Journal | C62: 46042 | D62: JE-CIV-18503 | I62: 4.4 | L62: =L61+I62-K62 -> 251454.56
... B67: Journal | C67: 46043 | D67: JE-CIV-18390 | I67: 9.66 | L67: =L66+I67-K67 -> 251511.32
B68: Bill | C68: 46043 | D68: S/2026/0433/A | E68: F-00093 Trenitalia S.p.A | G68: 46041 | H68: 2026/9000149832 | I68: 126 | L68: =L67+I68-K68 -> 251637.32
B69: Journal | C69: 46043 | D69: JE-CIV-18601 | I69: 40 | L69: =L68+I69-K69 -> 251677.32
B70: Bill | C70: 46043 | D70: S/2026/0437/A | E70: F-04313 J24HOTEL SRL | F70: Hotel J24 Lo Re | G70: 46036 | H70: 12600600J | I70: 112.19 | L70: =L69+I70-K70 -> 251789.51
B71: Journal | C71: 46043 | D71: JE-CIV-18504 | I71: 5.4 | L71: =L70+I71-K71 -> 251794.91
B72: Bill Credit | C72: 46043 | D72: S/2026/0422/A | E72: F-00093 Trenitalia S.p.A | G72: 46035 | H72: 2026/9000084602 | K72: 77 | L72: =L71+I72-K72 -> 251717.91
B73: Bill | C73: 46043 | D73: S/2026/0435/A | E73: F-04253 HOTEL B SRL | G73: 46034 | H73: 13/H | I73: 51.2 | L73: =L72+I73-K73 -> 251769.11
B74: Journal | C74: 46043 | D74: JE-CIV-18532 | I74: 125.1 | L74: =L73+I74-K74 -> 251894.21
B75: Journal | C75: 46043 | D75: JE-CIV-18531 | I75: 12 | L75: =L74+I75-K75 -> 251906.21
B76: Journal | C76: 46043 | D76: JE-CIV-18533 | I76: 40.6 | L76: =L75+I76-K76 -> 251946.81
B77: Bill | C77: 46043 | D77: S/2026/0421/A | E77: F-00093 Trenitalia S.p.A | G77: 46035 | H77: 2026/9000084603 | I77: 86 | L77: =L76+I77-K77 -> 252032.81
B78: Bill | C78: 46043 | D78: S/2026/0436/A | E78: F-04313 J24HOTEL SRL | F78: Hotel J24 Penazzo | G78: 46035 | H78: 12600537J | I78: 163.56 | L78: =L77+I78-K78 -> 252196.37
B79: Bill | C79: 46043 | D79: S/2026/0424/A | E79: F-00093 Trenitalia S.p.A | G79: 46035 | H79: 2026/9000092794 | I79: 86 | L79: =L78+I79-K79 -> 252282.37
B80: Bill | C80: 46043 | D80: S/2026/0447/A | E80: F-01087 UNIPOLTECH SPA | F80: IMPORTO ORIGINALE FATTURA: 0.00 IMPORTO CREDITO: 0.00 | G80: 46038 | H80: 1U717/ZE/901746639 | I80: 4 | L80: =L79+I80-K80 -> 252286.37
B81: Bill | C81: 46043 | D81: S/2026/0441/A | E81: F-04264 COMUNE DI VENEZIA | F81: Fattura già quietanzata - Sosta su strada a pagamento | G81: 46029 | H81: LP/RBPO/000035 | I81: 0.64 | L81: =L80+I81-K81 -> 252287.01
B82: Journal | C82: 46043 | D82: JE-CIV-18600 | I82: 8.5 | L82: =L81+I82-K82 -> 252295.51
B83: Journal | C83: 46043 | D83: JE-CIV-18534 | I83: 74.8 | L83: =L82+I83-K83 -> 252370.31
B84: Journal | C84: 46043 | D84: JE-CIV-18394 | I84: 2.4 | L84: =L83+I84-K84 -> 252372.71
B85: Bill Credit | C85: 46043 | D85: S/2026/0423/A | E85: F-00093 Trenitalia S.p.A | G85: 46035 | H85: 2026/9000092793 | K85: 86 | L85: =L84+I85-K85 -> 252286.71
B86: Bill | C86: 46043 | D86: S/2026/0438/A | E86: F-03834 OLIMPIA HOTEL SRL | G86: 46038 | H86: 48 | I86: 2048.18 | L86: =L85+I86-K86 -> 254334.89
B87: Bill | C87: 46043 | D87: S/2026/0434/A | E87: F-03533 HOTEL INTERNATIONAL SOC. COP | G87: 46031 | H87: 50 | I87: 46.54 | L87: =L86+I87-K87 -> 254381.43
B88: Bill | C88: 46043 | D88: S/2026/0420/A | E88: F-00093 Trenitalia S.p.A | G88: 46034 | H88: 2026/9000078037 | I88: 147 | L88: =L87+I88-K88 -> 254528.43
B89: Bill | C89: 46044 | D89: S/2026/0463/A | E89: F-04327 LUCA AUROLIA | F89: Fattura di vendita | G89: 46042 | H89: 2 | I89: 102 | L89: =L88+I89-K89 -> 254630.43
B90: Journal | C90: 46044 | D90: JE-CIV-18391 | I90: 3 | L90: =L89+I90-K90 -> 254633.43
B91: Journal | C91: 46044 | D91: JE-CIV-18392 | I91: 2.5 | L91: =L90+I91-K91 -> 254635.93
B92: Journal | C92: 46044 | D92: JE-CIV-18831 | I92: 8.4 | L92: =L91+I92-K92 -> 254644.33
B93: Journal | C93: 46044 | D93: JE-CIV-18830 | I93: 3 | L93: =L92+I93-K93 -> 254647.33
B94: Journal | C94: 46045 | D94: JE-CIV-18507 | I94: 7.4 | L94: =L93+I94-K94 -> 254654.73
B95: Bill | C95: 46045 | D95: S/2026/0518/A | E95: F-00757 RYANAIR LIMITED | G95: 46036 | H95: 18435-2026/F | I95: 105.58 | L95: =L94+I95-K95 -> 254760.31
B96: Journal | C96: 46045 | D96: JE-CIV-18347 | I96: 343.61 | L96: =L95+I96-K96 -> 255103.92
B97: Bill | C97: 46045 | D97: S/2026/0525/A | E97: F-03020 PARCHEGGI ITALIA SPA | F97: Codice cliente: 310991905 | G97: 46045 | H97: 000000236000194P | I97: 19.34 | L97: =L96+I97-K97 -> 255123.26
B98: Bill | C98: 46045 | D98: S/2026/0521/A | E98: F-00093 Trenitalia S.p.A | G98: 46042 | H98: 2026/9000157200 | I98: 217.8 | L98: =L97+I98-K98 -> 255341.06
B99: Bill | C99: 46045 | D99: S/2026/0539/A | E99: F-03952 Societa Servizi Territoriali spa | G99: 46043 | H99: Y25 | I99: 4.04 | L99: =L98+I99-K99 -> 255345.1
B100: Journal | C100: 46045 | D100: JE-CIV-18360 | I100: 261.76 | L100: =L99+I100-K100 -> 255606.86
B101: Bill | C101: 46045 | D101: S/2026/0541/A | E101: F-00060 LA PRIMULA S.R.L. | G101: 46045 | H101: E154 | I101: 375.27 | J101: Soggiorno Federico Mazzotta | L101: =L100+I101-K101 -> 255982.13
B102: Bill | C102: 46045 | D102: S/2026/0531/A | E102: F-01582 APCOA PARKING ITALIA SPA | F102: Codice cliente: 310991905 | G102: 46045 | H102: 000000020000843P | I102: 4.64 | L102: =L101+I102-K102 -> 255986.77
B103: Bill | C103: 46045 | D103: S/2026/0527/A | E103: F-03020 PARCHEGGI ITALIA SPA | F103: Codice cliente: 310991905 | G103: 46045 | H103: 000000634000311P | I103: 11.07 | L103: =L102+I103-K103 -> 255997.84
B104: Bill | C104: 46045 | D104: S/2026/0526/A | E104: F-03020 PARCHEGGI ITALIA SPA | F104: Codice cliente: 310991905 | G104: 46045 | H104: 000000156000496P | I104: 9.43 | L104: =L103+I104-K104 -> 256007.27
B105: Journal | C105: 46045 | D105: JE-CIV-18505 | I105: 26.8 | L105: =L104+I105-K105 -> 256034.07
B106: Journal | C106: 46045 | D106: JE-CIV-18386 | I106: 6.55 | L106: =L105+I106-K106 -> 256040.62
B107: Bill | C107: 46045 | D107: S/2026/0540/A | E107: F-00060 LA PRIMULA S.R.L. | G107: 46045 | H107: E155 | I107: 373.45 | J107: Soggiorno Marco Bordini | L107: =L106+I107-K107 -> 256414.07
B108: Bill | C108: 46045 | D108: S/2026/0522/A | E108: F-00093 Trenitalia S.p.A | G108: 46042 | H108: 2026/9000157127 | I108: 221.8 | L108: =L107+I108-K108 -> 256635.87
B109: Bill | C109: 46045 | D109: S/2026/0535/A | E109: F-00069 TELEPASS S.P.A. | F109: Codice cliente: 310991905 | G109: 46045 | H109: 0000000000149415 | I109: 110.63 | L109: =L108+I109-K109 -> 256746.5
B110: Bill | C110: 46045 | D110: S/2026/0533/A | E110: F-01582 APCOA PARKING ITALIA SPA | F110: Codice cliente: 310991905 | G110: 46045 | H110: 000000172001209P | I110: 16.7 | L110: =L109+I110-K110 -> 256763.2
B111: Journal | C111: 46046 | D111: JE-CIV-18706 | I111: 15 | L111: =L110+I111-K111 -> 256778.2
B112: Journal | C112: 46046 | D112: JE-CIV-18348 | I112: 4.4 | L112: =L111+I112-K112 -> 256782.6
B113: Journal | C113: 46046 | D113: JE-CIV-18707 | I113: 18 | L113: =L112+I113-K113 -> 256800.6
B114: Journal | C114: 46048 | D114: JE-CIV-18538 | I114: 38 | L114: =L113+I114-K114 -> 256838.6
B115: Journal | C115: 46048 | D115: JE-CIV-18362 | I115: 24.6 | L115: =L114+I115-K115 -> 256863.2
B116: Bill | C116: 46048 | D116: S/2026/0582/A | E116: F-04314 IPPAZIO CAPUTO | F116: N°01 Pernottamento effeffuato per Vs. conto Arrivo 14/01/2026 Partenza 15/01/2026 Ospite Sig:Amoroso Riccardo | G116: 46037 | H116: FPR 12/26 | I116: 100 | L116: =L115+I116-K116 -> 256963.2
B117: Journal | C117: 46048 | D117: JE-CIV-18489 | I117: 12.4 | L117: =L116+I117-K117 -> 256975.6
B118: Journal | C118: 46048 | D118: JE-CIV-18387 | I118: 7.02 | L118: =L117+I118-K118 -> 256982.62
B119: Journal | C119: 46048 | D119: JE-CIV-18539 | I119: 2.2 | L119: =L118+I119-K119 -> 256984.82
B120: Journal | C120: 46048 | D120: JE-CIV-18711 | I120: 15.29 | L120: =L119+I120-K120 -> 257000.11
B121: Bill | C121: 46048 | D121: S/2026/0570/A | E121: F-00093 Trenitalia S.p.A | G121: 46045 | H121: 2026/9000201187 | I121: 118 | L121: =L120+I121-K121 -> 257118.11
B122: Journal | C122: 46048 | D122: JE-CIV-18487 | I122: 0.86 | L122: =L121+I122-K122 -> 257118.97
B123: Journal | C123: 46048 | D123: JE-CIV-18537 | I123: 8.3 | L123: =L122+I123-K123 -> 257127.27
B124: Journal | C124: 46048 | D124: JE-CIV-18488 | I124: 10.8 | L124: =L123+I124-K124 -> 257138.07
B125: Bill | C125: 46048 | D125: S/2026/0592/A | E125: F-03908 AEROITALIA S.R.L. | G125: 46038 | H125: NA00007480 | I125: 309.98 | J125: Volo Linate Foggia | L125: =L124+I125-K125 -> 257448.05
B126: Journal | C126: 46049 | D126: JE-CIV-18712 | I126: 41.2 | L126: =L125+I126-K126 -> 257489.25
B127: Journal | C127: 46049 | D127: JE-CIV-18713 | I127: 3.9 | L127: =L126+I127-K127 -> 257493.15
B128: Journal | C128: 46049 | D128: JE-CIV-18363 | I128: 20 | L128: =L127+I128-K128 -> 257513.15
B129: Journal | C129: 46049 | D129: JE-CIV-18508 | I129: 19.95 | L129: =L128+I129-K129 -> 257533.1
B130: Bill | C130: 46049 | D130: S/2026/0631/A | E130: F-01582 APCOA PARKING ITALIA SPA | F130: Codice cliente: 310720217 | G130: 46045 | H130: 000000048000232P | I130: 1.86 | L130: =L129+I130-K130 -> 257534.96
B131: Bill | C131: 46049 | D131: S/2026/0626/A | E131: F-00069 TELEPASS S.P.A. | F131: Codice cliente: 310720217 | G131: 46045 | H131: 0000000000102945 | I131: 34.43 | L131: =L130+I131-K131 -> 257569.39
B132: Journal | C132: 46050 | D132: JE-CIV-18490 | I132: 10.9 | L132: =L131+I132-K132 -> 257580.29
...
